Workbook

Sheet ConsolidadoLoa27_ATIVIDADES
A1: secretaria | B1: unidade | C1: funcao | D1: subfuncao | E1: programa | F1: acao | G1: natureza | H1: Programática_LOA | I1: secretaria | J1: unidade | K1: funcao | L1: subfuncao | M1: programa | N1: acao | O1: natureza | P1: desc_sub | Q1: processo | R1: valor | S1: Peça Orçamentária
A2: 02 | B2: 001 | C2: 04 | D2: 122 | E2: 0001 | F2: 2.011 | G2: 3.3.90.30.00 | H2: =_xlfn.CONCAT(A2,".",B2,".",C2,".",D2,".",E2,".",F2,".",G2) -> 02.001.04.122.0001.2.011.3.3.90.30.00 | I2: 02 - GABINETE DO PREFEITO | J2: 001-CHEFIA DE GABINETE | K2: 4-ADMINISTRAÇÃO | L2: 122-ADMINISTRAÇÃO GERAL | M2: 0001-Administração e Coordenação Geral​ | N2: 2.011-Manutenção de Equipamentos Públicos | O2: 3.3.90.30.00-MATERIAL DE CONSUMO | P2: GÁS ENGARRAFADO | R2: 2500 | S2: LOA
A3: 02 | B3: 001 | C3: 04 | D3: 122 | E3: 0001 | F3: 2.011 | G3: 3.3.90.30.00 | H3: =_xlfn.CONCAT(A3,".",B3,".",C3,".",D3,".",E3,".",F3,".",G3) -> 02.001.04.122.0001.2.011.3.3.90.30.00 | I3: 02 - GABINETE DO PREFEITO | J3: 001-CHEFIA DE GABINETE | K3: 4-ADMINISTRAÇÃO | L3: 122-ADMINISTRAÇÃO GERAL | M3: 0001-Administração e Coordenação Geral​ | N3: 2.011-Manutenção de Equipamentos Públicos | O3: 3.3.90.30.00-MATERIAL DE CONSUMO | P3: MATERIAL DE COPA E COZINHA | R3: 36000 | S3: LOA
A4: 02 | B4: 001 | C4: 04 | D4: 122 | E4: 0001 | F4: 2.011 | G4: 3.3.90.30.00 | H4: =_xlfn.CONCAT(A4,".",B4,".",C4,".",D4,".",E4,".",F4,".",G4) -> 02.001.04.122.0001.2.011.3.3.90.30.00 | I4: 02 - GABINETE DO PREFEITO | J4: 001-CHEFIA DE GABINETE | K4: 4-ADMINISTRAÇÃO | L4: 122-ADMINISTRAÇÃO GERAL | M4: 0001-Administração e Coordenação Geral​ | N4: 2.011-Manutenção de Equipamentos Públicos | O4: 3.3.90.30.00-MATERIAL DE CONSUMO | P4: MATERIAL DE LIMPEZA E PRODUTOS DE HIGIENIZAÇÃO | R4: 12000 | S4: LOA
A5: 02 | B5: 001 | C5: 04 | D5: 122 | E5: 0001 | F5: 2.011 | G5: 3.3.90.30.00 | H5: =_xlfn.CONCAT(A5,".",B5,".",C5,".",D5,".",E5,".",F5,".",G5) -> 02.001.04.122.0001.2.011.3.3.90.30.00 | I5: 02 - GABINETE DO PREFEITO | J5: 001-CHEFIA DE GABINETE | K5: 4-ADMINISTRAÇÃO | L5: 122-ADMINISTRAÇÃO GERAL | M5: 0001-Administração e Coordenação Geral​ | N5: 2.011-Manutenção de Equipamentos Públicos | O5: 3.3.90.30.00-MATERIAL DE CONSUMO | P5: MATERIAL DE EXPEDIENTE | R5: 6500 | S5: LOA
A6: 02 | B6: 001 | C6: 04 | D6: 122 | E6: 0001 | F6: 2.011 | G6: 3.3.90.39.00 | H6: =_xlfn.CONCAT(A6,".",B6,".",C6,".",D6,".",E6,".",F6,".",G6) -> 02.001.04.122.0001.2.011.3.3.90.39.00 | I6: 02 - GABINETE DO PREFEITO | J6: 001-CHEFIA DE GABINETE | K6: 4-ADMINISTRAÇÃO | L6: 122-ADMINISTRAÇÃO GERAL | M6: 0001-Administração e Coordenação Geral​ | N6: 2.011-Manutenção de Equipamentos Públicos | O6: 3.3.90.39.00-OUTROS SERVIÇOS DE TERCEIROS - PESSOA JURÍDICA | P6: MANUTENÇÃO E CONSERVAÇÃO DE BENS IMÓVEIS | R6: 15000 | S6: LOA
A7: 02 | B7: 001 | C7: 04 | D7: 122 | E7: 0001 | F7: 2.011 | G7: 3.1.71.70.00 | H7: =_xlfn.CONCAT(A7,".",B7,".",C7,".",D7,".",E7,".",F7,".",G7) -> 02.001.04.122.0001.2.011.3.1.71.70.00 | I7: 02 - GABINETE DO PREFEITO | J7: 001-CHEFIA DE GABINETE | K7: 4-ADMINISTRAÇÃO | L7: 122-ADMINISTRAÇÃO GERAL | M7: 0001-Administração e Coordenação Geral​ | N7: 2.011-Manutenção de Equipamentos Públicos | O7: 3.1.71.70.00-RATEIO PELA PARTICIPAÇÃO EM CONSÓRCIO PÚBLICO | P7: RATEIO PELA PARTICIPAÇÃO EM CONSÓRCIO PÚBLICO | R7: 434527.81 | S7: LOA
A8: 02 | B8: 001 | C8: 04 | D8: L | E8: 0001 | F8: 2.011 | G8: 3.3.71.70.00 | H8: =_xlfn.CONCAT(A8,".",B8,".",C8,".",D8,".",E8,".",F8,".",G8) -> 02.001.04.L.0001.2.011.3.3.71.70.00 | I8: 02 - GABINETE DO PREFEITO | J8: 001-CHEFIA DE GABINETE | K8: 4-ADMINISTRAÇÃO | L8: 122-ADMINISTRAÇÃO GERAL | M8: 0001-Administração e Coordenação Geral​ | N8: 2.011-Manutenção de Equipamentos Públicos | O8: 3.3.71.70.00-RATEIO PELA PARTICIPAÇÃO EM CONSÓRCIO PÚBLICO | P8: RATEIO PELA PARTICIPAÇÃO EM CONSÓRCIO PÚBLICO | R8: 2511423.4 | S8: LOA
A9: 02 | B9: 001 | C9: 04 | D9: 122 | E9: 0001 | F9: 2.011 | G9: 3.3.90.30.00 | H9: =_xlfn.CONCAT(A9,".",B9,".",C9,".",D9,".",E9,".",F9,".",G9) -> 02.001.04.122.0001.2.011.3.3.90.30.00 | I9: 02 - GABINETE DO PREFEITO | J9: 001-CHEFIA DE GABINETE | K9: 4-ADMINISTRAÇÃO | L9: 122-ADMINISTRAÇÃO GERAL | M9: 0001-Administração e Coordenação Geral​ | N9: 2.011-Manutenção de Equipamentos Públicos | O9: 3.3.90.30.00-MATERIAL DE CONSUMO | P9: MATERIAL PARA MANUTENÇÃO DE BENS IMÓVEIS | R9: 15000 | S9: LOA
A10: 02 | B10: 001 | C10: 04 | D10: 122 | E10: 0001 | F10: 2.011 | G10: 4.4.50.52.00 | H10: =_xlfn.CONCAT(A10,".",B10,".",C10,".",D10,".",E10,".",F10,".",G10) -> 02.001.04.122.0001.2.011.4.4.50.52.00 | I10: 02 - GABINETE DO PREFEITO | J10: 001-CHEFIA DE GABINETE | K10: 4-ADMINISTRAÇÃO | L10: 122-ADMINISTRAÇÃO GERAL | M10: 0001-Administração e Coordenação Geral​ | N10: 2.011-Manutenção de Equipamentos Públicos | O10: 4.4.50.52.00-EQUIPAMENTOS E MATERIAL PERMANENTE | P10: APARELHOS E UTENSÍLIOS DOMÉSTICOS | R10: 22500 | S10: LOA
A11: 02 | B11: 001 | C11: 04 | D11: 122 | E11: 0001 | F11: 2.011 | G11: 3.3.90.39.00 | H11: =_xlfn.CONCAT(A11,".",B11,".",C11,".",D11,".",E11,".",F11,".",G11) -> 02.001.04.122.0001.2.011.3.3.90.39.00 | I11: 02 - GABINETE DO PREFEITO | J11: 001-CHEFIA DE GABINETE | K11: 4-ADMINISTRAÇÃO | L11: 122-ADMINISTRAÇÃO GERAL | M11: 0001-Administração e Coordenação Geral​ | N11: 2.011-Manutenção de Equipamentos Públicos | O11: 3.3.90.39.00-OUTROS SERVIÇOS DE TERCEIROS - PESSOA JURÍDICA | P11: ASSINATURAS DE PERIÓDICOS E ANUIDADES | R11: 318414 | S11: LOA
A12: 02 | B12: 001 | C12: 04 | D12: 122 | E12: 0001 | F12: 2.011 | G12: 3.3.90.39.00 | H12: =_xlfn.CONCAT(A12,".",B12,".",C12,".",D12,".",E12,".",F12,".",G12) -> 02.001.04.122.0001.2.011.3.3.90.39.00 | I12: 02 - GABINETE DO PREFEITO | J12: 001-CHEFIA DE GABINETE | K12: 4-ADMINISTRAÇÃO | L12: 122-ADMINISTRAÇÃO GERAL | M12: 0001-Administração e Coordenação Geral​ | N12: 2.011-Manutenção de Equipamentos Públicos | O12: 3.3.90.39.00-OUTROS SERVIÇOS DE TERCEIROS - PESSOA JURÍDICA | P12: MANUTENÇÃO E CONSERVAÇÃO DE VEÍCULOS | R12: 15000 | S12: LOA
A13: 02 | B13: 001 | C13: 04 | D13: 122 | E13: 0001 | F13: 2.011 | G13: 3.3.90.39.00 | H13: =_xlfn.CONCAT(A13,".",B13,".",C13,".",D13,".",E13,".",F13,".",G13) -> 02.001.04.122.0001.2.011.3.3.90.39.00 | I13: 02 - GABINETE DO PREFEITO | J13: 001-CHEFIA DE GABINETE | K13: 4-ADMINISTRAÇÃO | L13: 122-ADMINISTRAÇÃO GERAL | M13: 0001-Administração e Coordenação Geral​ | N13: 2.011-Manutenção de Equipamentos Públicos | O13: 3.3.90.39.00-OUTROS SERVIÇOS DE TERCEIROS - PESSOA JURÍDICA | P13: LOCAÇÃO BENS MÓVEIS DE OUTRAS NATUREZAS E INTANGÍVEIS | R13: 45000 | S13: LOA
... A24: 02 | B24: 001 | C24: 04 | D24: 122 | E24: 0001 | F24: 2.011 | G24: 3.3.90.39.00 | H24: =_xlfn.CONCAT(A24,".",B24,".",C24,".",D24,".",E24,".",F24,".",G24) -> 02.001.04.122.0001.2.011.3.3.90.39.00 | I24: 02 - GABINETE DO PREFEITO | J24: 001-CHEFIA DE GABINETE | K24: 4-ADMINISTRAÇÃO | L24: 122-ADMINISTRAÇÃO GERAL | M24: 0001-Administração e Coordenação Geral​ | N24: 2.011-Manutenção de Equipamentos Públicos | O24: 3.3.90.39.00-OUTROS SERVIÇOS DE TERCEIROS - PESSOA JURÍDICA | P24: FORNECIMENTO DE ALIMENTAÇÃO | R24: 1 | S24: LOA
A25: 04 | B25: 001 | C25: 04 | D25: 126 | E25: 0002 | F25: 2.007 | G25: 3.3.90.40.00 | H25: =_xlfn.CONCAT(A25,".",B25,".",C25,".",D25,".",E25,".",F25,".",G25) -> 04.001.04.126.0002.2.007.3.3.90.40.00 | I25: 04 - SECRETARIA DE FINANÇAS | J25: 001-GABINETE DA SECRETARIA DE FINANÇAS | K25: 4-ADMINISTRAÇÃO | L25: 126-TECNOLOGIA DA INFORMATIZAÇÃO | M25: 0002-Governo Inteligente, Aberto e Inovador​ | N25: 2.007-Ampliação e Manutenção de Sistemas de Inteligência, Fiscalização e Tecnologia | O25: 3.3.90.40.00-SERVIÇOS DE TECNOLOGIA DA INFORMAÇÃO E COMUNICAÇÃO - PESSOA JURÍDICA | P25: OUTROS SERVIÇOS DE TECNOLOGIA DA INFORMAÇÃO E COMUNICAÇÃO - PESSOA JURÍDICA | Q25: 961/2024 | R25: 7642566.6 | S25: LOA
A26: 04 | B26: 001 | C26: 04 | D26: 126 | E26: 0002 | F26: 2.007 | G26: 3.3.90.40.00 | H26: =_xlfn.CONCAT(A26,".",B26,".",C26,".",D26,".",E26,".",F26,".",G26) -> 04.001.04.126.0002.2.007.3.3.90.40.00 | I26: 04 - SECRETARIA DE FINANÇAS | J26: 001-GABINETE DA SECRETARIA DE FINANÇAS | K26: 4-ADMINISTRAÇÃO | L26: 126-TECNOLOGIA DA INFORMATIZAÇÃO | M26: 0002-Governo Inteligente, Aberto e Inovador​ | N26: 2.007-Ampliação e Manutenção de Sistemas de Inteligência, Fiscalização e Tecnologia | O26: 3.3.90.40.00-SERVIÇOS DE TECNOLOGIA DA INFORMAÇÃO E COMUNICAÇÃO - PESSOA JURÍDICA | P26: MATERIAL PARA MANUTENÇÃO DE BENS IMÓVEIS | Q26: 24087/2021 | R26: 32880000 | S26: LOA
A27: 04 | B27: 001 | C27: 04 | D27: 126 | E27: 0002 | F27: 2.007 | G27: 3.3.90.39.00 | H27: =_xlfn.CONCAT(A27,".",B27,".",C27,".",D27,".",E27,".",F27,".",G27) -> 04.001.04.126.0002.2.007.3.3.90.39.00 | I27: 04 - SECRETARIA DE FINANÇAS | J27: 001-GABINETE DA SECRETARIA DE FINANÇAS | K27: 4-ADMINISTRAÇÃO | L27: 126-TECNOLOGIA DA INFORMATIZAÇÃO | M27: 0002-Governo Inteligente, Aberto e Inovador​ | N27: 2.007-Ampliação e Manutenção de Sistemas de Inteligência, Fiscalização e Tecnologia | O27: 3.3.90.39.00-OUTROS SERVIÇOS DE TERCEIROS - PESSOA JURÍDICA | P27: ASSINATURAS DE PERIÓDICOS E ANUIDADES | Q27: 9534/2022 | R27: 100000 | S27: LOA
A28: 04 | B28: 001 | C28: 04 | D28: 122 | E28: 0001 | F28: 2.011 | G28: 3.3.90.39.00 | H28: =_xlfn.CONCAT(A28,".",B28,".",C28,".",D28,".",E28,".",F28,".",G28) -> 04.001.04.122.0001.2.011.3.3.90.39.00 | I28: 04 - SECRETARIA DE FINANÇAS | J28: 001-GABINETE DA SECRETARIA DE FINANÇAS | K28: 4-ADMINISTRAÇÃO | L28: 122-ADMINISTRAÇÃO GERAL | M28: 0001-Administração e Coordenação Geral​ | N28: 2.011-Manutenção de Equipamentos Públicos | O28: 3.3.90.39.00-OUTROS SERVIÇOS DE TERCEIROS - PESSOA JURÍDICA | P28: OUTROS SERVIÇOS DE TERCEIRO PESSOA JURÍDICA - PAGAMENTO ANTECIPADO | Q28: não tem (certificado digital) | R28: 16500 | S28: LOA
A29: 04 | B29: 001 | C29: 04 | D29: 122 | E29: 0001 | F29: 2.011 | G29: 3.3.90.39.00 | H29: =_xlfn.CONCAT(A29,".",B29,".",C29,".",D29,".",E29,".",F29,".",G29) -> 04.001.04.122.0001.2.011.3.3.90.39.00 | I29: 04 - SECRETARIA DE FINANÇAS | J29: 001-GABINETE DA SECRETARIA DE FINANÇAS | K29: 4-ADMINISTRAÇÃO | L29: 122-ADMINISTRAÇÃO GERAL | M29: 0001-Administração e Coordenação Geral​ | N29: 2.011-Manutenção de Equipamentos Públicos | O29: 3.3.90.39.00-OUTROS SERVIÇOS DE TERCEIROS - PESSOA JURÍDICA | P29: MANUTENÇÃO E CONSERVAÇÃO DE BENS MÓVEIS DE OUTRAS NATUREZAS | Q29: não tem (adiantamentos) | R29: 20000 | S29: LOA
A30: 04 | B30: 001 | C30: 04 | D30: 122 | E30: 0001 | F30: 2.011 | G30: 3.3.90.93.00 | H30: =_xlfn.CONCAT(A30,".",B30,".",C30,".",D30,".",E30,".",F30,".",G30) -> 04.001.04.122.0001.2.011.3.3.90.93.00 | I30: 04 - SECRETARIA DE FINANÇAS | J30: 001-GABINETE DA SECRETARIA DE FINANÇAS | K30: 4-ADMINISTRAÇÃO | L30: 122-ADMINISTRAÇÃO GERAL | M30: 0001-Administração e Coordenação Geral​ | N30: 2.011-Manutenção de Equipamentos Públicos | O30: 3.3.90.93.00-INDENIZAÇÕES E RESTITUIÇÕES | P30: RESTITUIÇÕES | Q30: não tem (ressarcimentos) | R30: 10000 | S30: LOA
A31: 04 | B31: 001 | C31: 04 | D31: 122 | E31: 0002 | F31: 2.011 | G31: 3.3.90.33.00 | H31: =_xlfn.CONCAT(A31,".",B31,".",C31,".",D31,".",E31,".",F31,".",G31) -> 04.001.04.122.0002.2.011.3.3.90.33.00 | I31: 04 - SECRETARIA DE FINANÇAS | J31: 001-GABINETE DA SECRETARIA DE FINANÇAS | K31: 4-ADMINISTRAÇÃO | L31: 122-ADMINISTRAÇÃO GERAL | M31: 0002-Governo Inteligente, Aberto e Inovador​ | N31: 2.011-Manutenção de Equipamentos Públicos | O31: 3.3.90.33.00-PASSAGENS E DESPESAS COM LOCOMOÇÃO | Q31: Ata 77/2025 (viagens) | R31: 40000 | S31: LOA
A32: 04 | B32: 001 | C32: 04 | D32: 122 | E32: 0001 | F32: 2.011 | G32: 3.3.90.39.00 | H32: =_xlfn.CONCAT(A32,".",B32,".",C32,".",D32,".",E32,".",F32,".",G32) -> 04.001.04.122.0001.2.011.3.3.90.39.00 | I32: 04 - SECRETARIA DE FINANÇAS | J32: 001-GABINETE DA SECRETARIA DE FINANÇAS | K32: 4-ADMINISTRAÇÃO | L32: 122-ADMINISTRAÇÃO GERAL | M32: 0001-Administração e Coordenação Geral​ | N32: 2.011-Manutenção de Equipamentos Públicos | O32: 3.3.90.39.00-OUTROS SERVIÇOS DE TERCEIROS - PESSOA JURÍDICA | P32: MANUTENÇÃO E CONSERVAÇÃO DE BENS MÓVEIS DE OUTRAS NATUREZAS | Q32: não tem (ar condicionado) | R32: 25000 | S32: LOA
A33: 04 | B33: 001 | C33: 04 | D33: 122 | E33: 0001 | F33: 2.011 | G33: 3.3.90.39.00 | H33: =_xlfn.CONCAT(A33,".",B33,".",C33,".",D33,".",E33,".",F33,".",G33) -> 04.001.04.122.0001.2.011.3.3.90.39.00 | I33: 04 - SECRETARIA DE FINANÇAS | J33: 001-GABINETE DA SECRETARIA DE FINANÇAS | K33: 4-ADMINISTRAÇÃO | L33: 122-ADMINISTRAÇÃO GERAL | M33: 0001-Administração e Coordenação Geral​ | N33: 2.011-Manutenção de Equipamentos Públicos | O33: 3.3.90.39.00-OUTROS SERVIÇOS DE TERCEIROS - PESSOA JURÍDICA | P33: MANUTENÇÃO E CONSERVAÇÃO DE BENS MÓVEIS DE OUTRAS NATUREZAS | Q33: não tem (veículos) | R33: 10000 | S33: LOA
A34: 04 | B34: 001 | C34: 04 | D34: 122 | E34: 0001 | F34: 2.011 | G34: 3.3.90.39.00 | H34: =_xlfn.CONCAT(A34,".",B34,".",C34,".",D34,".",E34,".",F34,".",G34) -> 04.001.04.122.0001.2.011.3.3.90.39.00 | I34: 04 - SECRETARIA DE FINANÇAS | J34: 001-GABINETE DA SECRETARIA DE FINANÇAS | K34: 4-ADMINISTRAÇÃO | L34: 122-ADMINISTRAÇÃO GERAL | M34: 0001-Administração e Coordenação Geral​ | N34: 2.011-Manutenção de Equipamentos Públicos | O34: 3.3.90.39.00-OUTROS SERVIÇOS DE TERCEIROS - PESSOA JURÍDICA | P34: MANUTENÇÃO E CONSERVAÇÃO DE BENS MÓVEIS DE OUTRAS NATUREZAS | Q34: não tem (bebedouros) | R34: 2000 | S34: LOA
A35: 04 | B35: 001 | C35: 04 | D35: 122 | E35: 0001 | F35: 2.011 | G35: 3.3.90.39.00 | H35: =_xlfn.CONCAT(A35,".",B35,".",C35,".",D35,".",E35,".",F35,".",G35) -> 04.001.04.122.0001.2.011.3.3.90.39.00 | I35: 04 - SECRETARIA DE FINANÇAS | J35: 001-GABINETE DA SECRETARIA DE FINANÇAS | K35: 4-ADMINISTRAÇÃO | L35: 122-ADMINISTRAÇÃO GERAL | M35: 0001-Administração e Coordenação Geral​ | N35: 2.011-Manutenção de Equipamentos Públicos | O35: 3.3.90.39.00-OUTROS SERVIÇOS DE TERCEIROS - PESSOA JURÍDICA | P35: MANUTENÇÃO E CONSERVAÇÃO DE BENS MÓVEIS DE OUTRAS NATUREZAS | Q35: não tem (hidraúlica, elétrica...) | R35: 5000 | S35: LOA
A36: 04 | B36: 001 | C36: 04 | D36: 122 | E36: 0001 | F36: 2.011 | G36: 4.4.90.52.00 | H36: =_xlfn.CONCAT(A36,".",B36,".",C36,".",D36,".",E36,".",F36,".",G36) -> 04.001.04.122.0001.2.011.4.4.90.52.00 | I36: 04 - SECRETARIA DE FINANÇAS | J36: 001-GABINETE DA SECRETARIA DE FINANÇAS | K36: 4-ADMINISTRAÇÃO | L36: 122-ADMINISTRAÇÃO GERAL | M36: 0001-Administração e Coordenação Geral​ | N36: 2.011-Manutenção de Equipamentos Públicos | O36: 4.4.90.52.00-EQUIPAMENTOS E MATERIAL PERMANENTE | P36: MÁQUINAS, UTENSÍLIOS E EQUIPAMENTOS DIVERSOS | Q36: não tem (ar condicionado) | R36: 40000 | S36: LOA
A37: 04 | B37: 001 | C37: 04 | D37: 122 | E37: 0001 | F37: 2.011 | G37: 3.3.90.30.00 | H37: =_xlfn.CONCAT(A37,".",B37,".",C37,".",D37,".",E37,".",F37,".",G37) -> 04.001.04.122.0001.2.011.3.3.90.30.00 | I37: 04 - SECRETARIA DE FINANÇAS | J37: 001-GABINETE DA SECRETARIA DE FINANÇAS | K37: 4-ADMINISTRAÇÃO | L37: 122-ADMINISTRAÇÃO GERAL | M37: 0001-Administração e Coordenação Geral​ | N37: 2.011-Manutenção de Equipamentos Públicos | O37: 3.3.90.30.00-MATERIAL DE CONSUMO | P37: MATERIAL DE COPA E COZINHA | Q37: Ata 146/2026 | R37: 16000 | S37: LOA
A38: 04 | B38: 001 | C38: 04 | D38: 122 | E38: 0001 | F38: 2.011 | G38: 3.3.90.30.00 | H38: =_xlfn.CONCAT(A38,".",B38,".",C38,".",D38,".",E38,".",F38,".",G38) -> 04.001.04.122.0001.2.011.3.3.90.30.00 | I38: 04 - SECRETARIA DE FINANÇAS | J38: 001-GABINETE DA SECRETARIA DE FINANÇAS | K38: 4-ADMINISTRAÇÃO | L38: 122-ADMINISTRAÇÃO GERAL | M38: 0001-Administração e Coordenação Geral​ | N38: 2.011-Manutenção de Equipamentos Públicos | O38: 3.3.90.30.00-MATERIAL DE CONSUMO | P38: MATERIAL DE COPA E COZINHA | Q38: Ata 66/2025 | R38: 2000 | S38: LOA
A39: 04 | B39: 001 | C39: 04 | D39: 122 | E39: 0001 | F39: 2.011 | G39: 3.3.90.30.00 | H39: =_xlfn.CONCAT(A39,".",B39,".",C39,".",D39,".",E39,".",F39,".",G39) -> 04.001.04.122.0001.2.011.3.3.90.30.00 | I39: 04 - SECRETARIA DE FINANÇAS | J39: 001-GABINETE DA SECRETARIA DE FINANÇAS | K39: 4-ADMINISTRAÇÃO | L39: 122-ADMINISTRAÇÃO GERAL | M39: 0001-Administração e Coordenação Geral​ | N39: 2.011-Manutenção de Equipamentos Públicos | O39: 3.3.90.30.00-MATERIAL DE CONSUMO | P39: MATERIAL DE LIMPEZA E PRODUTOS DE HIGIENIZAÇÃO | Q39: Ata 28 e 48/2026 | R39: 10000 | S39: LOA
A40: 04 | B40: 001 | C40: 04 | D40: 122 | E40: 0001 | F40: 2.011 | G40: 3.3.90.30.00 | H40: =_xlfn.CONCAT(A40,".",B40,".",C40,".",D40,".",E40,".",F40,".",G40) -> 04.001.04.122.0001.2.011.3.3.90.30.00 | I40: 04 - SECRETARIA DE FINANÇAS | J40: 001-GABINETE DA SECRETARIA DE FINANÇAS | K40: 4-ADMINISTRAÇÃO | L40: 122-ADMINISTRAÇÃO GERAL | M40: 0001-Administração e Coordenação Geral​ | N40: 2.011-Manutenção de Equipamentos Públicos | O40: 3.3.90.30.00-MATERIAL DE CONSUMO | P40: MATERIAL DE LIMPEZA E PRODUTOS DE HIGIENIZAÇÃO | Q40: Ata 93/2025 | R40: 28000 | S40: LOA
A41: 04 | B41: 001 | C41: 04 | D41: 122 | E41: 0001 | F41: 2.011 | G41: 3.3.90.30.00 | H41: =_xlfn.CONCAT(A41,".",B41,".",C41,".",D41,".",E41,".",F41,".",G41) -> 04.001.04.122.0001.2.011.3.3.90.30.00 | I41: 04 - SECRETARIA DE FINANÇAS | J41: 001-GABINETE DA SECRETARIA DE FINANÇAS | K41: 4-ADMINISTRAÇÃO | L41: 122-ADMINISTRAÇÃO GERAL | M41: 0001-Administração e Coordenação Geral​ | N41: 2.011-Manutenção de Equipamentos Públicos | O41: 3.3.90.30.00-MATERIAL DE CONSUMO | P41: MATERIAL ELÉTRICO E ELETRÔNICO | Q41: Ata 105 e 107/2025 | R41: 5000 | S41: LOA
A42: 04 | B42: 001 | C42: 04 | D42: 122 | E42: 0001 | F42: 2.011 | G42: 3.3.90.30.00 | H42: =_xlfn.CONCAT(A42,".",B42,".",C42,".",D42,".",E42,".",F42,".",G42) -> 04.001.04.122.0001.2.011.3.3.90.30.00 | I42: 04 - SECRETARIA DE FINANÇAS | J42: 001-GABINETE DA SECRETARIA DE FINANÇAS | K42: 4-ADMINISTRAÇÃO | L42: 122-ADMINISTRAÇÃO GERAL | M42: 0001-Administração e Coordenação Geral​ | N42: 2.011-Manutenção de Equipamentos Públicos | O42: 3.3.90.30.00-MATERIAL DE CONSUMO | P42: MATERIAL PARA MANUTENÇÃO DE VEÍCULOS | Q42: não tem (veículos) | R42: 10000 | S42: LOA
A43: 05 | B43: 001 | C43: 04 | D43: 122 | E43: 0001 | F43: 2.011 | G43: 3.3.90.30.00 | H43: =_xlfn.CONCAT(A43,".",B43,".",C43,".",D43,".",E43,".",F43,".",G43) -> 05.001.04.122.0001.2.011.3.3.90.30.00 | I43: 05 - PROCURADORIA GERAL DO MUNICÍPIO | J43: 001-GABINETE DA PROCURADORIA GERAL DO MUNICÍPIO | K43: 4-ADMINISTRAÇÃO | L43: 122-ADMINISTRAÇÃO GERAL | M43: 0001-Administração e Coordenação Geral​ | N43: 2.011-Manutenção de Equipamentos Públicos | O43: 3.3.90.30.00-MATERIAL DE CONSUMO | P43: MATERIAL DE COPA E COZINHA | R43: 25000 | S43: LOA
A44: 05 | B44: 001 | C44: 04 | D44: 122 | E44: 0001 | F44: 2.011 | G44: 3.3.90.30.00 | H44: =_xlfn.CONCAT(A44,".",B44,".",C44,".",D44,".",E44,".",F44,".",G44) -> 05.001.04.122.0001.2.011.3.3.90.30.00 | I44: 05 - PROCURADORIA GERAL DO MUNICÍPIO | J44: 001-GABINETE DA PROCURADORIA GERAL DO MUNICÍPIO | K44: 4-ADMINISTRAÇÃO | L44: 122-ADMINISTRAÇÃO GERAL | M44: 0001-Administração e Coordenação Geral​ | N44: 2.011-Manutenção de Equipamentos Públicos | O44: 3.3.90.30.00-MATERIAL DE CONSUMO | P44: MATERIAL DE EXPEDIENTE | R44: 25000 | S44: LOA
A45: 05 | B45: 001 | C45: 04 | D45: 122 | E45: 0001 | F45: 2.011 | G45: 3.3.90.30.00 | H45: =_xlfn.CONCAT(A45,".",B45,".",C45,".",D45,".",E45,".",F45,".",G45) -> 05.001.04.122.0001.2.011.3.3.90.30.00 | I45: 05 - PROCURADORIA GERAL DO MUNICÍPIO | J45: 001-GABINETE DA PROCURADORIA GERAL DO MUNICÍPIO | K45: 4-ADMINISTRAÇÃO | L45: 122-ADMINISTRAÇÃO GERAL | M45: 0001-Administração e Coordenação Geral​ | N45: 2.011-Manutenção de Equipamentos Públicos | O45: 3.3.90.30.00-MATERIAL DE CONSUMO | P45: MATERIAL DE LIMPEZA E PRODUTOS DE HIGIENIZAÇÃO | R45: 35000 | S45: LOA
A46: 05 | B46: 001 | C46: 04 | D46: 122 | E46: 0001 | F46: 2.011 | G46: 3.3.90.39.00 | H46: =_xlfn.CONCAT(A46,".",B46,".",C46,".",D46,".",E46,".",F46,".",G46) -> 05.001.04.122.0001.2.011.3.3.90.39.00 | I46: 05 - PROCURADORIA GERAL DO MUNICÍPIO | J46: 001-GABINETE DA PROCURADORIA GERAL DO MUNICÍPIO | K46: 4-ADMINISTRAÇÃO | L46: 122-ADMINISTRAÇÃO GERAL | M46: 0001-Administração e Coordenação Geral​ | N46: 2.011-Manutenção de Equipamentos Públicos | O46: 3.3.90.39.00-OUTROS SERVIÇOS DE TERCEIROS - PESSOA JURÍDICA | P46: OUTROS SERVIÇOS DE TERCEIROS - PESSOA JURÍDICA | Q46: Pagamento de Perito | R46: 100000 | S46: LOA
A47: 05 | B47: 001 | C47: 04 | D47: 122 | E47: 0001 | F47: 2.011 | G47: 3.3.90.39.00 | H47: =_xlfn.CONCAT(A47,".",B47,".",C47,".",D47,".",E47,".",F47,".",G47) -> 05.001.04.122.0001.2.011.3.3.90.39.00 | I47: 05 - PROCURADORIA GERAL DO MUNICÍPIO | J47: 001-GABINETE DA PROCURADORIA GERAL DO MUNICÍPIO | K47: 4-ADMINISTRAÇÃO | L47: 122-ADMINISTRAÇÃO GERAL | M47: 0001-Administração e Coordenação Geral​ | N47: 2.011-Manutenção de Equipamentos Públicos | O47: 3.3.90.39.00-OUTROS SERVIÇOS DE TERCEIROS - PESSOA JURÍDICA | P47: OUTROS SERVIÇOS DE TERCEIROS - PESSOA JURÍDICA | Q47: Locação de Veículos | R47: 44279 | S47: LOA
A48: 05 | B48: 001 | C48: 04 | D48: 122 | E48: 0001 | F48: 2.011 | G48: 3.3.90.39.00 | H48: =_xlfn.CONCAT(A48,".",B48,".",C48,".",D48,".",E48,".",F48,".",G48) -> 05.001.04.122.0001.2.011.3.3.90.39.00 | I48: 05 - PROCURADORIA GERAL DO MUNICÍPIO | J48: 001-GABINETE DA PROCURADORIA GERAL DO MUNICÍPIO | K48: 4-ADMINISTRAÇÃO | L48: 122-ADMINISTRAÇÃO GERAL | M48: 0001-Administração e Coordenação Geral​ | N48: 2.011-Manutenção de Equipamentos Públicos | O48: 3.3.90.39.00-OUTROS SERVIÇOS DE TERCEIROS - PESSOA JURÍDICA | P48: OUTROS SERVIÇOS DE TERCEIROS - PESSOA JURÍDICA | Q48: 1221/2025 | R48: 27784.02 | S48: LOA
A49: 05 | B49: 001 | C49: 04 | D49: 122 | E49: 0001 | F49: 2.011 | G49: 3.3.90.39.00 | H49: =_xlfn.CONCAT(A49,".",B49,".",C49,".",D49,".",E49,".",F49,".",G49) -> 05.001.04.122.0001.2.011.3.3.90.39.00 | I49: 05 - PROCURADORIA GERAL DO MUNICÍPIO | J49: 001-GABINETE DA PROCURADORIA GERAL DO MUNICÍPIO | K49: 4-ADMINISTRAÇÃO | L49: 122-ADMINISTRAÇÃO GERAL | M49: 0001-Administração e Coordenação Geral​ | N49: 2.011-Manutenção de Equipamentos Públicos | O49: 3.3.90.39.00-OUTROS SERVIÇOS DE TERCEIROS - PESSOA JURÍDICA | P49: OUTROS SERVIÇOS DE TERCEIROS - PESSOA JURÍDICA | Q49: 7925/2021 | R49: 15000 | S49: LOA
A50: 05 | B50: 001 | C50: 04 | D50: 122 | E50: 0001 | F50: 2.011 | G50: 3.3.90.39.00 | H50: =_xlfn.CONCAT(A50,".",B50,".",C50,".",D50,".",E50,".",F50,".",G50) -> 05.001.04.122.0001.2.011.3.3.90.39.00 | I50: 05 - PROCURADORIA GERAL DO MUNICÍPIO | J50: 001-GABINETE DA PROCURADORIA GERAL DO MUNICÍPIO | K50: 4-ADMINISTRAÇÃO | L50: 122-ADMINISTRAÇÃO GERAL | M50: 0001-Administração e Coordenação Geral​ | N50: 2.011-Manutenção de Equipamentos Públicos | O50: 3.3.90.39.00-OUTROS SERVIÇOS DE TERCEIROS - PESSOA JURÍDICA | P50: OUTROS SERVIÇOS DE TERCEIROS - PESSOA JURÍDICA | Q50: 1227/2024 | R50: 49472 | S50: LOA
A51: 05 | B51: 001 | C51: 04 | D51: 122 | E51: 0001 | F51: 2.011 | G51: 3.3.90.39.00 | H51: =_xlfn.CONCAT(A51,".",B51,".",C51,".",D51,".",E51,".",F51,".",G51) -> 05.001.04.122.0001.2.011.3.3.90.39.00 | I51: 05 - PROCURADORIA GERAL DO MUNICÍPIO | J51: 001-GABINETE DA PROCURADORIA GERAL DO MUNICÍPIO | K51: 4-ADMINISTRAÇÃO | L51: 122-ADMINISTRAÇÃO GERAL | M51: 0001-Administração e Coordenação Geral​ | N51: 2.011-Manutenção de Equipamentos Públicos | O51: 3.3.90.39.00-OUTROS SERVIÇOS DE TERCEIROS - PESSOA JURÍDICA | P51: OUTROS SERVIÇOS DE TERCEIROS - PESSOA JURÍDICA | Q51: 15401/2015 | R51: 64000 | S51: LOA
A52: 05 | B52: 001 | C52: 04 | D52: 122 | E52: 0001 | F52: 2.011 | G52: 3.3.90.39.00 | H52: =_xlfn.CONCAT(A52,".",B52,".",C52,".",D52,".",E52,".",F52,".",G52) -> 05.001.04.122.0001.2.011.3.3.90.39.00 | I52: 05 - PROCURADORIA GERAL DO MUNICÍPIO | J52: 001-GABINETE DA PROCURADORIA GERAL DO MUNICÍPIO | K52: 4-ADMINISTRAÇÃO | L52: 122-ADMINISTRAÇÃO GERAL | M52: 0001-Administração e Coordenação Geral​ | N52: 2.011-Manutenção de Equipamentos Públicos | O52: 3.3.90.39.00-OUTROS SERVIÇOS DE TERCEIROS - PESSOA JURÍDICA | P52: OUTROS SERVIÇOS DE TERCEIROS - PESSOA JURÍDICA | Q52: Taxas, Tarifas, Multas e Anuidade | R52: 800000 | S52: LOA
A53: 05 | B53: 001 | C53: 04 | D53: 122 | E53: 0001 | F53: 2.011 | G53: 3.3.90.39.00 | H53: =_xlfn.CONCAT(A53,".",B53,".",C53,".",D53,".",E53,".",F53,".",G53) -> 05.001.04.122.0001.2.011.3.3.90.39.00 | I53: 05 - PROCURADORIA GERAL DO MUNICÍPIO | J53: 001-GABINETE DA PROCURADORIA GERAL DO MUNICÍPIO | K53: 4-ADMINISTRAÇÃO | L53: 122-ADMINISTRAÇÃO GERAL | M53: 0001-Administração e Coordenação Geral​ | N53: 2.011-Manutenção de Equipamentos Públicos | O53: 3.3.90.39.00-OUTROS SERVIÇOS DE TERCEIROS - PESSOA JURÍDICA | P53: OUTROS SERVIÇOS DE TERCEIROS - PESSOA JURÍDICA | Q53: Diligências Realizadas por Oficiais de Justiça | R53: 300000 | S53: LOA
A54: 05 | B54: 001 | C54: 04 | D54: 122 | E54: 0001 | F54: 2.011 | G54: 3.3.90.39.00 | H54: =_xlfn.CONCAT(A54,".",B54,".",C54,".",D54,".",E54,".",F54,".",G54) -> 05.001.04.122.0001.2.011.3.3.90.39.00 | I54: 05 - PROCURADORIA GERAL DO MUNICÍPIO | J54: 001-GABINETE DA PROCURADORIA GERAL DO MUNICÍPIO | K54: 4-ADMINISTRAÇÃO | L54: 122-ADMINISTRAÇÃO GERAL | M54: 0001-Administração e Coordenação Geral​ | N54: 2.011-Manutenção de Equipamentos Públicos | O54: 3.3.90.39.00-OUTROS SERVIÇOS DE TERCEIROS - PESSOA JURÍDICA | Q54: Despesas com Intimações/Citações de Processos Digitais | R54: 1320000 | S54: LOA
A55: 05 | B55: 001 | C55: 04 | D55: 126 | E55: 0002 | F55: 2.007 | G55: 3.3.90.40.00 | H55: =_xlfn.CONCAT(A55,".",B55,".",C55,".",D55,".",E55,".",F55,".",G55) -> 05.001.04.126.0002.2.007.3.3.90.40.00 | I55: 05 - PROCURADORIA GERAL DO MUNICÍPIO | J55: 001-GABINETE DA PROCURADORIA GERAL DO MUNICÍPIO | K55: 4-ADMINISTRAÇÃO | L55: 126-TECNOLOGIA DA INFORMATIZAÇÃO | M55: 0002-Governo Inteligente, Aberto e Inovador​ | N55: 2.007-Ampliação e Manutenção de Sistemas de Inteligência, Fiscalização e Tecnologia | O55: 3.3.90.40.00-SERVIÇOS DE TECNOLOGIA DA INFORMAÇÃO E COMUNICAÇÃO - PESSOA JURÍDICA | Q55: 1272/2026 | R55: 1100000 | S55: LOA
A56: 05 | B56: 001 | C56: 04 | D56: 122 | E56: 0001 | F56: 2.011 | G56: 4.4.90.52.00 | H56: =_xlfn.CONCAT(A56,".",B56,".",C56,".",D56,".",E56,".",F56,".",G56) -> 05.001.04.122.0001.2.011.4.4.90.52.00 | I56: 05 - PROCURADORIA GERAL DO MUNICÍPIO | J56: 001-GABINETE DA PROCURADORIA GERAL DO MUNICÍPIO | K56: 4-ADMINISTRAÇÃO | L56: 122-ADMINISTRAÇÃO GERAL | M56: 0001-Administração e Coordenação Geral​ | N56: 2.011-Manutenção de Equipamentos Públicos | O56: 4.4.90.52.00-EQUIPAMENTOS E MATERIAL PERMANENTE | P56: MÁQUINAS, UTENSÍLIOS E EQUIPAMENTOS DIVERSOS | Q56: Sistema de Climatização - Materiais | R56: 10000 | S56: LOA
A57: 05 | B57: 001 | C57: 04 | D57: 122 | E57: 0001 | F57: 2.011 | G57: 3.3.90.39.00 | H57: =_xlfn.CONCAT(A57,".",B57,".",C57,".",D57,".",E57,".",F57,".",G57) -> 05.001.04.122.0001.2.011.3.3.90.39.00 | I57: 05 - PROCURADORIA GERAL DO MUNICÍPIO | J57: 001-GABINETE DA PROCURADORIA GERAL DO MUNICÍPIO | K57: 4-ADMINISTRAÇÃO | L57: 122-ADMINISTRAÇÃO GERAL | M57: 0001-Administração e Coordenação Geral​ | N57: 2.011-Manutenção de Equipamentos Públicos | O57: 3.3.90.39.00-OUTROS SERVIÇOS DE TERCEIROS - PESSOA JURÍDICA | P57: MANUTENÇÃO E CONSERVAÇÃO DE MÁQUINAS E EQUIPAMENTOS | Q57: Sistema de Climatização - Serviços | R57: 8000 | S57: LOA
A58: 05 | B58: 001 | C58: 04 | D58: 122 | E58: 0001 | F58: 2.011 | G58: 3.3.90.39.00 | H58: =_xlfn.CONCAT(A58,".",B58,".",C58,".",D58,".",E58,".",F58,".",G58) -> 05.001.04.122.0001.2.011.3.3.90.39.00 | I58: 05 - PROCURADORIA GERAL DO MUNICÍPIO | J58: 001-GABINETE DA PROCURADORIA GERAL DO MUNICÍPIO | K58: 4-ADMINISTRAÇÃO | L58: 122-ADMINISTRAÇÃO GERAL | M58: 0001-Administração e Coordenação Geral​ | N58: 2.011-Manutenção de Equipamentos Públicos | O58: 3.3.90.39.00-OUTROS SERVIÇOS DE TERCEIROS - PESSOA JURÍDICA | P58: MANUTENÇÃO E CONSERVAÇÃO DE MÁQUINAS E EQUIPAMENTOS | Q58: Manutenção de Veículos | R58: 10000 | S58: LOA
A59: 06 | B59: 001 | C59: 04 | D59: 122 | E59: 0001 | F59: 2.011 | G59: 3.3.90.30.00 | H59: =_xlfn.CONCAT(A59,".",B59,".",C59,".",D59,".",E59,".",F59,".",G59) -> 06.001.04.122.0001.2.011.3.3.90.30.00 | I59: 06 - SECRETARIA DE ADMINISTRAÇÃO | J59: 001-GABINETE DA SECRETARIA DE ADMINISTRAÇÃO | K59: 4-ADMINISTRAÇÃO | L59: 122-ADMINISTRAÇÃO GERAL | M59: 0001-Administração e Coordenação Geral​ | N59: 2.011-Manutenção de Equipamentos Públicos | O59: 3.3.90.30.00-MATERIAL DE CONSUMO | P59: MATERIAL DE LIMPEZA E PRODUTOS DE HIGIENIZAÇÃO | R59: 150000 | S59: LOA
A60: 06 | B60: 001 | C60: 04 | D60: 122 | E60: 0001 | F60: 2.011 | G60: 3.3.90.30.00 | H60: =_xlfn.CONCAT(A60,".",B60,".",C60,".",D60,".",E60,".",F60,".",G60) -> 06.001.04.122.0001.2.011.3.3.90.30.00 | I60: 06 - SECRETARIA DE ADMINISTRAÇÃO | J60: 001-GABINETE DA SECRETARIA DE ADMINISTRAÇÃO | K60: 4-ADMINISTRAÇÃO | L60: 122-ADMINISTRAÇÃO GERAL | M60: 0001-Administração e Coordenação Geral​ | N60: 2.011-Manutenção de Equipamentos Públicos | O60: 3.3.90.30.00-MATERIAL DE CONSUMO | P60: MATERIAL DE EXPEDIENTE | R60: 40468 | S60: LOA
A61: 06 | B61: 001 | C61: 04 | D61: 122 | E61: 0001 | F61: 2.011 | G61: 3.3.90.30.00 | H61: =_xlfn.CONCAT(A61,".",B61,".",C61,".",D61,".",E61,".",F61,".",G61) -> 06.001.04.122.0001.2.011.3.3.90.30.00 | I61: 06 - SECRETARIA DE ADMINISTRAÇÃO | J61: 001-GABINETE DA SECRETARIA DE ADMINISTRAÇÃO | K61: 4-ADMINISTRAÇÃO | L61: 122-ADMINISTRAÇÃO GERAL | M61: 0001-Administração e Coordenação Geral​ | N61: 2.011-Manutenção de Equipamentos Públicos | O61: 3.3.90.30.00-MATERIAL DE CONSUMO | P61: MATERIAL DE COPA E COZINHA | R61: 30000 | S61: LOA
A62: 06 | B62: 001 | C62: 04 | D62: 122 | E62: 0001 | F62: 2.011 | G62: 3.3.90.30.00 | H62: =_xlfn.CONCAT(A62,".",B62,".",C62,".",D62,".",E62,".",F62,".",G62) -> 06.001.04.122.0001.2.011.3.3.90.30.00 | I62: 06 - SECRETARIA DE ADMINISTRAÇÃO | J62: 001-GABINETE DA SECRETARIA DE ADMINISTRAÇÃO | K62: 4-ADMINISTRAÇÃO | L62: 122-ADMINISTRAÇÃO GERAL | M62: 0001-Administração e Coordenação Geral​ | N62: 2.011-Manutenção de Equipamentos Públicos | O62: 3.3.90.30.00-MATERIAL DE CONSUMO | P62: MATERIAL PARA MANUTENÇÃO DE BENS IMÓVEIS | R62: 10000 | S62: LOA
A63: 06 | B63: 001 | C63: 04 | D63: 122 | E63: 0001 | F63: 2.011 | G63: 3.3.90.30.00 | H63: =_xlfn.CONCAT(A63,".",B63,".",C63,".",D63,".",E63,".",F63,".",G63) -> 06.001.04.122.0001.2.011.3.3.90.30.00 | I63: 06 - SECRETARIA DE ADMINISTRAÇÃO | J63: 001-GABINETE DA SECRETARIA DE ADMINISTRAÇÃO | K63: 4-ADMINISTRAÇÃO | L63: 122-ADMINISTRAÇÃO GERAL | M63: 0001-Administração e Coordenação Geral​ | N63: 2.011-Manutenção de Equipamentos Públicos | O63: 3.3.90.30.00-MATERIAL DE CONSUMO | P63: MATERIAL PARA MANUTENÇÃO DE VEÍCULOS | R63: 30000 | S63: LOA
A64: 06 | B64: 001 | C64: 04 | D64: 122 | E64: 0001 | F64: 2.011 | G64: 3.3.90.30.00 | H64: =_xlfn.CONCAT(A64,".",B64,".",C64,".",D64,".",E64,".",F64,".",G64) -> 06.001.04.122.0001.2.011.3.3.90.30.00 | I64: 06 - SECRETARIA DE ADMINISTRAÇÃO | J64: 001-GABINETE DA SECRETARIA DE ADMINISTRAÇÃO | K64: 4-ADMINISTRAÇÃO | L64: 122-ADMINISTRAÇÃO GERAL | M64: 0001-Administração e Coordenação Geral​ | N64: 2.011-Manutenção de Equipamentos Públicos | O64: 3.3.90.30.00-MATERIAL DE CONSUMO | P64: MATERIAL PARA UTILIZAÇÃO EM GRÁFICA | R64: 10000 | S64: LOA
A65: 06 | B65: 001 | C65: 04 | D65: 122 | E65: 0001 | F65: 2.011 | G65: 4.4.90.52.00 | H65: =_xlfn.CONCAT(A65,".",B65,".",C65,".",D65,".",E65,".",F65,".",G65) -> 06.001.04.122.0001.2.011.4.4.90.52.00 | I65: 06 - SECRETARIA DE ADMINISTRAÇÃO | J65: 001-GABINETE DA SECRETARIA DE ADMINISTRAÇÃO | K65: 4-ADMINISTRAÇÃO | L65: 122-ADMINISTRAÇÃO GERAL | M65: 0001-Administração e Coordenação Geral​ | N65: 2.011-Manutenção de Equipamentos Públicos | O65: 4.4.90.52.00-EQUIPAMENTOS E MATERIAL PERMANENTE | P65: OUTROS MATERIAIS PERMANENTES | R65: 100000 | S65: LOA
A66: 06 | B66: 001 | C66: 04 | D66: 122 | E66: 0001 | F66: 2.011 | G66: 3.3.90.39.00 | H66: =_xlfn.CONCAT(A66,".",B66,".",C66,".",D66,".",E66,".",F66,".",G66) -> 06.001.04.122.0001.2.011.3.3.90.39.00 | I66: 06 - SECRETARIA DE ADMINISTRAÇÃO | J66: 001-GABINETE DA SECRETARIA DE ADMINISTRAÇÃO | K66: 4-ADMINISTRAÇÃO | L66: 122-ADMINISTRAÇÃO GERAL | M66: 0001-Administração e Coordenação Geral​ | N66: 2.011-Manutenção de Equipamentos Públicos | O66: 3.3.90.39.00-OUTROS SERVIÇOS DE TERCEIROS - PESSOA JURÍDICA | P66: OUTROS SERVIÇOS DE TERCEIROS - PESSOA JURÍDICA | Q66: 1780/25 | R66: 12898090 | S66: LOA
A67: 06 | B67: 001 | C67: 04 | D67: 122 | E67: 0001 | F67: 2.011 | G67: 3.3.90.39.00 | H67: =_xlfn.CONCAT(A67,".",B67,".",C67,".",D67,".",E67,".",F67,".",G67) -> 06.001.04.122.0001.2.011.3.3.90.39.00 | I67: 06 - SECRETARIA DE ADMINISTRAÇÃO | J67: 001-GABINETE DA SECRETARIA DE ADMINISTRAÇÃO | K67: 4-ADMINISTRAÇÃO | L67: 122-ADMINISTRAÇÃO GERAL | M67: 0001-Administração e Coordenação Geral​ | N67: 2.011-Manutenção de Equipamentos Públicos | O67: 3.3.90.39.00-OUTROS SERVIÇOS DE TERCEIROS - PESSOA JURÍDICA | P67: LOCAÇÃO DE MÁQUINAS E EQUIPAMENTOS | Q67: 1097/25 | R67: 72000 | S67: LOA
A68: 06 | B68: 001 | C68: 04 | D68: 122 | E68: 0001 | F68: 2.011 | G68: 3.3.90.39.00 | H68: =_xlfn.CONCAT(A68,".",B68,".",C68,".",D68,".",E68,".",F68,".",G68) -> 06.001.04.122.0001.2.011.3.3.90.39.00 | I68: 06 - SECRETARIA DE ADMINISTRAÇÃO | J68: 001-GABINETE DA SECRETARIA DE ADMINISTRAÇÃO | K68: 4-ADMINISTRAÇÃO | L68: 122-ADMINISTRAÇÃO GERAL | M68: 0001-Administração e Coordenação Geral​ | N68: 2.011-Manutenção de Equipamentos Públicos | O68: 3.3.90.39.00-OUTROS SERVIÇOS DE TERCEIROS - PESSOA JURÍDICA | P68: MANUTENÇÃO E CONSERVAÇÃO DE BENS MÓVEIS DE OUTRAS NATUREZAS | Q68: 185/25 | R68: 82000 | S68: LOA
A69: 06 | B69: 001 | C69: 04 | D69: 122 | E69: 0001 | F69: 2.011 | G69: 3.3.90.39.00 | H69: =_xlfn.CONCAT(A69,".",B69,".",C69,".",D69,".",E69,".",F69,".",G69) -> 06.001.04.122.0001.2.011.3.3.90.39.00 | I69: 06 - SECRETARIA DE ADMINISTRAÇÃO | J69: 001-GABINETE DA SECRETARIA DE ADMINISTRAÇÃO | K69: 4-ADMINISTRAÇÃO | L69: 122-ADMINISTRAÇÃO GERAL | M69: 0001-Administração e Coordenação Geral​ | N69: 2.011-Manutenção de Equipamentos Públicos | O69: 3.3.90.39.00-OUTROS SERVIÇOS DE TERCEIROS - PESSOA JURÍDICA | P69: OUTROS SERVIÇOS DE TERCEIROS - PESSOA JURÍDICA | Q69: 1284/25 | R69: 1433376 | S69: LOA
A70: 06 | B70: 001 | C70: 04 | D70: 122 | E70: 0001 | F70: 2.011 | G70: 3.3.90.39.00 | H70: =_xlfn.CONCAT(A70,".",B70,".",C70,".",D70,".",E70,".",F70,".",G70) -> 06.001.04.122.0001.2.011.3.3.90.39.00 | I70: 06 - SECRETARIA DE ADMINISTRAÇÃO | J70: 001-GABINETE DA SECRETARIA DE ADMINISTRAÇÃO | K70: 4-ADMINISTRAÇÃO | L70: 122-ADMINISTRAÇÃO GERAL | M70: 0001-Administração e Coordenação Geral​ | N70: 2.011-Manutenção de Equipamentos Públicos | O70: 3.3.90.39.00-OUTROS SERVIÇOS DE TERCEIROS - PESSOA JURÍDICA | P70: MANUTENÇÃO E CONSERVAÇÃO DE VEÍCULOS | R70: 34432 | S70: LOA
A71: 06 | B71: 001 | C71: 04 | D71: 122 | E71: 0001 | F71: 2.011 | G71: 3.3.90.92.00 | H71: =_xlfn.CONCAT(A71,".",B71,".",C71,".",D71,".",E71,".",F71,".",G71) -> 06.001.04.122.0001.2.011.3.3.90.92.00 | I71: 06 - SECRETARIA DE ADMINISTRAÇÃO | J71: 001-GABINETE DA SECRETARIA DE ADMINISTRAÇÃO | K71: 4-ADMINISTRAÇÃO | L71: 122-ADMINISTRAÇÃO GERAL | M71: 0001-Administração e Coordenação Geral​ | N71: 2.011-Manutenção de Equipamentos Públicos | O71: 3.3.90.92.00-DESPESAS DE EXERCÍCIOS ANTERIORES | P71: OUTROS SERVIÇOS DE TERCEIROS - PESSOA JURÍDICA | R71: 1 | S71: LOA
A72: 06 | B72: 001 | C72: 04 | D72: 122 | E72: 0001 | F72: 2.011 | G72: 3.3.90.93.00 | H72: =_xlfn.CONCAT(A72,".",B72,".",C72,".",D72,".",E72,".",F72,".",G72) -> 06.001.04.122.0001.2.011.3.3.90.93.00 | I72: 06 - SECRETARIA DE ADMINISTRAÇÃO | J72: 001-GABINETE DA SECRETARIA DE ADMINISTRAÇÃO | K72: 4-ADMINISTRAÇÃO | L72: 122-ADMINISTRAÇÃO GERAL | M72: 0001-Administração e Coordenação Geral​ | N72: 2.011-Manutenção de Equipamentos Públicos | O72: 3.3.90.93.00-INDENIZAÇÕES E RESTITUIÇÕES | R72: 1 | S72: LOA
A73: 06 | B73: 011 | C73: 04 | D73: 128 | E73: 0002 | F73: 2.003 | G73: 3.3.90.30.00 | H73: =_xlfn.CONCAT(A73,".",B73,".",C73,".",D73,".",E73,".",F73,".",G73) -> 06.011.04.128.0002.2.003.3.3.90.30.00 | I73: 06 - SECRETARIA DE ADMINISTRAÇÃO | J73: 011-FUNDO MUNICIPAL DE VALORIZAÇÃO DOS SERVIDORES | K73: 4-ADMINISTRAÇÃO | L73: 128-FORMAÇÃO DE RECURSOS HUMANOS | M73: 0002-Governo Inteligente, Aberto e Inovador​ | N73: 2.003-Qualificação de Servidores e Processos Institucionais | O73: 3.3.90.30.00-MATERIAL DE CONSUMO | P73: MATERIAL DE EXPEDIENTE | R73: 100000 | S73: LOA
A74: 06 | B74: 011 | C74: 04 | D74: 128 | E74: 0002 | F74: 2.003 | G74: 3.3.90.39.00 | H74: =_xlfn.CONCAT(A74,".",B74,".",C74,".",D74,".",E74,".",F74,".",G74) -> 06.011.04.128.0002.2.003.3.3.90.39.00 | I74: 06 - SECRETARIA DE ADMINISTRAÇÃO | J74: 011-FUNDO MUNICIPAL DE VALORIZAÇÃO DOS SERVIDORES | K74: 4-ADMINISTRAÇÃO | L74: 128-FORMAÇÃO DE RECURSOS HUMANOS | M74: 0002-Governo Inteligente, Aberto e Inovador​ | N74: 2.003-Qualificação de Servidores e Processos Institucionais | O74: 3.3.90.39.00-OUTROS SERVIÇOS DE TERCEIROS - PESSOA JURÍDICA | P74: OUTROS SERVIÇOS DE TERCEIROS - PESSOA JURÍDICA | R74: 100000 | S74: LOA
A75: 06 | B75: 011 | C75: 04 | D75: 128 | E75: 0002 | F75: 2.003 | G75: 3.3.90.40.00 | H75: =_xlfn.CONCAT(A75,".",B75,".",C75,".",D75,".",E75,".",F75,".",G75) -> 06.011.04.128.0002.2.003.3.3.90.40.00 | I75: 06 - SECRETARIA DE ADMINISTRAÇÃO | J75: 011-FUNDO MUNICIPAL DE VALORIZAÇÃO DOS SERVIDORES | K75: 4-ADMINISTRAÇÃO | L75: 128-FORMAÇÃO DE RECURSOS HUMANOS | M75: 0002-Governo Inteligente, Aberto e Inovador​ | N75: 2.003-Qualificação de Servidores e Processos Institucionais | O75: 3.3.90.40.00-SERVIÇOS DE TECNOLOGIA DA INFORMAÇÃO E COMUNICAÇÃO - PESSOA JURÍDICA | P75: OUTROS SERVIÇOS DE TECNOLOGIA DA INFORMAÇÃO E COMUNICAÇÃO - PESSOA JURÍDICA | R75: 100000 | S75: LOA
A76: 06 | B76: 011 | C76: 04 | D76: 128 | E76: 0002 | F76: 2.003 | G76: 4.4.90.52.00 | H76: =_xlfn.CONCAT(A76,".",B76,".",C76,".",D76,".",E76,".",F76,".",G76) -> 06.011.04.128.0002.2.003.4.4.90.52.00 | I76: 06 - SECRETARIA DE ADMINISTRAÇÃO | J76: 011-FUNDO MUNICIPAL DE VALORIZAÇÃO DOS SERVIDORES | K76: 4-ADMINISTRAÇÃO | L76: 128-FORMAÇÃO DE RECURSOS HUMANOS | M76: 0002-Governo Inteligente, Aberto e Inovador​ | N76: 2.003-Qualificação de Servidores e Processos Institucionais | O76: 4.4.90.52.00-EQUIPAMENTOS E MATERIAL PERMANENTE | P76: MÁQUINAS, UTENSÍLIOS E EQUIPAMENTOS DIVERSOS | R76: 100000 | S76: LOA
A77: 07 | B77: 001 | C77: 04 | D77: 122 | E77: 0001 | F77: 2.006 | G77: 3.3.90.33.00 | H77: =_xlfn.CONCAT(A77,".",B77,".",C77,".",D77,".",E77,".",F77,".",G77) -> 07.001.04.122.0001.2.006.3.3.90.33.00 | I77: 07 - SECRETARIA DE EMPREGO, TRABALHO E RENDA | J77: 001-GABINETE DA SECRETARIA DE EMPREGO, TRABALHO E RENDA | K77: 4-ADMINISTRAÇÃO | L77: 122-ADMINISTRAÇÃO GERAL | M77: 0001-Administração e Coordenação Geral​ | N77: 2.006-Representações Oficiais | O77: 3.3.90.33.00-PASSAGENS E DESPESAS COM LOCOMOÇÃO | Q77: 88 | R77: 15000 | S77: LOA
A78: 07 | B78: 001 | C78: 04 | D78: 122 | E78: 0001 | F78: 2.006 | G78: 3.3.90.39.00 | H78: =_xlfn.CONCAT(A78,".",B78,".",C78,".",D78,".",E78,".",F78,".",G78) -> 07.001.04.122.0001.2.006.3.3.90.39.00 | I78: 07 - SECRETARIA DE EMPREGO, TRABALHO E RENDA | J78: 001-GABINETE DA SECRETARIA DE EMPREGO, TRABALHO E RENDA | K78: 4-ADMINISTRAÇÃO | L78: 122-ADMINISTRAÇÃO GERAL | M78: 0001-Administração e Coordenação Geral​ | N78: 2.006-Representações Oficiais | O78: 3.3.90.39.00-OUTROS SERVIÇOS DE TERCEIROS - PESSOA JURÍDICA | P78: OUTROS SERVIÇOS DE TERCEIRO PESSOA JURÍDICA - PAGAMENTO ANTECIPADO | Q78: 89 | R78: 15000 | S78: LOA
A79: 07 | B79: 001 | C79: 04 | D79: 122 | E79: 0002 | F79: 2.003 | G79: 3.3.90.36.00 | H79: =_xlfn.CONCAT(A79,".",B79,".",C79,".",D79,".",E79,".",F79,".",G79) -> 07.001.04.122.0002.2.003.3.3.90.36.00 | I79: 07 - SECRETARIA DE EMPREGO, TRABALHO E RENDA | J79: 001-GABINETE DA SECRETARIA DE EMPREGO, TRABALHO E RENDA | K79: 4-ADMINISTRAÇÃO | L79: 122-ADMINISTRAÇÃO GERAL | M79: 0002-Governo Inteligente, Aberto e Inovador​ | N79: 2.003-Qualificação de Servidores e Processos Institucionais | O79: 3.3.90.36.00-OUTROS SERVIÇOS DE TERCEIROS - PESSOA FÍSICA | Q79: 90 | R79: 1 | S79: LOA
A80: 07 | B80: 001 | C80: 04 | D80: 122 | E80: 0002 | F80: 2.003 | G80: 3.3.90.39.00 | H80: =_xlfn.CONCAT(A80,".",B80,".",C80,".",D80,".",E80,".",F80,".",G80) -> 07.001.04.122.0002.2.003.3.3.90.39.00 | I80: 07 - SECRETARIA DE EMPREGO, TRABALHO E RENDA | J80: 001-GABINETE DA SECRETARIA DE EMPREGO, TRABALHO E RENDA | K80: 4-ADMINISTRAÇÃO | L80: 122-ADMINISTRAÇÃO GERAL | M80: 0002-Governo Inteligente, Aberto e Inovador​ | N80: 2.003-Qualificação de Servidores e Processos Institucionais | O80: 3.3.90.39.00-OUTROS SERVIÇOS DE TERCEIROS - PESSOA JURÍDICA | P80: OUTROS SERVIÇOS DE TERCEIRO PESSOA JURÍDICA - PAGAMENTO ANTECIPADO | Q80: 91 | R80: 1 | S80: LOA
A81: 07 | B81: 001 | C81: 04 | D81: 122 | E81: 0002 | F81: 2.005 | G81: 3.3.90.30.00 | H81: =_xlfn.CONCAT(A81,".",B81,".",C81,".",D81,".",E81,".",F81,".",G81) -> 07.001.04.122.0002.2.005.3.3.90.30.00 | I81: 07 - SECRETARIA DE EMPREGO, TRABALHO E RENDA | J81: 001-GABINETE DA SECRETARIA DE EMPREGO, TRABALHO E RENDA | K81: 4-ADMINISTRAÇÃO | L81: 122-ADMINISTRAÇÃO GERAL | M81: 0002-Governo Inteligente, Aberto e Inovador​ | N81: 2.005-Promoção de Eventos, Comunicação e Participação Social | O81: 3.3.90.30.00-MATERIAL DE CONSUMO | P81: GÊNEROS DE ALIMENTAÇÃO | Q81: 92 | S81: LOA
A82: 07 | B82: 001 | C82: 04 | D82: 122 | E82: 0002 | F82: 2.005 | G82: 3.3.90.39.00 | H82: =_xlfn.CONCAT(A82,".",B82,".",C82,".",D82,".",E82,".",F82,".",G82) -> 07.001.04.122.0002.2.005.3.3.90.39.00 | I82: 07 - SECRETARIA DE EMPREGO, TRABALHO E RENDA | J82: 001-GABINETE DA SECRETARIA DE EMPREGO, TRABALHO E RENDA | K82: 4-ADMINISTRAÇÃO | L82: 122-ADMINISTRAÇÃO GERAL | M82: 0002-Governo Inteligente, Aberto e Inovador​ | N82: 2.005-Promoção de Eventos, Comunicação e Participação Social | O82: 3.3.90.39.00-OUTROS SERVIÇOS DE TERCEIROS - PESSOA JURÍDICA | P82: SERVIÇOS GRÁFICOS E EDITORIAIS | Q82: 93 | S82: LOA
A83: 07 | B83: 001 | C83: 11 | D83: 334 | E83: 0017 | F83: 1.002 | G83: 3.3.90.39.00 | H83: =_xlfn.CONCAT(A83,".",B83,".",C83,".",D83,".",E83,".",F83,".",G83) -> 07.001.11.334.0017.1.002.3.3.90.39.00 | I83: 07 - SECRETARIA DE EMPREGO, TRABALHO E RENDA | J83: 001-GABINETE DA SECRETARIA DE EMPREGO, TRABALHO E RENDA | K83: 11-TRABALHO | L83: 334-FOMENTO AO TRABALHO | M83: 0017-Trabalho, Emprego e Renda​ | N83: 1.002-Reforma e Ampliação de Unidades | O83: 3.3.90.39.00-OUTROS SERVIÇOS DE TERCEIROS - PESSOA JURÍDICA | P83: OUTROS SERVIÇOS DE TERCEIRO PESSOA JURÍDICA - PAGAMENTO ANTECIPADO | Q83: 94 | S83: LOA
A84: 07 | B84: 001 | C84: 11 | D84: 334 | E84: 0017 | F84: 2.011 | G84: 3.3.90.30.00 | H84: =_xlfn.CONCAT(A84,".",B84,".",C84,".",D84,".",E84,".",F84,".",G84) -> 07.001.11.334.0017.2.011.3.3.90.30.00 | I84: 07 - SECRETARIA DE EMPREGO, TRABALHO E RENDA | J84: 001-GABINETE DA SECRETARIA DE EMPREGO, TRABALHO E RENDA | K84: 11-TRABALHO | L84: 334-FOMENTO AO TRABALHO | M84: 0017-Trabalho, Emprego e Renda​ | N84: 2.011-Manutenção de Equipamentos Públicos | O84: 3.3.90.30.00-MATERIAL DE CONSUMO | P84: GÊNEROS DE ALIMENTAÇÃO | Q84: 95 | R84: 15000 | S84: LOA
A85: 07 | B85: 001 | C85: 11 | D85: 334 | E85: 0017 | F85: 2.011 | G85: 3.3.90.30.00 | H85: =_xlfn.CONCAT(A85,".",B85,".",C85,".",D85,".",E85,".",F85,".",G85) -> 07.001.11.334.0017.2.011.3.3.90.30.00 | I85: 07 - SECRETARIA DE EMPREGO, TRABALHO E RENDA | J85: 001-GABINETE DA SECRETARIA DE EMPREGO, TRABALHO E RENDA | K85: 11-TRABALHO | L85: 334-FOMENTO AO TRABALHO | M85: 0017-Trabalho, Emprego e Renda​ | N85: 2.011-Manutenção de Equipamentos Públicos | O85: 3.3.90.30.00-MATERIAL DE CONSUMO | P85: MATERIAL DE LIMPEZA E PRODUTOS DE HIGIENIZAÇÃO | Q85: 95 | R85: 60000 | S85: LOA
A86: 07 | B86: 001 | C86: 11 | D86: 334 | E86: 0017 | F86: 2.011 | G86: 3.3.90.30.00 | H86: =_xlfn.CONCAT(A86,".",B86,".",C86,".",D86,".",E86,".",F86,".",G86) -> 07.001.11.334.0017.2.011.3.3.90.30.00 | I86: 07 - SECRETARIA DE EMPREGO, TRABALHO E RENDA | J86: 001-GABINETE DA SECRETARIA DE EMPREGO, TRABALHO E RENDA | K86: 11-TRABALHO | L86: 334-FOMENTO AO TRABALHO | M86: 0017-Trabalho, Emprego e Renda​ | N86: 2.011-Manutenção de Equipamentos Públicos | O86: 3.3.90.30.00-MATERIAL DE CONSUMO | P86: MATERIAL DE EXPEDIENTE | Q86: 95 | R86: 50000 | S86: LOA
A87: 07 | B87: 001 | C87: 11 | D87: 334 | E87: 0017 | F87: 2.011 | G87: 3.3.90.30.00 | H87: =_xlfn.CONCAT(A87,".",B87,".",C87,".",D87,".",E87,".",F87,".",G87) -> 07.001.11.334.0017.2.011.3.3.90.30.00 | I87: 07 - SECRETARIA DE EMPREGO, TRABALHO E RENDA | J87: 001-GABINETE DA SECRETARIA DE EMPREGO, TRABALHO E RENDA | K87: 11-TRABALHO | L87: 334-FOMENTO AO TRABALHO | M87: 0017-Trabalho, Emprego e Renda​ | N87: 2.011-Manutenção de Equipamentos Públicos | O87: 3.3.90.30.00-MATERIAL DE CONSUMO | P87: MATERIAL DE COPA E COZINHA | Q87: 95 | R87: 40000 | S87: LOA
A88: 07 | B88: 001 | C88: 11 | D88: 334 | E88: 0017 | F88: 2.011 | G88: 3.3.90.30.00 | H88: =_xlfn.CONCAT(A88,".",B88,".",C88,".",D88,".",E88,".",F88,".",G88) -> 07.001.11.334.0017.2.011.3.3.90.30.00 | I88: 07 - SECRETARIA DE EMPREGO, TRABALHO E RENDA | J88: 001-GABINETE DA SECRETARIA DE EMPREGO, TRABALHO E RENDA | K88: 11-TRABALHO | L88: 334-FOMENTO AO TRABALHO | M88: 0017-Trabalho, Emprego e Renda​ | N88: 2.011-Manutenção de Equipamentos Públicos | O88: 3.3.90.30.00-MATERIAL DE CONSUMO | P88: MATERIAL ELÉTRICO E ELETRÔNICO | Q88: 95 | R88: 15000 | S88: LOA
A89: 07 | B89: 001 | C89: 11 | D89: 334 | E89: 0017 | F89: 2.011 | G89: 3.3.90.39.00 | H89: =_xlfn.CONCAT(A89,".",B89,".",C89,".",D89,".",E89,".",F89,".",G89) -> 07.001.11.334.0017.2.011.3.3.90.39.00 | I89: 07 - SECRETARIA DE EMPREGO, TRABALHO E RENDA | J89: 001-GABINETE DA SECRETARIA DE EMPREGO, TRABALHO E RENDA | K89: 11-TRABALHO | L89: 334-FOMENTO AO TRABALHO | M89: 0017-Trabalho, Emprego e Renda​ | N89: 2.011-Manutenção de Equipamentos Públicos | O89: 3.3.90.39.00-OUTROS SERVIÇOS DE TERCEIROS - PESSOA JURÍDICA | P89: SERVIÇOS GRÁFICOS E EDITORIAIS | Q89: 0 | R89: 80000 | S89: LOA
A90: 07 | B90: 001 | C90: 11 | D90: 334 | E90: 0017 | F90: 2.011 | G90: 3.3.90.39.00 | H90: =_xlfn.CONCAT(A90,".",B90,".",C90,".",D90,".",E90,".",F90,".",G90) -> 07.001.11.334.0017.2.011.3.3.90.39.00 | I90: 07 - SECRETARIA DE EMPREGO, TRABALHO E RENDA | J90: 001-GABINETE DA SECRETARIA DE EMPREGO, TRABALHO E RENDA | K90: 11-TRABALHO | L90: 334-FOMENTO AO TRABALHO | M90: 0017-Trabalho, Emprego e Renda​ | N90: 2.011-Manutenção de Equipamentos Públicos | O90: 3.3.90.39.00-OUTROS SERVIÇOS DE TERCEIROS - PESSOA JURÍDICA | P90: OUTROS SERVIÇOS DE TERCEIRO PESSOA JURÍDICA - PAGAMENTO ANTECIPADO | Q90: 0 | R90: 120000 | S90: LOA
A91: 07 | B91: 001 | C91: 11 | D91: 334 | E91: 0017 | F91: 2.011 | G91: 4.4.90.52.00 | H91: =_xlfn.CONCAT(A91,".",B91,".",C91,".",D91,".",E91,".",F91,".",G91) -> 07.001.11.334.0017.2.011.4.4.90.52.00 | I91: 07 - SECRETARIA DE EMPREGO, TRABALHO E RENDA | J91: 001-GABINETE DA SECRETARIA DE EMPREGO, TRABALHO E RENDA | K91: 11-TRABALHO | L91: 334-FOMENTO AO TRABALHO | M91: 0017-Trabalho, Emprego e Renda​ | N91: 2.011-Manutenção de Equipamentos Públicos | O91: 4.4.90.52.00-EQUIPAMENTOS E MATERIAL PERMANENTE | P91: APARELHOS E UTENSÍLIOS DOMÉSTICOS | Q91: 0 | R91: 35000 | S91: LOA
A92: 07 | B92: 001 | C92: 11 | D92: 334 | E92: 0017 | F92: 2.011 | G92: 4.4.90.52.00 | H92: =_xlfn.CONCAT(A92,".",B92,".",C92,".",D92,".",E92,".",F92,".",G92) -> 07.001.11.334.0017.2.011.4.4.90.52.00 | I92: 07 - SECRETARIA DE EMPREGO, TRABALHO E RENDA | J92: 001-GABINETE DA SECRETARIA DE EMPREGO, TRABALHO E RENDA | K92: 11-TRABALHO | L92: 334-FOMENTO AO TRABALHO | M92: 0017-Trabalho, Emprego e Renda​ | N92: 2.011-Manutenção de Equipamentos Públicos | O92: 4.4.90.52.00-EQUIPAMENTOS E MATERIAL PERMANENTE | P92: VEÍCULOS DE TRAÇÃO MECÂNICA | Q92: 0 | R92: 150000 | S92: LOA
A93: 07 | B93: 001 | C93: 11 | D93: 333 | E93: 0017 | F93: 2.027 | G93: 3.3.90.30.00 | H93: =_xlfn.CONCAT(A93,".",B93,".",C93,".",D93,".",E93,".",F93,".",G93) -> 07.001.11.333.0017.2.027.3.3.90.30.00 | I93: 07 - SECRETARIA DE EMPREGO, TRABALHO E RENDA | J93: 001-GABINETE DA SECRETARIA DE EMPREGO, TRABALHO E RENDA | K93: 11-TRABALHO | L93: 333-EMPREGABILIDADE | M93: 0017-Trabalho, Emprego e Renda​ | N93: 2.027-Intermediação Profissional | O93: 3.3.90.30.00-MATERIAL DE CONSUMO | P93: GÊNEROS DE ALIMENTAÇÃO | Q93: 0 | R93: 10000 | S93: LOA
A94: 07 | B94: 001 | C94: 11 | D94: 333 | E94: 0017 | F94: 2.027 | G94: 3.3.90.39.00 | H94: =_xlfn.CONCAT(A94,".",B94,".",C94,".",D94,".",E94,".",F94,".",G94) -> 07.001.11.333.0017.2.027.3.3.90.39.00 | I94: 07 - SECRETARIA DE EMPREGO, TRABALHO E RENDA | J94: 001-GABINETE DA SECRETARIA DE EMPREGO, TRABALHO E RENDA | K94: 11-TRABALHO | L94: 333-EMPREGABILIDADE | M94: 0017-Trabalho, Emprego e Renda​ | N94: 2.027-Intermediação Profissional | O94: 3.3.90.39.00-OUTROS SERVIÇOS DE TERCEIROS - PESSOA JURÍDICA | P94: OUTROS SERVIÇOS DE TERCEIRO PESSOA JURÍDICA - PAGAMENTO ANTECIPADO | Q94: 14533/2021 | R94: 16069995 | S94: LOA
A95: 07 | B95: 001 | C95: 11 | D95: 333 | E95: 0017 | F95: 2.027 | G95: 3.3.90.39.00 | H95: =_xlfn.CONCAT(A95,".",B95,".",C95,".",D95,".",E95,".",F95,".",G95) -> 07.001.11.333.0017.2.027.3.3.90.39.00 | I95: 07 - SECRETARIA DE EMPREGO, TRABALHO E RENDA | J95: 001-GABINETE DA SECRETARIA DE EMPREGO, TRABALHO E RENDA | K95: 11-TRABALHO | L95: 333-EMPREGABILIDADE | M95: 0017-Trabalho, Emprego e Renda​ | N95: 2.027-Intermediação Profissional | O95: 3.3.90.39.00-OUTROS SERVIÇOS DE TERCEIROS - PESSOA JURÍDICA | P95: SERVIÇOS GRÁFICOS E EDITORIAIS | Q95: 0 | R95: 30000 | S95: LOA
A96: 07 | B96: 001 | C96: 11 | D96: 333 | E96: 0017 | F96: 2.027 | G96: 3.3.90.39.00 | H96: =_xlfn.CONCAT(A96,".",B96,".",C96,".",D96,".",E96,".",F96,".",G96) -> 07.001.11.333.0017.2.027.3.3.90.39.00 | I96: 07 - SECRETARIA DE EMPREGO, TRABALHO E RENDA | J96: 001-GABINETE DA SECRETARIA DE EMPREGO, TRABALHO E RENDA | K96: 11-TRABALHO | L96: 333-EMPREGABILIDADE | M96: 0017-Trabalho, Emprego e Renda​ | N96: 2.027-Intermediação Profissional | O96: 3.3.90.39.00-OUTROS SERVIÇOS DE TERCEIROS - PESSOA JURÍDICA | P96: FORNECIMENTO DE ALIMENTAÇÃO | Q96: 0 | R96: 15000 | S96: LOA
A97: 07 | B97: 001 | C97: 11 | D97: 333 | E97: 0017 | F97: 2.027 | G97: 3.3.90.39.00 | H97: =_xlfn.CONCAT(A97,".",B97,".",C97,".",D97,".",E97,".",F97,".",G97) -> 07.001.11.333.0017.2.027.3.3.90.39.00 | I97: 07 - SECRETARIA DE EMPREGO, TRABALHO E RENDA | J97: 001-GABINETE DA SECRETARIA DE EMPREGO, TRABALHO E RENDA | K97: 11-TRABALHO | L97: 333-EMPREGABILIDADE | M97: 0017-Trabalho, Emprego e Renda​ | N97: 2.027-Intermediação Profissional | O97: 3.3.90.39.00-OUTROS SERVIÇOS DE TERCEIROS - PESSOA JURÍDICA | P97: SERVIÇOS DE PUBLICIDADE E PROPAGANDA | Q97: 0 | R97: 15000 | S97: LOA
A98: 07 | B98: 001 | C98: 11 | D98: 333 | E98: 0017 | F98: 2.027 | G98: 4.4.90.52.00 | H98: =_xlfn.CONCAT(A98,".",B98,".",C98,".",D98,".",E98,".",F98,".",G98) -> 07.001.11.333.0017.2.027.4.4.90.52.00 | I98: 07 - SECRETARIA DE EMPREGO, TRABALHO E RENDA | J98: 001-GABINETE DA SECRETARIA DE EMPREGO, TRABALHO E RENDA | K98: 11-TRABALHO | L98: 333-EMPREGABILIDADE | M98: 0017-Trabalho, Emprego e Renda​ | N98: 2.027-Intermediação Profissional | O98: 4.4.90.52.00-EQUIPAMENTOS E MATERIAL PERMANENTE | P98: VEÍCULOS DE TRAÇÃO MECÂNICA | Q98: 0 | R98: 150000 | S98: LOA
A99: 07 | B99: 001 | C99: 11 | D99: 333 | E99: 0017 | F99: 2.004 | G99: 3.3.50.39.00 | H99: =_xlfn.CONCAT(A99,".",B99,".",C99,".",D99,".",E99,".",F99,".",G99) -> 07.001.11.333.0017.2.004.3.3.50.39.00 | I99: 07 - SECRETARIA DE EMPREGO, TRABALHO E RENDA | J99: 001-GABINETE DA SECRETARIA DE EMPREGO, TRABALHO E RENDA | K99: 11-TRABALHO | L99: 333-EMPREGABILIDADE | M99: 0017-Trabalho, Emprego e Renda​ | N99: 2.004-Qualificação Socioprofissional | O99: 3.3.50.39.00-OUTROS SERVIÇOS DE TERCEIROS - PESSOA JURÍDICA | P99: TERMO DE COLABORAÇÃO | Q99: 2967/2025 | R99: 2834440 | S99: LOA
A100: 07 | B100: 001 | C100: 11 | D100: 333 | E100: 0017 | F100: 2.004 | G100: 3.3.90.30.00 | H100: =_xlfn.CONCAT(A100,".",B100,".",C100,".",D100,".",E100,".",F100,".",G100) -> 07.001.11.333.0017.2.004.3.3.90.30.00 | I100: 07 - SECRETARIA DE EMPREGO, TRABALHO E RENDA | J100: 001-GABINETE DA SECRETARIA DE EMPREGO, TRABALHO E RENDA | K100: 11-TRABALHO | L100: 333-EMPREGABILIDADE | M100: 0017-Trabalho, Emprego e Renda​ | N100: 2.004-Qualificação Socioprofissional | O100: 3.3.90.30.00-MATERIAL DE CONSUMO | P100: MATERIAL DE EXPEDIENTE | Q100: 0 | R100: 45000 | S100: LOA
A101: 07 | B101: 001 | C101: 11 | D101: 333 | E101: 0017 | F101: 2.004 | G101: 3.3.90.39.00 | H101: =_xlfn.CONCAT(A101,".",B101,".",C101,".",D101,".",E101,".",F101,".",G101) -> 07.001.11.333.0017.2.004.3.3.90.39.00 | I101: 07 - SECRETARIA DE EMPREGO, TRABALHO E RENDA | J101: 001-GABINETE DA SECRETARIA DE EMPREGO, TRABALHO E RENDA | K101: 11-TRABALHO | L101: 333-EMPREGABILIDADE | M101: 0017-Trabalho, Emprego e Renda​ | N101: 2.004-Qualificação Socioprofissional | O101: 3.3.90.39.00-OUTROS SERVIÇOS DE TERCEIROS - PESSOA JURÍDICA | P101: SERVIÇOS GRÁFICOS E EDITORIAIS | Q101: 0 | R101: 30000 | S101: LOA
A102: 07 | B102: 001 | C102: 11 | D102: 333 | E102: 0017 | F102: 2.004 | G102: 3.3.90.39.00 | H102: =_xlfn.CONCAT(A102,".",B102,".",C102,".",D102,".",E102,".",F102,".",G102) -> 07.001.11.333.0017.2.004.3.3.90.39.00 | I102: 07 - SECRETARIA DE EMPREGO, TRABALHO E RENDA | J102: 001-GABINETE DA SECRETARIA DE EMPREGO, TRABALHO E RENDA | K102: 11-TRABALHO | L102: 333-EMPREGABILIDADE | M102: 0017-Trabalho, Emprego e Renda​ | N102: 2.004-Qualificação Socioprofissional | O102: 3.3.90.39.00-OUTROS SERVIÇOS DE TERCEIROS - PESSOA JURÍDICA | P102: FORNECIMENTO DE ALIMENTAÇÃO | Q102: 0 | R102: 30000 | S102: LOA
A103: 07 | B103: 001 | C103: 11 | D103: 333 | E103: 0017 | F103: 2.004 | G103: 3.3.90.39.00 | H103: =_xlfn.CONCAT(A103,".",B103,".",C103,".",D103,".",E103,".",F103,".",G103) -> 07.001.11.333.0017.2.004.3.3.90.39.00 | I103: 07 - SECRETARIA DE EMPREGO, TRABALHO E RENDA | J103: 001-GABINETE DA SECRETARIA DE EMPREGO, TRABALHO E RENDA | K103: 11-TRABALHO | L103: 333-EMPREGABILIDADE | M103: 0017-Trabalho, Emprego e Renda​ | N103: 2.004-Qualificação Socioprofissional | O103: 3.3.90.39.00-OUTROS SERVIÇOS DE TERCEIROS - PESSOA JURÍDICA | P103: OUTROS SERVIÇOS DE TERCEIRO PESSOA JURÍDICA - PAGAMENTO ANTECIPADO | Q103: 0 | R103: 30000 | S103: LOA
A104: 07 | B104: 001 | C104: 11 | D104: 334 | E104: 0017 | F104: 2.033 | G104: 3.3.90.30.00 | H104: =_xlfn.CONCAT(A104,".",B104,".",C104,".",D104,".",E104,".",F104,".",G104) -> 07.001.11.334.0017.2.033.3.3.90.30.00 | I104: 07 - SECRETARIA DE EMPREGO, TRABALHO E RENDA | J104: 001-GABINETE DA SECRETARIA DE EMPREGO, TRABALHO E RENDA | K104: 11-TRABALHO | L104: 334-FOMENTO AO TRABALHO | M104: 0017-Trabalho, Emprego e Renda​ | N104: 2.033-Fortalecimento da Economia Criativa e Solidária | O104: 3.3.90.30.00-MATERIAL DE CONSUMO | P104: MATERIAL PARA MANUTENÇÃO DE BENS IMÓVEIS | Q104: 102 | R104: 63200 | S104: LOA
A105: 07 | B105: 001 | C105: 11 | D105: 334 | E105: 0017 | F105: 2.033 | G105: 3.3.90.30.00 | H105: =_xlfn.CONCAT(A105,".",B105,".",C105,".",D105,".",E105,".",F105,".",G105) -> 07.001.11.334.0017.2.033.3.3.90.30.00 | I105: 07 - SECRETARIA DE EMPREGO, TRABALHO E RENDA | J105: 001-GABINETE DA SECRETARIA DE EMPREGO, TRABALHO E RENDA | K105: 11-TRABALHO | L105: 334-FOMENTO AO TRABALHO | M105: 0017-Trabalho, Emprego e Renda​ | N105: 2.033-Fortalecimento da Economia Criativa e Solidária | O105: 3.3.90.30.00-MATERIAL DE CONSUMO | P105: FERRAMENTAS | Q105: 102 | R105: 30000 | S105: LOA
A106: 07 | B106: 001 | C106: 11 | D106: 334 | E106: 0017 | F106: 2.033 | G106: 3.3.90.39.00 | H106: =_xlfn.CONCAT(A106,".",B106,".",C106,".",D106,".",E106,".",F106,".",G106) -> 07.001.11.334.0017.2.033.3.3.90.39.00 | I106: 07 - SECRETARIA DE EMPREGO, TRABALHO E RENDA | J106: 001-GABINETE DA SECRETARIA DE EMPREGO, TRABALHO E RENDA | K106: 11-TRABALHO | L106: 334-FOMENTO AO TRABALHO | M106: 0017-Trabalho, Emprego e Renda​ | N106: 2.033-Fortalecimento da Economia Criativa e Solidária | O106: 3.3.90.39.00-OUTROS SERVIÇOS DE TERCEIROS - PESSOA JURÍDICA | P106: FORNECIMENTO DE ALIMENTAÇÃO | Q106: 103 | R106: 20000 | S106: LOA
A107: 07 | B107: 001 | C107: 11 | D107: 334 | E107: 0017 | F107: 2.033 | G107: 3.3.90.39.00 | H107: =_xlfn.CONCAT(A107,".",B107,".",C107,".",D107,".",E107,".",F107,".",G107) -> 07.001.11.334.0017.2.033.3.3.90.39.00 | I107: 07 - SECRETARIA DE EMPREGO, TRABALHO E RENDA | J107: 001-GABINETE DA SECRETARIA DE EMPREGO, TRABALHO E RENDA | K107: 11-TRABALHO | L107: 334-FOMENTO AO TRABALHO | M107: 0017-Trabalho, Emprego e Renda​ | N107: 2.033-Fortalecimento da Economia Criativa e Solidária | O107: 3.3.90.39.00-OUTROS SERVIÇOS DE TERCEIROS - PESSOA JURÍDICA | P107: FESTIVIDADES E HOMENAGENS | Q107: 103 | R107: 15000 | S107: LOA
A108: 07 | B108: 001 | C108: 11 | D108: 334 | E108: 0017 | F108: 2.033 | G108: 3.3.90.39.00 | H108: =_xlfn.CONCAT(A108,".",B108,".",C108,".",D108,".",E108,".",F108,".",G108) -> 07.001.11.334.0017.2.033.3.3.90.39.00 | I108: 07 - SECRETARIA DE EMPREGO, TRABALHO E RENDA | J108: 001-GABINETE DA SECRETARIA DE EMPREGO, TRABALHO E RENDA | K108: 11-TRABALHO | L108: 334-FOMENTO AO TRABALHO | M108: 0017-Trabalho, Emprego e Renda​ | N108: 2.033-Fortalecimento da Economia Criativa e Solidária | O108: 3.3.90.39.00-OUTROS SERVIÇOS DE TERCEIROS - PESSOA JURÍDICA | P108: SERVIÇOS GRÁFICOS E EDITORIAIS | Q108: 103 | R108: 25000 | S108: LOA
A109: 07 | B109: 001 | C109: 11 | D109: 334 | E109: 0017 | F109: 2.033 | G109: 4.4.90.52.00 | H109: =_xlfn.CONCAT(A109,".",B109,".",C109,".",D109,".",E109,".",F109,".",G109) -> 07.001.11.334.0017.2.033.4.4.90.52.00 | I109: 07 - SECRETARIA DE EMPREGO, TRABALHO E RENDA | J109: 001-GABINETE DA SECRETARIA DE EMPREGO, TRABALHO E RENDA | K109: 11-TRABALHO | L109: 334-FOMENTO AO TRABALHO | M109: 0017-Trabalho, Emprego e Renda​ | N109: 2.033-Fortalecimento da Economia Criativa e Solidária | O109: 4.4.90.52.00-EQUIPAMENTOS E MATERIAL PERMANENTE | P109: MÁQUINAS, UTENSÍLIOS E EQUIPAMENTOS DIVERSOS | Q109: 0 | R109: 40000 | S109: LOA
A110: 07 | B110: 001 | C110: 11 | D110: 334 | E110: 0017 | F110: 2.027 | G110: 3.3.90.30.00 | H110: =_xlfn.CONCAT(A110,".",B110,".",C110,".",D110,".",E110,".",F110,".",G110) -> 07.001.11.334.0017.2.027.3.3.90.30.00 | I110: 07 - SECRETARIA DE EMPREGO, TRABALHO E RENDA | J110: 001-FUNDO MUNICIPAL DO TRABALHO | K110: 11-TRABALHO | L110: 334-FOMENTO AO TRABALHO | M110: 0017-Trabalho, Emprego e Renda​ | N110: 2.027-Intermediação Profissional | O110: 3.3.90.30.00-MATERIAL DE CONSUMO | P110: MATERIAL PARA MANUTENÇÃO DE BENS IMÓVEIS | Q110: 0 | R110: 1 | S110: LOA
...

Sheet LDO 2027
A1: PROGRAMÁTICA | B1: VALOR FINAL PLDO 27 | C1: DS_INICIATIVA | D1: Programática LDO | E1: Secretaria | F1: Ação
A2: 01.001.01.031.0003.1.003.3.3.90.39.01.110.0000 | B2: 2000000 | C2: Construção da Nova Sede da Câmara | D2: =_xlfn.CONCAT(LEFT(A2,34),".00") -> 01.001.01.031.0003.1.003.3.3.90.39.00 | E2: =VLOOKUP(LEFT(A2,2),ConsolidadoLoa27_ATIVIDADES!A:I,9,0) -> 01- CMO | F2: =MID(A2,20,5) -> 1.003 | G2: =RIGHT(A2,11) -> 01.110.0000
A3: 01.001.01.031.0003.1.003.3.3.90.92.01.110.0000 | B3: 1 | C3: Construção da Nova Sede da Câmara | D3: =_xlfn.CONCAT(LEFT(A3,34),".00") -> 01.001.01.031.0003.1.003.3.3.90.92.00 | E3: =VLOOKUP(LEFT(A3,2),ConsolidadoLoa27_ATIVIDADES!A:I,9,0) -> 01- CMO | F3: =MID(A3,20,5) -> 1.003 | G3: =RIGHT(A3,11) -> 01.110.0000
A4: 01.001.01.031.0003.1.003.3.3.90.93.01.110.0000 | B4: 1 | C4: Construção da Nova Sede da Câmara | D4: =_xlfn.CONCAT(LEFT(A4,34),".00") -> 01.001.01.031.0003.1.003.3.3.90.93.00 | E4: =VLOOKUP(LEFT(A4,2),ConsolidadoLoa27_ATIVIDADES!A:I,9,0) -> 01- CMO | F4: =MID(A4,20,5) -> 1.003 | G4: =RIGHT(A4,11) -> 01.110.0000
A5: 01.001.01.031.0003.1.003.4.4.90.51.01.110.0000 | B5: 1000000 | C5: Construção da Nova Sede da Câmara | D5: =_xlfn.CONCAT(LEFT(A5,34),".00") -> 01.001.01.031.0003.1.003.4.4.90.51.00 | E5: =VLOOKUP(LEFT(A5,2),ConsolidadoLoa27_ATIVIDADES!A:I,9,0) -> 01- CMO | F5: =MID(A5,20,5) -> 1.003 | G5: =RIGHT(A5,11) -> 01.110.0000
A6: 01.001.01.031.0003.1.003.4.4.90.52.01.110.0000 | B6: 3500000 | C6: Construção da Nova Sede da Câmara | D6: =_xlfn.CONCAT(LEFT(A6,34),".00") -> 01.001.01.031.0003.1.003.4.4.90.52.00 | E6: =VLOOKUP(LEFT(A6,2),ConsolidadoLoa27_ATIVIDADES!A:I,9,0) -> 01- CMO | F6: =MID(A6,20,5) -> 1.003 | G6: =RIGHT(A6,11) -> 01.110.0000
A7: 01.001.01.031.0003.1.003.4.4.90.92.01.110.0000 | B7: 1 | C7: Construção da Nova Sede da Câmara | D7: =_xlfn.CONCAT(LEFT(A7,34),".00") -> 01.001.01.031.0003.1.003.4.4.90.92.00 | E7: =VLOOKUP(LEFT(A7,2),ConsolidadoLoa27_ATIVIDADES!A:I,9,0) -> 01- CMO | F7: =MID(A7,20,5) -> 1.003 | G7: =RIGHT(A7,11) -> 01.110.0000
A8: 01.001.01.031.0003.2.042.3.3.90.14.01.110.0000 | B8: 1 | C8: Manutenção das Atividades Legislativas | D8: =_xlfn.CONCAT(LEFT(A8,34),".00") -> 01.001.01.031.0003.2.042.3.3.90.14.00 | E8: =VLOOKUP(LEFT(A8,2),ConsolidadoLoa27_ATIVIDADES!A:I,9,0) -> 01- CMO | F8: =MID(A8,20,5) -> 2.042 | G8: =RIGHT(A8,11) -> 01.110.0000
A9: 01.001.01.031.0003.2.042.3.3.90.30.01.110.0000 | B9: 1575000 | C9: Manutenção das Atividades Legislativas | D9: =_xlfn.CONCAT(LEFT(A9,34),".00") -> 01.001.01.031.0003.2.042.3.3.90.30.00 | E9: =VLOOKUP(LEFT(A9,2),ConsolidadoLoa27_ATIVIDADES!A:I,9,0) -> 01- CMO | F9: =MID(A9,20,5) -> 2.042 | G9: =RIGHT(A9,11) -> 01.110.0000
A10: 01.001.01.031.0003.2.042.3.3.90.32.01.110.0000 | B10: 1 | C10: Manutenção das Atividades Legislativas | D10: =_xlfn.CONCAT(LEFT(A10,34),".00") -> 01.001.01.031.0003.2.042.3.3.90.32.00 | E10: =VLOOKUP(LEFT(A10,2),ConsolidadoLoa27_ATIVIDADES!A:I,9,0) -> 01- CMO | F10: =MID(A10,20,5) -> 2.042 | G10: =RIGHT(A10,11) -> 01.110.0000
A11: 01.001.01.031.0003.2.042.3.3.90.33.01.110.0000 | B11: 1 | C11: Manutenção das Atividades Legislativas | D11: =_xlfn.CONCAT(LEFT(A11,34),".00") -> 01.001.01.031.0003.2.042.3.3.90.33.00 | E11: =VLOOKUP(LEFT(A11,2),ConsolidadoLoa27_ATIVIDADES!A:I,9,0) -> 01- CMO | F11: =MID(A11,20,5) -> 2.042 | G11: =RIGHT(A11,11) -> 01.110.0000
A12: 01.001.01.031.0003.2.042.3.3.90.35.01.110.0000 | B12: 1 | C12: Manutenção das Atividades Legislativas | D12: =_xlfn.CONCAT(LEFT(A12,34),".00") -> 01.001.01.031.0003.2.042.3.3.90.35.00 | E12: =VLOOKUP(LEFT(A12,2),ConsolidadoLoa27_ATIVIDADES!A:I,9,0) -> 01- CMO | F12: =MID(A12,20,5) -> 2.042 | G12: =RIGHT(A12,11) -> 01.110.0000
A13: 01.001.01.031.0003.2.042.3.3.90.37.01.110.0000 | B13: 1 | C13: Manutenção das Atividades Legislativas | D13: =_xlfn.CONCAT(LEFT(A13,34),".00") -> 01.001.01.031.0003.2.042.3.3.90.37.00 | E13: =VLOOKUP(LEFT(A13,2),ConsolidadoLoa27_ATIVIDADES!A:I,9,0) -> 01- CMO | F13: =MID(A13,20,5) -> 2.042 | G13: =RIGHT(A13,11) -> 01.110.0000
... A279: 08.001.12.122.0001.2.008.3.3.90.39.01.200.0000 | B279: 493440 | C279: Estagiários - Ensino Superior SED - Taxa | D279: =_xlfn.CONCAT(LEFT(A279,34),".00") -> 08.001.12.122.0001.2.008.3.3.90.39.00 | E279: =VLOOKUP(LEFT(A279,2),ConsolidadoLoa27_ATIVIDADES!A:I,9,0) -> 08 - SECRETARIA DE EDUCAÇÃO | F279: =MID(A279,20,5) -> 2.008 | G279: =RIGHT(A279,11) -> 01.200.0000
A280: 08.001.12.122.0001.2.008.3.3.90.48.01.110.0000 | C280: Estagiários Ensino Superior - SED | D280: =_xlfn.CONCAT(LEFT(A280,34),".00") -> 08.001.12.122.0001.2.008.3.3.90.48.00 | E280: =VLOOKUP(LEFT(A280,2),ConsolidadoLoa27_ATIVIDADES!A:I,9,0) -> 08 - SECRETARIA DE EDUCAÇÃO | F280: =MID(A280,20,5) -> 2.008 | G280: =RIGHT(A280,11) -> 01.110.0000
A281: 08.001.12.122.0001.2.008.3.3.90.48.01.200.0000 | B281: 16964195 | C281: Estagiários Ensino Superior - SED | D281: =_xlfn.CONCAT(LEFT(A281,34),".00") -> 08.001.12.122.0001.2.008.3.3.90.48.00 | E281: =VLOOKUP(LEFT(A281,2),ConsolidadoLoa27_ATIVIDADES!A:I,9,0) -> 08 - SECRETARIA DE EDUCAÇÃO | F281: =MID(A281,20,5) -> 2.008 | G281: =RIGHT(A281,11) -> 01.200.0000
A282: 08.001.12.122.0001.2.011.3.3.50.39.08.110.0000 | B282: 0 | C282: Emenda Impositiva - Josias da Juco - E.E José Ribeiro de Souza | D282: =_xlfn.CONCAT(LEFT(A282,34),".00") -> 08.001.12.122.0001.2.011.3.3.50.39.00 | E282: =VLOOKUP(LEFT(A282,2),ConsolidadoLoa27_ATIVIDADES!A:I,9,0) -> 08 - SECRETARIA DE EDUCAÇÃO | F282: =MID(A282,20,5) -> 2.011 | G282: =RIGHT(A282,11) -> 08.110.0000
A283: 08.001.12.122.0001.2.011.3.3.90.30.01.110.0000 | B283: 103910 | C283: Copa e Cozinha | D283: =_xlfn.CONCAT(LEFT(A283,34),".00") -> 08.001.12.122.0001.2.011.3.3.90.30.00 | E283: =VLOOKUP(LEFT(A283,2),ConsolidadoLoa27_ATIVIDADES!A:I,9,0) -> 08 - SECRETARIA DE EDUCAÇÃO | F283: =MID(A283,20,5) -> 2.011 | G283: =RIGHT(A283,11) -> 01.110.0000
A284: 08.001.12.122.0001.2.011.3.3.90.30.01.110.0000 | B284: 373606.33 | C284: Higiene e Limpeza | D284: =_xlfn.CONCAT(LEFT(A284,34),".00") -> 08.001.12.122.0001.2.011.3.3.90.30.00 | E284: =VLOOKUP(LEFT(A284,2),ConsolidadoLoa27_ATIVIDADES!A:I,9,0) -> 08 - SECRETARIA DE EDUCAÇÃO | F284: =MID(A284,20,5) -> 2.011 | G284: =RIGHT(A284,11) -> 01.110.0000
A285: 08.001.12.122.0001.2.011.3.3.90.30.01.110.0000 | B285: 62346 | C285: Manutenção de Veículos | D285: =_xlfn.CONCAT(LEFT(A285,34),".00") -> 08.001.12.122.0001.2.011.3.3.90.30.00 | E285: =VLOOKUP(LEFT(A285,2),ConsolidadoLoa27_ATIVIDADES!A:I,9,0) -> 08 - SECRETARIA DE EDUCAÇÃO | F285: =MID(A285,20,5) -> 2.011 | G285: =RIGHT(A285,11) -> 01.110.0000
A286: 08.001.12.122.0001.2.011.3.3.90.30.01.110.0000 | B286: 51955 | C286: Sistema de Climatização - Materiais | D286: =_xlfn.CONCAT(LEFT(A286,34),".00") -> 08.001.12.122.0001.2.011.3.3.90.30.00 | E286: =VLOOKUP(LEFT(A286,2),ConsolidadoLoa27_ATIVIDADES!A:I,9,0) -> 08 - SECRETARIA DE EDUCAÇÃO | F286: =MID(A286,20,5) -> 2.011 | G286: =RIGHT(A286,11) -> 01.110.0000
A287: 08.001.12.122.0001.2.011.3.3.90.30.01.110.0000 | B287: 6700 | C287: Materiais de Expediente | D287: =_xlfn.CONCAT(LEFT(A287,34),".00") -> 08.001.12.122.0001.2.011.3.3.90.30.00 | E287: =VLOOKUP(LEFT(A287,2),ConsolidadoLoa27_ATIVIDADES!A:I,9,0) -> 08 - SECRETARIA DE EDUCAÇÃO | F287: =MID(A287,20,5) -> 2.011 | G287: =RIGHT(A287,11) -> 01.110.0000
A288: 08.001.12.122.0001.2.011.3.3.90.30.01.200.0000 | B288: 169947 | C288: Materiais de Expediente | D288: =_xlfn.CONCAT(LEFT(A288,34),".00") -> 08.001.12.122.0001.2.011.3.3.90.30.00 | E288: =VLOOKUP(LEFT(A288,2),ConsolidadoLoa27_ATIVIDADES!A:I,9,0) -> 08 - SECRETARIA DE EDUCAÇÃO | F288: =MID(A288,20,5) -> 2.011 | G288: =RIGHT(A288,11) -> 01.200.0000
A289: 08.001.12.122.0001.2.011.3.3.90.39.01.110.0000 | B289: 610990.8 | C289: Contas de Consumo | D289: =_xlfn.CONCAT(LEFT(A289,34),".00") -> 08.001.12.122.0001.2.011.3.3.90.39.00 | E289: =VLOOKUP(LEFT(A289,2),ConsolidadoLoa27_ATIVIDADES!A:I,9,0) -> 08 - SECRETARIA DE EDUCAÇÃO | F289: =MID(A289,20,5) -> 2.011 | G289: =RIGHT(A289,11) -> 01.110.0000
A290: 08.001.12.122.0001.2.011.3.3.90.39.01.110.0000 | B290: 31173 | C290: Manutenção de Veículos | D290: =_xlfn.CONCAT(LEFT(A290,34),".00") -> 08.001.12.122.0001.2.011.3.3.90.39.00 | E290: =VLOOKUP(LEFT(A290,2),ConsolidadoLoa27_ATIVIDADES!A:I,9,0) -> 08 - SECRETARIA DE EDUCAÇÃO | F290: =MID(A290,20,5) -> 2.011 | G290: =RIGHT(A290,11) -> 01.110.0000
A291: 08.001.12.122.0001.2.011.3.3.90.39.01.110.0000 | B291: 51955 | C291: Sistema de Climatização - Serviços | D291: =_xlfn.CONCAT(LEFT(A291,34),".00") -> 08.001.12.122.0001.2.011.3.3.90.39.00 | E291: =VLOOKUP(LEFT(A291,2),ConsolidadoLoa27_ATIVIDADES!A:I,9,0) -> 08 - SECRETARIA DE EDUCAÇÃO | F291: =MID(A291,20,5) -> 2.011 | G291: =RIGHT(A291,11) -> 01.110.0000
A292: 08.001.12.122.0001.2.011.3.3.90.39.01.110.0000 | B292: 12469.2 | C292: Taxas, Tarifas, Multas e Anuidade | D292: =_xlfn.CONCAT(LEFT(A292,34),".00") -> 08.001.12.122.0001.2.011.3.3.90.39.00 | E292: =VLOOKUP(LEFT(A292,2),ConsolidadoLoa27_ATIVIDADES!A:I,9,0) -> 08 - SECRETARIA DE EDUCAÇÃO | F292: =MID(A292,20,5) -> 2.011 | G292: =RIGHT(A292,11) -> 01.110.0000
... A2374: 99.999.99.999.9999.9.999.9.9.99.99.08.804.0000 | B2374: 24000000 | C2374: Emenda Impositiva - Saúde | D2374: =_xlfn.CONCAT(LEFT(A2374,34),".00") -> 99.999.99.999.9999.9.999.9.9.99.99.00 | E2374: =VLOOKUP(LEFT(A2374,2),ConsolidadoLoa27_ATIVIDADES!A:I,9,0) -> PMO - RC | F2374: =MID(A2374,20,5) -> 9.999 | G2374: =RIGHT(A2374,11) -> 08.804.0000
A2375: =D2375 -> 02.001.04.122.0001.2.011.4.4.50.52.00 | B2375: 0 | C2375: Sem previsão na LDO | D2375: 02.001.04.122.0001.2.011.4.4.50.52.00 | E2375: =VLOOKUP(LEFT(A2375,2),ConsolidadoLoa27_ATIVIDADES!A:I,9,0) -> 02 - GABINETE DO PREFEITO | F2375: =MID(A2375,20,5) -> 2.011 | G2375: =RIGHT(A2375,11) -> .4.50.52.00
A2376: =D2376 -> 02.012.04.122.0001.2.011.3.3.90.39.00 | B2376: 0 | C2376: Sem previsão na LDO | D2376: 02.012.04.122.0001.2.011.3.3.90.39.00 | E2376: =VLOOKUP(LEFT(A2376,2),ConsolidadoLoa27_ATIVIDADES!A:I,9,0) -> 02 - GABINETE DO PREFEITO | F2376: =MID(A2376,20,5) -> 2.011 | G2376: =RIGHT(A2376,11) -> .3.90.39.00
A2377: =D2377 -> 02.012.04.122.0001.2.011.4.4.50.52.00 | B2377: 0 | C2377: Sem previsão na LDO | D2377: 02.012.04.122.0001.2.011.4.4.50.52.00 | E2377: =VLOOKUP(LEFT(A2377,2),ConsolidadoLoa27_ATIVIDADES!A:I,9,0) -> 02 - GABINETE DO PREFEITO | F2377: =MID(A2377,20,5) -> 2.011 | G2377: =RIGHT(A2377,11) -> .4.50.52.00
A2378: =D2378 -> 04.001.04.122.0001.2.011.3.3.90.93.00 | B2378: 0 | C2378: Sem previsão na LDO | D2378: 04.001.04.122.0001.2.011.3.3.90.93.00 | E2378: =VLOOKUP(LEFT(A2378,2),ConsolidadoLoa27_ATIVIDADES!A:I,9,0) -> 04 - SECRETARIA DE FINANÇAS | F2378: =MID(A2378,20,5) -> 2.011 | G2378: =RIGHT(A2378,11) -> .3.90.93.00
A2379: =D2379 -> 04.001.04.122.0002.2.011.3.3.90.33.00 | B2379: 0 | C2379: Sem previsão na LDO | D2379: 04.001.04.122.0002.2.011.3.3.90.33.00 | E2379: =VLOOKUP(LEFT(A2379,2),ConsolidadoLoa27_ATIVIDADES!A:I,9,0) -> 04 - SECRETARIA DE FINANÇAS | F2379: =MID(A2379,20,5) -> 2.011 | G2379: =RIGHT(A2379,11) -> .3.90.33.00
A2380: =D2380 -> 04.001.04.122.0001.2.011.4.4.90.52.00 | B2380: 0 | C2380: Sem previsão na LDO | D2380: 04.001.04.122.0001.2.011.4.4.90.52.00 | E2380: =VLOOKUP(LEFT(A2380,2),ConsolidadoLoa27_ATIVIDADES!A:I,9,0) -> 04 - SECRETARIA DE FINANÇAS | F2380: =MID(A2380,20,5) -> 2.011 | G2380: =RIGHT(A2380,11) -> .4.90.52.00
A2381: =D2381 -> 05.001.04.122.0001.2.011.4.4.90.52.00 | B2381: 0 | C2381: Sem previsão na LDO | D2381: 05.001.04.122.0001.2.011.4.4.90.52.00 | E2381: =VLOOKUP(LEFT(A2381,2),ConsolidadoLoa27_ATIVIDADES!A:I,9,0) -> 05 - PROCURADORIA GERAL DO MUNICÍPIO | F2381: =MID(A2381,20,5) -> 2.011 | G2381: =RIGHT(A2381,11) -> .4.90.52.00
A2382: =D2382 -> 06.001.04.122.0001.2.011.4.4.90.52.00 | B2382: 0 | C2382: Sem previsão na LDO | D2382: 06.001.04.122.0001.2.011.4.4.90.52.00 | E2382: =VLOOKUP(LEFT(A2382,2),ConsolidadoLoa27_ATIVIDADES!A:I,9,0) -> 06 - SECRETARIA DE ADMINISTRAÇÃO | F2382: =MID(A2382,20,5) -> 2.011 | G2382: =RIGHT(A2382,11) -> .4.90.52.00
A2383: =D2383 -> 06.001.04.122.0001.2.011.3.3.90.92.00 | B2383: 0 | C2383: Sem previsão na LDO | D2383: 06.001.04.122.0001.2.011.3.3.90.92.00 | E2383: =VLOOKUP(LEFT(A2383,2),ConsolidadoLoa27_ATIVIDADES!A:I,9,0) -> 06 - SECRETARIA DE ADMINISTRAÇÃO | F2383: =MID(A2383,20,5) -> 2.011 | G2383: =RIGHT(A2383,11) -> .3.90.92.00
A2384: =D2384 -> 06.001.04.122.0001.2.011.3.3.90.93.00 | B2384: 0 | C2384: Sem previsão na LDO | D2384: 06.001.04.122.0001.2.011.3.3.90.93.00 | E2384: =VLOOKUP(LEFT(A2384,2),ConsolidadoLoa27_ATIVIDADES!A:I,9,0) -> 06 - SECRETARIA DE ADMINISTRAÇÃO | F2384: =MID(A2384,20,5) -> 2.011 | G2384: =RIGHT(A2384,11) -> .3.90.93.00
A2385: =D2385 -> 06.011.04.128.0002.2.003.3.3.90.30.00 | B2385: 0 | C2385: Sem previsão na LDO | D2385: 06.011.04.128.0002.2.003.3.3.90.30.00 | E2385: =VLOOKUP(LEFT(A2385,2),ConsolidadoLoa27_ATIVIDADES!A:I,9,0) -> 06 - SECRETARIA DE ADMINISTRAÇÃO | F2385: =MID(A2385,20,5) -> 2.003 | G2385: =RIGHT(A2385,11) -> .3.90.30.00
A2386: =D2386 -> 06.011.04.128.0002.2.003.3.3.90.40.00 | B2386: 0 | C2386: Sem previsão na LDO | D2386: 06.011.04.128.0002.2.003.3.3.90.40.00 | E2386: =VLOOKUP(LEFT(A2386,2),ConsolidadoLoa27_ATIVIDADES!A:I,9,0) -> 06 - SECRETARIA DE ADMINISTRAÇÃO | F2386: =MID(A2386,20,5) -> 2.003 | G2386: =RIGHT(A2386,11) -> .3.90.40.00
... A2532: =D2532 -> 36.001.08.244.0019.1.002.3.3.90.39.00 | B2532: 0 | C2532: Sem previsão na LDO | D2532: 36.001.08.244.0019.1.002.3.3.90.39.00 | E2532: =VLOOKUP(LEFT(A2532,2),ConsolidadoLoa27_ATIVIDADES!A:I,9,0) -> 36 - SECRETARIA DA FAMÍLIA, CIDADANIA E SEGURANÇA ALIMENTAR | F2532: =MID(A2532,20,5) -> 1.002 | G2532: =RIGHT(A2532,11) -> .3.90.39.00

Sheet Planilha3
A3: desc_sub | B3: (Tudo)
A4: processo | B4: (Tudo)
A5: acao | B5: (Vários itens)
A7: Soma de valor | D7: Peça Orçamentária
A8: secretaria2 | B8: Programática_LOA | C8: natureza | D8: LDO | E8: LOA | F8: LDO - LOA
A9: 01- CMO | D9: 148065765 | E9: 148065765 | F9: =D9-E9 -> 0
A10: 02 - GABINETE DO PREFEITO | D10: 18874619 | E10: 11899869 | F10: =D10-E10 -> 6974749.8
A11: 04 - SECRETARIA DE FINANÇAS | D11: 62642563 | E11: 75652774 | F11: =D11-E11 -> -13010210
A12: 05 - PROCURADORIA GERAL DO MUNICÍPIO | D12: 33757519 | E12: 35154694 | F12: =D12-E12 -> -1397174.9
A13: 06 - SECRETARIA DE ADMINISTRAÇÃO | D13: 37676638 | E13: 37231192 | F13: =D13-E13 -> 445446.65
A14: 07 - SECRETARIA DE EMPREGO, TRABALHO E RENDA | D14: 57883745 | E14: 26648767 | F14: =D14-E14 -> 31234978
A15: 08 - SECRETARIA DE EDUCAÇÃO | D15: 1.8419565e+09 | E15: 1.9647853e+09 | F15: =D15-E15 -> -1.2282887e+08
A16: 09 - SECRETARIA DA SAÚDE | D16: 1.1882527e+09 | E16: 1.3941639e+09 | F16: =D16-E16 -> -2.0591119e+08
A17: 11 - SECRETARIA DE SERVIÇOS E OBRAS | D17: 4.3866268e+08 | E17: 5.122192e+08 | F17: =D17-E17 -> -73556524
A18: 12 - SECRETARIA DE ESPORTE, RECREAÇÃO E LAZER | D18: 30836077 | E18: 23349507 | F18: =D18-E18 -> 7486570.5
A19: 13 - SECRETARIA DE HABITAÇÃO | D19: 57373716 | E19: 1.0287072e+08 | F19: =D19-E19 -> -45497004
A20: 14 - SECRETARIA DE ASSISTÊNCIA SOCIAL | D20: 1.5334309e+08 | E20: 1.0535109e+08 | F20: =D20-E20 -> 47992001
... A43: Total Geral | D43: 5.7572313e+09 | E43: 6.2331825e+09 | F43: =D43-E43 -> -4.759512e+08

Sheet Planilha1
A1: unidade | C1: funcao | E1: subfuncao | G1: programa | I1: acao | K1: natureza
A2: 001-CHEFIA DE GABINETE | C2: 4-ADMINISTRAÇÃO | E2: 122-ADMINISTRAÇÃO GERAL | G2: 0001-Administração e Coordenação Geral​ | I2: 2.011-Manutenção de Equipamentos Públicos | K2: 3.3.90.30.00-MATERIAL DE CONSUMO
A3: 012-FUNDO ESPECIAL DE MANUTENÇÃO DOS BOMBEIROS | C3: 11-TRABALHO | E3: 126-TECNOLOGIA DA INFORMATIZAÇÃO | G3: 0002-Governo Inteligente, Aberto e Inovador​ | I3: 2.007-Ampliação e Manutenção de Sistemas de Inteligência, Fiscalização e Tecnologia | K3: 3.3.90.39.00-OUTROS SERVIÇOS DE TERCEIROS - PESSOA JURÍDICA
A4: 001-GABINETE DA SECRETARIA DE FINANÇAS | C4: 12-EDUCAÇÃO | E4: 128-FORMAÇÃO DE RECURSOS HUMANOS | G4: 0017-Trabalho, Emprego e Renda​ | I4: 2.003-Qualificação de Servidores e Processos Institucionais | K4: 3.1.71.70.00-RATEIO PELA PARTICIPAÇÃO EM CONSÓRCIO PÚBLICO
A5: 001-GABINETE DA PROCURADORIA GERAL DO MUNICÍPIO | C5: 10-SAÚDE | E5: 334-FOMENTO AO TRABALHO | G5: 0016-Escola para Todos​ | I5: 2.006-Representações Oficiais | K5: 3.3.71.70.00-RATEIO PELA PARTICIPAÇÃO EM CONSÓRCIO PÚBLICO
A6: 001-GABINETE DA SECRETARIA DE ADMINISTRAÇÃO | C6: 15-URBANISMO | E6: 333-EMPREGABILIDADE | G6: 0015-Atenção e Cuidado em Saúde​ | I6: 2.005-Promoção de Eventos, Comunicação e Participação Social | K6: 4.4.50.52.00-EQUIPAMENTOS E MATERIAL PERMANENTE
A7: 011-FUNDO MUNICIPAL DE VALORIZAÇÃO DOS SERVIDORES | C7: 17-SANEAMENTO | E7: 361-ENSINO FUNDAMENTAL | G7: 0014-Gestão em Saúde​ | I7: 1.002-Reforma e Ampliação de Unidades | K7: 3.3.90.40.00-SERVIÇOS DE TECNOLOGIA DA INFORMAÇÃO E COMUNICAÇÃO - PESSOA JURÍDICA
A8: 001-GABINETE DA SECRETARIA DE EMPREGO, TRABALHO E RENDA | C8: 18-GESTÃO AMBIENTAL | E8: 365-EDUCAÇÃO INFANTIL | G8: 0004-Planejamento e Gestão de Políticas Públicas | I8: 2.027-Intermediação Profissional | K8: 3.3.90.93.00-INDENIZAÇÕES E RESTITUIÇÕES
A9: 001-FUNDO MUNICIPAL DO TRABALHO | C9: 27-DESPORTO E LAZER | E9: 364-ENSINO SUPERIOR | G9: 0011-Zeladoria Urbana e Cuidados com a Cidade​ | I9: 2.004-Qualificação Socioprofissional | K9: 3.3.90.33.00-PASSAGENS E DESPESAS COM LOCOMOÇÃO
A10: 001-GABINETE DA SECRETARIA DA EDUCAÇÃO | C10: 16-HABITAÇÃO | E10: 306-ALIMENTAÇÃO E NUTRIÇÃO | G10: 0013-Mobilidade Urbana e Infraestrutura Viária​ | I10: 2.033-Fortalecimento da Economia Criativa e Solidária | K10: 4.4.90.52.00-EQUIPAMENTOS E MATERIAL PERMANENTE
A11: 001-GABINETE DA SECRETARIA DA SAÚDE | C11: 8-ASSISTÊNCIA SOCIAL | E11: 366-EDUCAÇÃO DE JOVENS E ADULTOS | G11: 0007-Meio Ambiente, Sustentabilidade e Bem-Estar Animal​ | I11: 2.025-Auxílio para Inclusão no Mercado de Trabalho | K11: 3.3.90.92.00-DESPESAS DE EXERCÍCIOS ANTERIORES
A12: 010-DIRETORIA GERAL DE URGÊNCIA E EMERGÊNCIA | C12: 13-CULTURA | E12: 367-EDUCAÇÃO ESPECIAL | G12: 0005-Resiliência Urbana​ | I12: 1.003-Implantação de Novas Unidades | K12: 3.3.90.36.00-OUTROS SERVIÇOS DE TERCEIROS - PESSOA FÍSICA
... A15: 008-DIRETORIA GERAL DE ATENÇÃO PRIMÁRIA EM SAÚDE | C15: 14-DIREITOS DA CIDADANIA | E15: 301-ATENÇÃO BÁSICA | G15: 0019-Segurança Alimentar e Combate à Pobreza​ | I15: 2.017-Suporte ao Aluno | K15: 3.3.90.96.00-RESSARCIMENTO DE DESPESAS DE PESSOAL REQUISITADO
A16: 015-DIRETORIA GERAL DA GESTÃO DE SAÚDE | C16: =VLOOKUP(#REF!,$E$1:$T$994,9,0) -> #REF! | E16: 303-SUPORTE PROFILÁTICO E TERAPÊUTICO | G16: 0018-Proteção Social e Garantia de Direitos​ | I16: 2.018-Conectividade e Tecnologia na Educação | K16: 3.3.90.31.00-PREMIAÇÕES CULTURAIS, ARTÍSTICAS, CIENTÍFICAS, DESPORTIVAS E OUTRAS
A17: 012-DEPARTAMENTO DE ASSISTÊNCIA FARMACÊUTICA | E17: 121-PLANEJAMENTO E ORÇAMENTO | G17: 0009-Cultura, Economia Criativa e Patrimônio Histórico​ | I17: 2.019-Ações Pedagógicas Complementares | K17: 3.3.90.48.00 - OUTROS AUXILIOS FINANCEIROS A PESSOAS FISICAS
A18: 001-GABINETE DA SECRETARIA DE SERVIÇOS E OBRAS | E18: 452-SERVIÇOS URBNOS | G18: 0008-Empreendedorismo, Negócios e Turismo​ | I18: 2.020-Transporte de Alunos | K18: 3.3.90.32.00-MATERIAL, BEM OU SERVIÇO PARA DISTRIBUIÇÃO GRATUITA
A19: 014-FUNDO MUNICIPAL DE MANUTENÇÃO DE VELÓRIOS | E19: 451-INFRA-ESTRUTURA URBANA | G19: 0006-Segurança Pública e Fiscalização Inteligente​ | I19: 2.022-Parcerias para Criação de Vagas | K19: 4.4.50.39.00-OUTROS SERVIÇOS DE TERCEIROS - PESSOA JURÍDICA
A20: 001-GABINETE DA SECRETARIA DE ESPORTE, RECREAÇÃO E LAZER | E20: 452-SERVIÇOS URBANOS | G20: =#REF! -> #REF! | I20: 2.023-Gestão Compartilhada de Equipamentos Públicos | K20: 3.3.50.85.00-CONTRATO DE GESTÃO
A21: 001-GABINETE DA SECRETARIA DE HABITAÇÃO | E21: 544-RECURSOS HÍDRICOS | I21: 2.013-Manutenção de Equipamentos Públicos - Atenção Especializada
A22: 008-FUNDO MUNICIPAL DE POLÍTICA URBANA E HABITACIONAL | E22: 543-RECUPERAÇÃO DE ÁREAS DEGRADADAS | I22: 2.014-Manutenção de Equipamentos Públicos - Atenção Hospitalar e Urgência e Emergência | K22: 4.5.90.62.00-AQUISIÇÃO DE PRODUTOS PARA REVENDA
A23: 001-GABINETE DA SECRETARIA DE ASSISTÊNCIA SOCIAL | E23: 811-DESPORTO DE RENDIMENTO | I23: 2.012-Manutenção de Equipamentos Públicos - Atenção Primária | K23: 4.4.71.70.00-RATEIO PELA PARTICIPAÇÃO EM CONSÓRCIO PÚBLICO
A24: 005-FUNDO MUNICIPAL DE ASSISTÊNCIA SOCIAL | E24: 812-DESPORTO COMUNITÁRIO | I24: 2.026-Residências e Internações Compulsórias | K24: 4.4.50.51.00-OBRAS E INSTALAÇÕES
A25: 007-DEPARTAMENTO DE PROTEÇÃO SOCIAL BÁSICA | E25: 482-HABITAÇÃO URBANA | I25: 1.001-Estudos, Pesquisas, Planos e Projetos | K25: 3.3.90.48.00-OUTROS AUXÍLIOS FINANCEIROS A PESSOA FÍSICA
A26: 008-DEPARTAMENTO DE PROTEÇÃO SOCIAL ESPECIAL | E26: 245-SERVIÇOS SOCIOASSISTENCIAIS | I26: 2.034-Manutenção da Infraestrutura Viária | K26: 3.3.90.91.00-SENTENÇAS JUDICIAIS
A27: 001-GABINETE DA CULTURA | E27: 246-SEGURANÇA DE RENDA | I27: 1.006-Desenvolvimento da Infraestrutura Viária | K27: 3.3.90.35.00-SERVIÇOS DE CONSULTORIA
A28: 001-GABINETE DA SECRETARIA DE TECNOLOGIA, INOVAÇÃO E DESENVOLVIMENTO ECONÔMICO | E28: 241-ASSISTÊNCIA AO IDOSO ASSISTÊNCIA À PESSOA IDOSA | I28: 2.038-Iluminação Pública | K28: =VLOOKUP(#REF!,$L$1:$T$994,9,0) -> #REF!
A29: 001-GABINETE DA SECRETARIA DE MEIO AMBIENTE E RECURSOS HÍDRICOS | E29: 392-DIFUSÃO CULTURAL | I29: 2.039-Limpeza Urbana e Gestão de Resíduos Sólidos
A30: 003-FUNDO MUNICIPAL DE MEIO AMBIENTE | E30: 541-PRESERVAÇÃO E CONSERVAÇÃO AMBIENTAL | I30: 2.035-Manutenção e Serviços de Drenagem Urbana
A31: 002-RECURSOS SOB A SUPERVISÃO DA SECRETARIA DE ADMINISTRAÇÃO | E31: 422-DIREITOS INDIVIDUAIS, COLETIVOS E DIFUSOS | I31: 2.037-Ampliação e Manutenção de Áreas Verdes
A32: 001-RECURSOS SOB A SUPERVISÃO DA SECRETARIA DE FINANÇAS | E32: 453-TRANSPORTES COLETIVOS URBANOS | I32: 2.032-Iniciação Esportiva
A33: 003-RECURSOS SOB SUPERVISÃO DA SECRETARIA DE TECNOLOGIA, INOVAÇÃO E DESENVOLVIMENTO ECONÔMICO | E33: 181-POLICIAMENTO | I33: 2.030-Apoio ao Esporte de Alto Rendimento
A34: 001-GABINETE DA SECRETARIA DE TRANSPORTE E DA MOBILIDADE URBANA | E34: 242-ASSISTÊNCIA AO PORTADOR DE DEFICIÊNCIA ASSISTÊNCIA À PESSOA COM DEFICIÊNCIA | I34: 2.028-Disseminação de Atividades Culturais e Esportivas Decentralizadas
A35: 005-FUNDO MUNICIPAL DE TRÂNSITO | E35: 391-PATRIMÔNIO HISTÓRICO, ARTÍSTICO E ARQUEOLÓGICO | I35: 2.031-Esporte Amador
A36: 001-GABINETE DA SECRETARIA DE SEGURANÇA E CONTROLE URBANO | E36: 182-DEFESA CIVIL | I36: 1.009-Urbanização de Favelas e Comunidades
A37: 001-GABINETE DA SECRETARIA DE COMUNICAÇÃO | E37: 244-ASSISTÊNCIA COMUNITÁRIA | I37: 1.010-Requalificação de Favelas e Comunidades
A38: 001-GABINETE DA SECRETARIA DE PLANEJAMENTO E GESTÃO | E38: =VLOOKUP(#REF!,$G$1:$T$994,9,0) -> #REF! | I38: 1.014-Recuperação de Conjuntos Habitacionais
A39: 001-GABINETE DA CONTROLADORIA GERAL DO MUNICÍPIO | I39: 1.011-Regularização Fundiária de Assentamentos Precários, Loteamentos e Conjuntos Habitacionais
A40: 001-GABINETE DA SECRETARIA DE GOVERNO | I40: 2.024-Distribuição de Alimentos e Benefícios para as Famílias em Situação de Vulnerabilidade
A41: 007-FUNDO MUNICIPAL DE POLÍTICAS SOBRE DROGAS | I41: 2.015-Manutenção de Equipamentos Públicos - Proteção Básica
A42: 001-GABINETE DA SECRETARIA EXECUTIVA DA PESSOA COM DEFICIÊNCIA | I42: 2.016-Manutenção de Equipamentos Públicos - Proteção Especial
A43: 001-GABINETE DA SECRETARIA EXECUTIVA DE POLITICAS DE PROMOÇÃO DA IGUALDADE RACIAL | I43: 2.041-Ação Transversal de Garantia de Direitos
A44: 001-GABINETE DA SECRETARIA EXECUTIVA DE POLÍTICAS PARA MULHERES E DIVERSIDADE | I44: 2.021-Educação Cidadã
A45: 001-GABINETE DA SECRETARIA EXECUTIVA DE COMPRAS E LICITAÇÕES | I45: 2.009-Locação de Imóveis
A46: 001-GABINETE DA COORDENADORIA DA DEFESA CIVIL | I46: 0.003-Precatórios e Sentenças Judiciais
A47: 001-GABINETE DA SECRETARIA DA FAMÍLIA, CIDADANIA E SEGURANÇA ALIMENTAR | I47: 2.010-Manutenção do Transporte Coletivo
A48: 777 | I48: 2.002-Abastecimento de Frota
A49: 999 | I49: =#REF! -> #REF!
I50: 2.036-Manutenção da Mobilidade Ativa
I51: 2.029-Valorização do Patrimônio Histórico-Cultural

Sheet Programática que não tem na LDO
A1: secretaria | B1: unidade | C1: funcao | D1: subfuncao | E1: programa | F1: acao | G1: natureza | H1: Programática_LOA | I1: secretaria | J1: unidade | K1: funcao | L1: subfuncao | M1: programa | N1: acao | O1: natureza | P1: desc_sub | Q1: processo | R1: valor
A2: 02 | B2: 001 | C2: 04 | D2: 122 | E2: 0001 | F2: 2.011 | G2: 4.4.50.52.00 | H2: 02.001.04.122.0001.2.011.4.4.50.52.00 | I2: 02 - GABINETE DO PREFEITO | J2: 001-CHEFIA DE GABINETE | K2: 4-ADMINISTRAÇÃO | L2: 122-ADMINISTRAÇÃO GERAL | M2: 0001-Administração e Coordenação Geral​ | N2: 2.011-Manutenção de Equipamentos Públicos | O2: 4.4.50.52.00-EQUIPAMENTOS E MATERIAL PERMANENTE | P2: APARELHOS E UTENSÍLIOS DOMÉSTICOS | R2: 22500 | S2: Não tem o Cód. na LDO
A3: 02 | B3: 012 | C3: 04 | D3: 122 | E3: 0001 | F3: 2.011 | G3: 3.3.90.39.00 | H3: 02.012.04.122.0001.2.011.3.3.90.39.00 | I3: 02 - GABINETE DO PREFEITO | J3: 012-FUNDO ESPECIAL DE MANUTENÇÃO DOS BOMBEIROS | K3: 4-ADMINISTRAÇÃO | L3: 122-ADMINISTRAÇÃO GERAL | M3: 0001-Administração e Coordenação Geral​ | N3: 2.011-Manutenção de Equipamentos Públicos | O3: 3.3.90.39.00-OUTROS SERVIÇOS DE TERCEIROS - PESSOA JURÍDICA | P3: MANUTENÇÃO E CONSERVAÇÃO DE VEÍCULOS | R3: 20000 | S3: Não tem o Cód. na LDO
A4: 02 | B4: 012 | C4: 04 | D4: 122 | E4: 0001 | F4: 2.011 | G4: 4.4.50.52.00 | H4: 02.012.04.122.0001.2.011.4.4.50.52.00 | I4: 02 - GABINETE DO PREFEITO | J4: 012-FUNDO ESPECIAL DE MANUTENÇÃO DOS BOMBEIROS | K4: 4-ADMINISTRAÇÃO | L4: 122-ADMINISTRAÇÃO GERAL | M4: 0001-Administração e Coordenação Geral​ | N4: 2.011-Manutenção de Equipamentos Públicos | O4: 4.4.50.52.00-EQUIPAMENTOS E MATERIAL PERMANENTE | P4: APARELHOS E UTENSÍLIOS DOMÉSTICOS | R4: 3000 | S4: Não tem o Cód. na LDO
A5: 04 | B5: 001 | C5: 04 | D5: 122 | E5: 0001 | F5: 2.011 | G5: 3.3.90.93.00 | H5: 04.001.04.122.0001.2.011.3.3.90.93.00 | I5: 04 - SECRETARIA DE FINANÇAS | J5: 001-GABINETE DA SECRETARIA DE FINANÇAS | K5: 4-ADMINISTRAÇÃO | L5: 122-ADMINISTRAÇÃO GERAL | M5: 0001-Administração e Coordenação Geral​ | N5: 2.011-Manutenção de Equipamentos Públicos | O5: 3.3.90.93.00-INDENIZAÇÕES E RESTITUIÇÕES | P5: RESTITUIÇÕES | Q5: não tem (ressarcimentos) | R5: 10000 | S5: Não tem o Cód. na LDO
A6: 04 | B6: 001 | C6: 04 | D6: 122 | E6: 0002 | F6: 2.011 | G6: 3.3.90.33.00 | H6: 04.001.04.122.0002.2.011.3.3.90.33.00 | I6: 04 - SECRETARIA DE FINANÇAS | J6: 001-GABINETE DA SECRETARIA DE FINANÇAS | K6: 4-ADMINISTRAÇÃO | L6: 122-ADMINISTRAÇÃO GERAL | M6: 0002-Governo Inteligente, Aberto e Inovador​ | N6: 2.011-Manutenção de Equipamentos Públicos | O6: 3.3.90.33.00-PASSAGENS E DESPESAS COM LOCOMOÇÃO | Q6: Ata 77/2025 (viagens) | R6: 40000 | S6: Não tem o Cód. na LDO
A7: 04 | B7: 001 | C7: 04 | D7: 122 | E7: 0001 | F7: 2.011 | G7: 4.4.90.52.00 | H7: 04.001.04.122.0001.2.011.4.4.90.52.00 | I7: 04 - SECRETARIA DE FINANÇAS | J7: 001-GABINETE DA SECRETARIA DE FINANÇAS | K7: 4-ADMINISTRAÇÃO | L7: 122-ADMINISTRAÇÃO GERAL | M7: 0001-Administração e Coordenação Geral​ | N7: 2.011-Manutenção de Equipamentos Públicos | O7: 4.4.90.52.00-EQUIPAMENTOS E MATERIAL PERMANENTE | P7: MÁQUINAS, UTENSÍLIOS E EQUIPAMENTOS DIVERSOS | Q7: não tem (ar condicionado) | R7: 40000 | S7: Não tem o Cód. na LDO
A8: 05 | B8: 001 | C8: 04 | D8: 122 | E8: 0001 | F8: 2.011 | G8: 4.4.90.52.00 | H8: 05.001.04.122.0001.2.011.4.4.90.52.00 | I8: 05 - PROCURADORIA GERAL DO MUNICÍPIO | J8: 001-GABINETE DA PROCURADORIA GERAL DO MUNICÍPIO | K8: 4-ADMINISTRAÇÃO | L8: 122-ADMINISTRAÇÃO GERAL | M8: 0001-Administração e Coordenação Geral​ | N8: 2.011-Manutenção de Equipamentos Públicos | O8: 4.4.90.52.00-EQUIPAMENTOS E MATERIAL PERMANENTE | P8: MÁQUINAS, UTENSÍLIOS E EQUIPAMENTOS DIVERSOS | Q8: Sistema de Climatização - Materiais | R8: 10000 | S8: Não tem o Cód. na LDO
A9: 06 | B9: 001 | C9: 04 | D9: 122 | E9: 0001 | F9: 2.011 | G9: 4.4.90.52.00 | H9: 06.001.04.122.0001.2.011.4.4.90.52.00 | I9: 06 - SECRETARIA DE ADMINISTRAÇÃO | J9: 001-GABINETE DA SECRETARIA DE ADMINISTRAÇÃO | K9: 4-ADMINISTRAÇÃO | L9: 122-ADMINISTRAÇÃO GERAL | M9: 0001-Administração e Coordenação Geral​ | N9: 2.011-Manutenção de Equipamentos Públicos | O9: 4.4.90.52.00-EQUIPAMENTOS E MATERIAL PERMANENTE | P9: OUTROS MATERIAIS PERMANENTES | R9: 100000 | S9: Não tem o Cód. na LDO
A10: 06 | B10: 001 | C10: 04 | D10: 122 | E10: 0001 | F10: 2.011 | G10: 3.3.90.92.00 | H10: 06.001.04.122.0001.2.011.3.3.90.92.00 | I10: 06 - SECRETARIA DE ADMINISTRAÇÃO | J10: 001-GABINETE DA SECRETARIA DE ADMINISTRAÇÃO | K10: 4-ADMINISTRAÇÃO | L10: 122-ADMINISTRAÇÃO GERAL | M10: 0001-Administração e Coordenação Geral​ | N10: 2.011-Manutenção de Equipamentos Públicos | O10: 3.3.90.92.00-DESPESAS DE EXERCÍCIOS ANTERIORES | P10: OUTROS SERVIÇOS DE TERCEIROS - PESSOA JURÍDICA | R10: 1 | S10: Não tem o Cód. na LDO
A11: 06 | B11: 001 | C11: 04 | D11: 122 | E11: 0001 | F11: 2.011 | G11: 3.3.90.93.00 | H11: 06.001.04.122.0001.2.011.3.3.90.93.00 | I11: 06 - SECRETARIA DE ADMINISTRAÇÃO | J11: 001-GABINETE DA SECRETARIA DE ADMINISTRAÇÃO | K11: 4-ADMINISTRAÇÃO | L11: 122-ADMINISTRAÇÃO GERAL | M11: 0001-Administração e Coordenação Geral​ | N11: 2.011-Manutenção de Equipamentos Públicos | O11: 3.3.90.93.00-INDENIZAÇÕES E RESTITUIÇÕES | R11: 1 | S11: Não tem o Cód. na LDO
A12: 06 | B12: 011 | C12: 04 | D12: 128 | E12: 0002 | F12: 2.003 | G12: 3.3.90.30.00 | H12: 06.011.04.128.0002.2.003.3.3.90.30.00 | I12: 06 - SECRETARIA DE ADMINISTRAÇÃO | J12: 011-FUNDO MUNICIPAL DE VALORIZAÇÃO DOS SERVIDORES | K12: 4-ADMINISTRAÇÃO | L12: 128-FORMAÇÃO DE RECURSOS HUMANOS | M12: 0002-Governo Inteligente, Aberto e Inovador​ | N12: 2.003-Qualificação de Servidores e Processos Institucionais | O12: 3.3.90.30.00-MATERIAL DE CONSUMO | P12: MATERIAL DE EXPEDIENTE | R12: 100000 | S12: Não tem o Cód. na LDO
A13: 06 | B13: 011 | C13: 04 | D13: 128 | E13: 0002 | F13: 2.003 | G13: 3.3.90.40.00 | H13: 06.011.04.128.0002.2.003.3.3.90.40.00 | I13: 06 - SECRETARIA DE ADMINISTRAÇÃO | J13: 011-FUNDO MUNICIPAL DE VALORIZAÇÃO DOS SERVIDORES | K13: 4-ADMINISTRAÇÃO | L13: 128-FORMAÇÃO DE RECURSOS HUMANOS | M13: 0002-Governo Inteligente, Aberto e Inovador​ | N13: 2.003-Qualificação de Servidores e Processos Institucionais | O13: 3.3.90.40.00-SERVIÇOS DE TECNOLOGIA DA INFORMAÇÃO E COMUNICAÇÃO - PESSOA JURÍDICA | P13: OUTROS SERVIÇOS DE TECNOLOGIA DA INFORMAÇÃO E COMUNICAÇÃO - PESSOA JURÍDICA | R13: 100000 | S13: Não tem o Cód. na LDO
A14: 06 | B14: 011 | C14: 04 | D14: 128 | E14: 0002 | F14: 2.003 | G14: 4.4.90.52.00 | H14: 06.011.04.128.0002.2.003.4.4.90.52.00 | I14: 06 - SECRETARIA DE ADMINISTRAÇÃO | J14: 011-FUNDO MUNICIPAL DE VALORIZAÇÃO DOS SERVIDORES | K14: 4-ADMINISTRAÇÃO | L14: 128-FORMAÇÃO DE RECURSOS HUMANOS | M14: 0002-Governo Inteligente, Aberto e Inovador​ | N14: 2.003-Qualificação de Servidores e Processos Institucionais | O14: 4.4.90.52.00-EQUIPAMENTOS E MATERIAL PERMANENTE | P14: MÁQUINAS, UTENSÍLIOS E EQUIPAMENTOS DIVERSOS | R14: 100000 | S14: Não tem o Cód. na LDO
A15: 07 | B15: 001 | C15: 04 | D15: 122 | E15: 0002 | F15: 2.003 | G15: 3.3.90.36.00 | H15: 07.001.04.122.0002.2.003.3.3.90.36.00 | I15: 07 - SECRETARIA DE EMPREGO, TRABALHO E RENDA | J15: 001-GABINETE DA SECRETARIA DE EMPREGO, TRABALHO E RENDA | K15: 4-ADMINISTRAÇÃO | L15: 122-ADMINISTRAÇÃO GERAL | M15: 0002-Governo Inteligente, Aberto e Inovador​ | N15: 2.003-Qualificação de Servidores e Processos Institucionais | O15: 3.3.90.36.00-OUTROS SERVIÇOS DE TERCEIROS - PESSOA FÍSICA | Q15: 90 | R15: 1 | S15: Não tem o Cód. na LDO
A16: 07 | B16: 001 | C16: 04 | D16: 122 | E16: 0002 | F16: 2.003 | G16: 3.3.90.39.00 | H16: 07.001.04.122.0002.2.003.3.3.90.39.00 | I16: 07 - SECRETARIA DE EMPREGO, TRABALHO E RENDA | J16: 001-GABINETE DA SECRETARIA DE EMPREGO, TRABALHO E RENDA | K16: 4-ADMINISTRAÇÃO | L16: 122-ADMINISTRAÇÃO GERAL | M16: 0002-Governo Inteligente, Aberto e Inovador​ | N16: 2.003-Qualificação de Servidores e Processos Institucionais | O16: 3.3.90.39.00-OUTROS SERVIÇOS DE TERCEIROS - PESSOA JURÍDICA | P16: OUTROS SERVIÇOS DE TERCEIRO PESSOA JURÍDICA - PAGAMENTO ANTECIPADO | Q16: 91 | R16: 1 | S16: Não tem o Cód. na LDO
A17: 07 | B17: 001 | C17: 04 | D17: 122 | E17: 0002 | F17: 2.005 | G17: 3.3.90.30.00 | H17: 07.001.04.122.0002.2.005.3.3.90.30.00 | I17: 07 - SECRETARIA DE EMPREGO, TRABALHO E RENDA | J17: 001-GABINETE DA SECRETARIA DE EMPREGO, TRABALHO E RENDA | K17: 4-ADMINISTRAÇÃO | L17: 122-ADMINISTRAÇÃO GERAL | M17: 0002-Governo Inteligente, Aberto e Inovador​ | N17: 2.005-Promoção de Eventos, Comunicação e Participação Social | O17: 3.3.90.30.00-MATERIAL DE CONSUMO | P17: GÊNEROS DE ALIMENTAÇÃO | Q17: 92 | S17: Não tem o Cód. na LDO
A18: 07 | B18: 001 | C18: 04 | D18: 122 | E18: 0002 | F18: 2.005 | G18: 3.3.90.39.00 | H18: 07.001.04.122.0002.2.005.3.3.90.39.00 | I18: 07 - SECRETARIA DE EMPREGO, TRABALHO E RENDA | J18: 001-GABINETE DA SECRETARIA DE EMPREGO, TRABALHO E RENDA | K18: 4-ADMINISTRAÇÃO | L18: 122-ADMINISTRAÇÃO GERAL | M18: 0002-Governo Inteligente, Aberto e Inovador​ | N18: 2.005-Promoção de Eventos, Comunicação e Participação Social | O18: 3.3.90.39.00-OUTROS SERVIÇOS DE TERCEIROS - PESSOA JURÍDICA | P18: SERVIÇOS GRÁFICOS E EDITORIAIS | Q18: 93 | S18: Não tem o Cód. na LDO
A19: 07 | B19: 001 | C19: 11 | D19: 334 | E19: 0017 | F19: 1.002 | G19: 3.3.90.39.00 | H19: 07.001.11.334.0017.1.002.3.3.90.39.00 | I19: 07 - SECRETARIA DE EMPREGO, TRABALHO E RENDA | J19: 001-GABINETE DA SECRETARIA DE EMPREGO, TRABALHO E RENDA | K19: 11-TRABALHO | L19: 334-FOMENTO AO TRABALHO | M19: 0017-Trabalho, Emprego e Renda​ | N19: 1.002-Reforma e Ampliação de Unidades | O19: 3.3.90.39.00-OUTROS SERVIÇOS DE TERCEIROS - PESSOA JURÍDICA | P19: OUTROS SERVIÇOS DE TERCEIRO PESSOA JURÍDICA - PAGAMENTO ANTECIPADO | Q19: 94 | S19: Não tem o Cód. na LDO
A20: 07 | B20: 001 | C20: 11 | D20: 334 | E20: 0017 | F20: 2.011 | G20: 3.3.90.30.00 | H20: 07.001.11.334.0017.2.011.3.3.90.30.00 | I20: 07 - SECRETARIA DE EMPREGO, TRABALHO E RENDA | J20: 001-GABINETE DA SECRETARIA DE EMPREGO, TRABALHO E RENDA | K20: 11-TRABALHO | L20: 334-FOMENTO AO TRABALHO | M20: 0017-Trabalho, Emprego e Renda​ | N20: 2.011-Manutenção de Equipamentos Públicos | O20: 3.3.90.30.00-MATERIAL DE CONSUMO | P20: GÊNEROS DE ALIMENTAÇÃO | Q20: 95 | R20: 15000 | S20: Não tem o Cód. na LDO
A21: 07 | B21: 001 | C21: 11 | D21: 334 | E21: 0017 | F21: 2.011 | G21: 3.3.90.30.00 | H21: 07.001.11.334.0017.2.011.3.3.90.30.00 | I21: 07 - SECRETARIA DE EMPREGO, TRABALHO E RENDA | J21: 001-GABINETE DA SECRETARIA DE EMPREGO, TRABALHO E RENDA | K21: 11-TRABALHO | L21: 334-FOMENTO AO TRABALHO | M21: 0017-Trabalho, Emprego e Renda​ | N21: 2.011-Manutenção de Equipamentos Públicos | O21: 3.3.90.30.00-MATERIAL DE CONSUMO | P21: MATERIAL DE LIMPEZA E PRODUTOS DE HIGIENIZAÇÃO | Q21: 95 | R21: 60000 | S21: Não tem o Cód. na LDO
A22: 07 | B22: 001 | C22: 11 | D22: 334 | E22: 0017 | F22: 2.011 | G22: 3.3.90.30.00 | H22: 07.001.11.334.0017.2.011.3.3.90.30.00 | I22: 07 - SECRETARIA DE EMPREGO, TRABALHO E RENDA | J22: 001-GABINETE DA SECRETARIA DE EMPREGO, TRABALHO E RENDA | K22: 11-TRABALHO | L22: 334-FOMENTO AO TRABALHO | M22: 0017-Trabalho, Emprego e Renda​ | N22: 2.011-Manutenção de Equipamentos Públicos | O22: 3.3.90.30.00-MATERIAL DE CONSUMO | P22: MATERIAL DE EXPEDIENTE | Q22: 95 | R22: 50000 | S22: Não tem o Cód. na LDO
A23: 07 | B23: 001 | C23: 11 | D23: 334 | E23: 0017 | F23: 2.011 | G23: 3.3.90.30.00 | H23: 07.001.11.334.0017.2.011.3.3.90.30.00 | I23: 07 - SECRETARIA DE EMPREGO, TRABALHO E RENDA | J23: 001-GABINETE DA SECRETARIA DE EMPREGO, TRABALHO E RENDA | K23: 11-TRABALHO | L23: 334-FOMENTO AO TRABALHO | M23: 0017-Trabalho, Emprego e Renda​ | N23: 2.011-Manutenção de Equipamentos Públicos | O23: 3.3.90.30.00-MATERIAL DE CONSUMO | P23: MATERIAL DE COPA E COZINHA | Q23: 95 | R23: 40000 | S23: Não tem o Cód. na LDO
A24: 07 | B24: 001 | C24: 11 | D24: 334 | E24: 0017 | F24: 2.011 | G24: 3.3.90.30.00 | H24: 07.001.11.334.0017.2.011.3.3.90.30.00 | I24: 07 - SECRETARIA DE EMPREGO, TRABALHO E RENDA | J24: 001-GABINETE DA SECRETARIA DE EMPREGO, TRABALHO E RENDA | K24: 11-TRABALHO | L24: 334-FOMENTO AO TRABALHO | M24: 0017-Trabalho, Emprego e Renda​ | N24: 2.011-Manutenção de Equipamentos Públicos | O24: 3.3.90.30.00-MATERIAL DE CONSUMO | P24: MATERIAL ELÉTRICO E ELETRÔNICO | Q24: 95 | R24: 15000 | S24: Não tem o Cód. na LDO
A25: 07 | B25: 001 | C25: 11 | D25: 334 | E25: 0017 | F25: 2.011 | G25: 3.3.90.39.00 | H25: 07.001.11.334.0017.2.011.3.3.90.39.00 | I25: 07 - SECRETARIA DE EMPREGO, TRABALHO E RENDA | J25: 001-GABINETE DA SECRETARIA DE EMPREGO, TRABALHO E RENDA | K25: 11-TRABALHO | L25: 334-FOMENTO AO TRABALHO | M25: 0017-Trabalho, Emprego e Renda​ | N25: 2.011-Manutenção de Equipamentos Públicos | O25: 3.3.90.39.00-OUTROS SERVIÇOS DE TERCEIROS - PESSOA JURÍDICA | P25: SERVIÇOS GRÁFICOS E EDITORIAIS | Q25: 0 | R25: 80000 | S25: Não tem o Cód. na LDO
A26: 07 | B26: 001 | C26: 11 | D26: 334 | E26: 0017 | F26: 2.011 | G26: 3.3.90.39.00 | H26: 07.001.11.334.0017.2.011.3.3.90.39.00 | I26: 07 - SECRETARIA DE EMPREGO, TRABALHO E RENDA | J26: 001-GABINETE DA SECRETARIA DE EMPREGO, TRABALHO E RENDA | K26: 11-TRABALHO | L26: 334-FOMENTO AO TRABALHO | M26: 0017-Trabalho, Emprego e Renda​ | N26: 2.011-Manutenção de Equipamentos Públicos | O26: 3.3.90.39.00-OUTROS SERVIÇOS DE TERCEIROS - PESSOA JURÍDICA | P26: OUTROS SERVIÇOS DE TERCEIRO PESSOA JURÍDICA - PAGAMENTO ANTECIPADO | Q26: 0 | R26: 120000 | S26: Não tem o Cód. na LDO
A27: 07 | B27: 001 | C27: 11 | D27: 334 | E27: 0017 | F27: 2.011 | G27: 4.4.90.52.00 | H27: 07.001.11.334.0017.2.011.4.4.90.52.00 | I27: 07 - SECRETARIA DE EMPREGO, TRABALHO E RENDA | J27: 001-GABINETE DA SECRETARIA DE EMPREGO, TRABALHO E RENDA | K27: 11-TRABALHO | L27: 334-FOMENTO AO TRABALHO | M27: 0017-Trabalho, Emprego e Renda​ | N27: 2.011-Manutenção de Equipamentos Públicos | O27: 4.4.90.52.00-EQUIPAMENTOS E MATERIAL PERMANENTE | P27: APARELHOS E UTENSÍLIOS DOMÉSTICOS | Q27: 0 | R27: 35000 | S27: Não tem o Cód. na LDO
A28: 07 | B28: 001 | C28: 11 | D28: 334 | E28: 0017 | F28: 2.011 | G28: 4.4.90.52.00 | H28: 07.001.11.334.0017.2.011.4.4.90.52.00 | I28: 07 - SECRETARIA DE EMPREGO, TRABALHO E RENDA | J28: 001-GABINETE DA SECRETARIA DE EMPREGO, TRABALHO E RENDA | K28: 11-TRABALHO | L28: 334-FOMENTO AO TRABALHO | M28: 0017-Trabalho, Emprego e Renda​ | N28: 2.011-Manutenção de Equipamentos Públicos | O28: 4.4.90.52.00-EQUIPAMENTOS E MATERIAL PERMANENTE | P28: VEÍCULOS DE TRAÇÃO MECÂNICA | Q28: 0 | R28: 150000 | S28: Não tem o Cód. na LDO
A29: 07 | B29: 001 | C29: 11 | D29: 333 | E29: 0017 | F29: 2.027 | G29: 3.3.90.30.00 | H29: 07.001.11.333.0017.2.027.3.3.90.30.00 | I29: 07 - SECRETARIA DE EMPREGO, TRABALHO E RENDA | J29: 001-GABINETE DA SECRETARIA DE EMPREGO, TRABALHO E RENDA | K29: 11-TRABALHO | L29: 333-EMPREGABILIDADE | M29: 0017-Trabalho, Emprego e Renda​ | N29: 2.027-Intermediação Profissional | O29: 3.3.90.30.00-MATERIAL DE CONSUMO | P29: GÊNEROS DE ALIMENTAÇÃO | Q29: 0 | R29: 10000 | S29: Não tem o Cód. na LDO
A30: 07 | B30: 001 | C30: 11 | D30: 333 | E30: 0017 | F30: 2.027 | G30: 4.4.90.52.00 | H30: 07.001.11.333.0017.2.027.4.4.90.52.00 | I30: 07 - SECRETARIA DE EMPREGO, TRABALHO E RENDA | J30: 001-GABINETE DA SECRETARIA DE EMPREGO, TRABALHO E RENDA | K30: 11-TRABALHO | L30: 333-EMPREGABILIDADE | M30: 0017-Trabalho, Emprego e Renda​ | N30: 2.027-Intermediação Profissional | O30: 4.4.90.52.00-EQUIPAMENTOS E MATERIAL PERMANENTE | P30: VEÍCULOS DE TRAÇÃO MECÂNICA | Q30: 0 | R30: 150000 | S30: Não tem o Cód. na LDO
A31: 07 | B31: 001 | C31: 11 | D31: 333 | E31: 0017 | F31: 2.004 | G31: 3.3.50.39.00 | H31: 07.001.11.333.0017.2.004.3.3.50.39.00 | I31: 07 - SECRETARIA DE EMPREGO, TRABALHO E RENDA | J31: 001-GABINETE DA SECRETARIA DE EMPREGO, TRABALHO E RENDA | K31: 11-TRABALHO | L31: 333-EMPREGABILIDADE | M31: 0017-Trabalho, Emprego e Renda​ | N31: 2.004-Qualificação Socioprofissional | O31: 3.3.50.39.00-OUTROS SERVIÇOS DE TERCEIROS - PESSOA JURÍDICA | P31: TERMO DE COLABORAÇÃO | Q31: 2967/2025 | R31: 2834440 | S31: Não tem o Cód. na LDO
A32: 07 | B32: 001 | C32: 11 | D32: 333 | E32: 0017 | F32: 2.004 | G32: 3.3.90.30.00 | H32: 07.001.11.333.0017.2.004.3.3.90.30.00 | I32: 07 - SECRETARIA DE EMPREGO, TRABALHO E RENDA | J32: 001-GABINETE DA SECRETARIA DE EMPREGO, TRABALHO E RENDA | K32: 11-TRABALHO | L32: 333-EMPREGABILIDADE | M32: 0017-Trabalho, Emprego e Renda​ | N32: 2.004-Qualificação Socioprofissional | O32: 3.3.90.30.00-MATERIAL DE CONSUMO | P32: MATERIAL DE EXPEDIENTE | Q32: 0 | R32: 45000 | S32: Não tem o Cód. na LDO
A33: 07 | B33: 001 | C33: 11 | D33: 333 | E33: 0017 | F33: 2.004 | G33: 3.3.90.39.00 | H33: 07.001.11.333.0017.2.004.3.3.90.39.00 | I33: 07 - SECRETARIA DE EMPREGO, TRABALHO E RENDA | J33: 001-GABINETE DA SECRETARIA DE EMPREGO, TRABALHO E RENDA | K33: 11-TRABALHO | L33: 333-EMPREGABILIDADE | M33: 0017-Trabalho, Emprego e Renda​ | N33: 2.004-Qualificação Socioprofissional | O33: 3.3.90.39.00-OUTROS SERVIÇOS DE TERCEIROS - PESSOA JURÍDICA | P33: SERVIÇOS GRÁFICOS E EDITORIAIS | Q33: 0 | R33: 30000 | S33: Não tem o Cód. na LDO
A34: 07 | B34: 001 | C34: 11 | D34: 333 | E34: 0017 | F34: 2.004 | G34: 3.3.90.39.00 | H34: 07.001.11.333.0017.2.004.3.3.90.39.00 | I34: 07 - SECRETARIA DE EMPREGO, TRABALHO E RENDA | J34: 001-GABINETE DA SECRETARIA DE EMPREGO, TRABALHO E RENDA | K34: 11-TRABALHO | L34: 333-EMPREGABILIDADE | M34: 0017-Trabalho, Emprego e Renda​ | N34: 2.004-Qualificação Socioprofissional | O34: 3.3.90.39.00-OUTROS SERVIÇOS DE TERCEIROS - PESSOA JURÍDICA | P34: FORNECIMENTO DE ALIMENTAÇÃO | Q34: 0 | R34: 30000 | S34: Não tem o Cód. na LDO
A35: 07 | B35: 001 | C35: 11 | D35: 333 | E35: 0017 | F35: 2.004 | G35: 3.3.90.39.00 | H35: 07.001.11.333.0017.2.004.3.3.90.39.00 | I35: 07 - SECRETARIA DE EMPREGO, TRABALHO E RENDA | J35: 001-GABINETE DA SECRETARIA DE EMPREGO, TRABALHO E RENDA | K35: 11-TRABALHO | L35: 333-EMPREGABILIDADE | M35: 0017-Trabalho, Emprego e Renda​ | N35: 2.004-Qualificação Socioprofissional | O35: 3.3.90.39.00-OUTROS SERVIÇOS DE TERCEIROS - PESSOA JURÍDICA | P35: OUTROS SERVIÇOS DE TERCEIRO PESSOA JURÍDICA - PAGAMENTO ANTECIPADO | Q35: 0 | R35: 30000 | S35: Não tem o Cód. na LDO
A36: 07 | B36: 001 | C36: 11 | D36: 334 | E36: 0017 | F36: 2.027 | G36: 3.3.90.30.00 | H36: 07.001.11.334.0017.2.027.3.3.90.30.00 | I36: 07 - SECRETARIA DE EMPREGO, TRABALHO E RENDA | J36: 001-FUNDO MUNICIPAL DO TRABALHO | K36: 11-TRABALHO | L36: 334-FOMENTO AO TRABALHO | M36: 0017-Trabalho, Emprego e Renda​ | N36: 2.027-Intermediação Profissional | O36: 3.3.90.30.00-MATERIAL DE CONSUMO | P36: MATERIAL PARA MANUTENÇÃO DE BENS IMÓVEIS | Q36: 0 | R36: 1 | S36: Não tem o Cód. na LDO
A37: 07 | B37: 001 | C37: 11 | D37: 334 | E37: 0017 | F37: 2.027 | G37: 3.3.90.39.00 | H37: 07.001.11.334.0017.2.027.3.3.90.39.00 | I37: 07 - SECRETARIA DE EMPREGO, TRABALHO E RENDA | J37: 001-FUNDO MUNICIPAL DO TRABALHO | K37: 11-TRABALHO | L37: 334-FOMENTO AO TRABALHO | M37: 0017-Trabalho, Emprego e Renda​ | N37: 2.027-Intermediação Profissional | O37: 3.3.90.39.00-OUTROS SERVIÇOS DE TERCEIROS - PESSOA JURÍDICA | P37: OUTROS SERVIÇOS DE TERCEIRO PESSOA JURÍDICA - PAGAMENTO ANTECIPADO | Q37: 106 | R37: 1 | S37: Não tem o Cód. na LDO
A38: 07 | B38: 001 | C38: 11 | D38: 334 | E38: 0017 | F38: 2.027 | G38: 4.4.90.52.00 | H38: 07.001.11.334.0017.2.027.4.4.90.52.00 | I38: 07 - SECRETARIA DE EMPREGO, TRABALHO E RENDA | J38: 001-FUNDO MUNICIPAL DO TRABALHO | K38: 11-TRABALHO | L38: 334-FOMENTO AO TRABALHO | M38: 0017-Trabalho, Emprego e Renda​ | N38: 2.027-Intermediação Profissional | O38: 4.4.90.52.00-EQUIPAMENTOS E MATERIAL PERMANENTE | P38: VEÍCULOS DE TRAÇÃO MECÂNICA | Q38: 0 | R38: 1 | S38: Não tem o Cód. na LDO
A39: 07 | B39: 001 | C39: 11 | D39: 334 | E39: 0017 | F39: 2.025 | G39: 3.3.90.30.00 | H39: 07.001.11.334.0017.2.025.3.3.90.30.00 | I39: 07 - SECRETARIA DE EMPREGO, TRABALHO E RENDA | J39: 001-GABINETE DA SECRETARIA DE EMPREGO, TRABALHO E RENDA | K39: 11-TRABALHO | L39: 334-FOMENTO AO TRABALHO | M39: 0017-Trabalho, Emprego e Renda​ | N39: 2.025-Auxílio para Inclusão no Mercado de Trabalho | O39: 3.3.90.30.00-MATERIAL DE CONSUMO | P39: MATERIAL DE EXPEDIENTE | Q39: 0 | R39: 40000 | S39: Não tem o Cód. na LDO
A40: 07 | B40: 001 | C40: 11 | D40: 334 | E40: 0017 | F40: 2.025 | G40: 3.3.90.30.00 | H40: 07.001.11.334.0017.2.025.3.3.90.30.00 | I40: 07 - SECRETARIA DE EMPREGO, TRABALHO E RENDA | J40: 001-GABINETE DA SECRETARIA DE EMPREGO, TRABALHO E RENDA | K40: 11-TRABALHO | L40: 334-FOMENTO AO TRABALHO | M40: 0017-Trabalho, Emprego e Renda​ | N40: 2.025-Auxílio para Inclusão no Mercado de Trabalho | O40: 3.3.90.30.00-MATERIAL DE CONSUMO | P40: UNIFORMES, TECIDOS E AVIAMENTOS | Q40: 0 | R40: 50000 | S40: Não tem o Cód. na LDO
A41: 07 | B41: 001 | C41: 11 | D41: 334 | E41: 0017 | F41: 2.025 | G41: 3.3.90.39.00 | H41: 07.001.11.334.0017.2.025.3.3.90.39.00 | I41: 07 - SECRETARIA DE EMPREGO, TRABALHO E RENDA | J41: 001-GABINETE DA SECRETARIA DE EMPREGO, TRABALHO E RENDA | K41: 11-TRABALHO | L41: 334-FOMENTO AO TRABALHO | M41: 0017-Trabalho, Emprego e Renda​ | N41: 2.025-Auxílio para Inclusão no Mercado de Trabalho | O41: 3.3.90.39.00-OUTROS SERVIÇOS DE TERCEIROS - PESSOA JURÍDICA | P41: SERVIÇOS GRÁFICOS E EDITORIAIS | Q41: 0 | R41: 150000 | S41: Não tem o Cód. na LDO
A42: 08 | B42: 001 | C42: 12 | D42: 122 | E42: 0001 | F42: 2.001 | G42: 3.3.90.92.00 | H42: 08.001.12.122.0001.2.001.3.3.90.92.00 | I42: 08 - SECRETARIA DE EDUCAÇÃO | J42: 001-GABINETE DA SECRETARIA DA EDUCAÇÃO | K42: 12-EDUCAÇÃO | L42: 122-ADMINISTRAÇÃO GERAL | M42: 0001-Administração e Coordenação Geral​ | N42: 2.001-Remuneração, Benefícios e Encargos | O42: 3.3.90.92.00-DESPESAS DE EXERCÍCIOS ANTERIORES | P42: RESSARCIMENTO DE DESPESAS COM PESSOAL REQUISITADO | Q42: PA 1466/2023 e 5551/2023 - Ressarcimento com Pessoa Requisitado - Pref. SP/Estado de SP | R42: 84000 | S42: Não tem o Cód. na LDO
A43: 08 | B43: 001 | C43: 12 | D43: 122 | E43: 0001 | F43: 2.001 | G43: 3.3.90.96.00 | H43: 08.001.12.122.0001.2.001.3.3.90.96.00 | I43: 08 - SECRETARIA DE EDUCAÇÃO | J43: 001-GABINETE DA SECRETARIA DA EDUCAÇÃO | K43: 12-EDUCAÇÃO | L43: 122-ADMINISTRAÇÃO GERAL | M43: 0001-Administração e Coordenação Geral​ | N43: 2.001-Remuneração, Benefícios e Encargos | O43: 3.3.90.96.00-RESSARCIMENTO DE DESPESAS DE PESSOAL REQUISITADO | P43: RESSARCIMENTO DE DESPESAS COM PESSOAL REQUISITADO | Q43: PA 1466/2023 e 5551/2023 - Ressarcimento com Pessoa Requisitado - Pref. SP/Estado de SP | R43: 320000 | S43: Não tem o Cód. na LDO
A44: 08 | B44: 001 | C44: 12 | D44: 122 | E44: 0002 | F44: 2.005 | G44: 3.3.90.30.00 | H44: 08.001.12.122.0002.2.005.3.3.90.30.00 | I44: 08 - SECRETARIA DE EDUCAÇÃO | J44: 001-GABINETE DA SECRETARIA DA EDUCAÇÃO | K44: 12-EDUCAÇÃO | L44: 122-ADMINISTRAÇÃO GERAL | M44: 0002-Governo Inteligente, Aberto e Inovador​ | N44: 2.005-Promoção de Eventos, Comunicação e Participação Social | O44: 3.3.90.30.00-MATERIAL DE CONSUMO | P44: MATERIAL DE EXPEDIENTE | Q44: Papelaria 7 de Setembro | R44: 420000 | S44: Não tem o Cód. na LDO
A45: 08 | B45: 001 | C45: 12 | D45: 122 | E45: 0002 | F45: 2.005 | G45: 3.3.90.30.00 | H45: 08.001.12.122.0002.2.005.3.3.90.30.00 | I45: 08 - SECRETARIA DE EDUCAÇÃO | J45: 001-GABINETE DA SECRETARIA DA EDUCAÇÃO | K45: 12-EDUCAÇÃO | L45: 122-ADMINISTRAÇÃO GERAL | M45: 0002-Governo Inteligente, Aberto e Inovador​ | N45: 2.005-Promoção de Eventos, Comunicação e Participação Social | O45: 3.3.90.30.00-MATERIAL DE CONSUMO | P45: GÊNEROS DE ALIMENTAÇÃO | Q45: Kit Lanche 7 de Setembro | R45: 1000000 | S45: Não tem o Cód. na LDO
A46: 08 | B46: 001 | C46: 12 | D46: 122 | E46: 0002 | F46: 2.005 | G46: 3.3.90.39.00 | H46: 08.001.12.122.0002.2.005.3.3.90.39.00 | I46: 08 - SECRETARIA DE EDUCAÇÃO | J46: 001-GABINETE DA SECRETARIA DA EDUCAÇÃO | K46: 12-EDUCAÇÃO | L46: 122-ADMINISTRAÇÃO GERAL | M46: 0002-Governo Inteligente, Aberto e Inovador​ | N46: 2.005-Promoção de Eventos, Comunicação e Participação Social | O46: 3.3.90.39.00-OUTROS SERVIÇOS DE TERCEIROS - PESSOA JURÍDICA | P46: FESTIVIDADES E HOMENAGENS | Q46: Decoração 7 de Setembro | R46: 1655000 | S46: Não tem o Cód. na LDO
A47: 08 | B47: 001 | C47: 12 | D47: 122 | E47: 0001 | F47: 2.011 | G47: 3.3.90.93.00 | H47: 08.001.12.122.0001.2.011.3.3.90.93.00 | I47: 08 - SECRETARIA DE EDUCAÇÃO | J47: 001-GABINETE DA SECRETARIA DA EDUCAÇÃO | K47: 12-EDUCAÇÃO | L47: 122-ADMINISTRAÇÃO GERAL | M47: 0001-Administração e Coordenação Geral​ | N47: 2.011-Manutenção de Equipamentos Públicos | O47: 3.3.90.93.00-INDENIZAÇÕES E RESTITUIÇÕES | P47: INDENIZAÇÕES | Q47: Indenização por dados | R47: 5000 | S47: Não tem o Cód. na LDO
A48: 08 | B48: 001 | C48: 12 | D48: 361 | E48: 0016 | F48: 2.018 | G48: 3.3.90.30.00 | H48: 08.001.12.361.0016.2.018.3.3.90.30.00 | I48: 08 - SECRETARIA DE EDUCAÇÃO | J48: 001-GABINETE DA SECRETARIA DA EDUCAÇÃO | K48: 12-EDUCAÇÃO | L48: 361-ENSINO FUNDAMENTAL | M48: 0016-Escola para Todos​ | N48: 2.018-Conectividade e Tecnologia na Educação | O48: 3.3.90.30.00-MATERIAL DE CONSUMO | P48: OUTROS MATERIAIS DE CONSUMO | Q48: PA 17682/2021 - Kit Conectividade -MULTI LASER | R48: 1 | S48: Não tem o Cód. na LDO
A49: 08 | B49: 001 | C49: 12 | D49: 366 | E49: 0016 | F49: 2.019 | G49: 3.3.90.39.00 | H49: 08.001.12.366.0016.2.019.3.3.90.39.00 | I49: 08 - SECRETARIA DE EDUCAÇÃO | J49: 001-GABINETE DA SECRETARIA DA EDUCAÇÃO | K49: 12-EDUCAÇÃO | L49: 366-EDUCAÇÃO DE JOVENS E ADULTOS | M49: 0016-Escola para Todos​ | N49: 2.019-Ações Pedagógicas Complementares | O49: 3.3.90.39.00-OUTROS SERVIÇOS DE TERCEIROS - PESSOA JURÍDICA | P49: OUTROS SERVIÇOS DE TERCEIROS - PESSOA JURÍDICA | Q49: PA 11604/2007 - Mova Entidades | R49: 79200 | S49: Não tem o Cód. na LDO
A50: 09 | B50: 001 | C50: 04 | D50: 128 | E50: 0002 | F50: 2.003 | G50: 3.3.90.36.00 | H50: 09.001.04.128.0002.2.003.3.3.90.36.00 | I50: 09 - SECRETARIA DA SAÚDE | J50: 001-GABINETE DA SECRETARIA DA SAÚDE | K50: 4-ADMINISTRAÇÃO | L50: 128-FORMAÇÃO DE RECURSOS HUMANOS | M50: 0002-Governo Inteligente, Aberto e Inovador​ | N50: 2.003-Qualificação de Servidores e Processos Institucionais | O50: 3.3.90.36.00-OUTROS SERVIÇOS DE TERCEIROS - PESSOA FÍSICA | Q50: Cursos e Capacitação | R50: 1 | S50: Não tem o Cód. na LDO
A51: 09 | B51: 010 | C51: 10 | D51: 302 | E51: 0002 | F51: 2.014 | G51: 3.3.90.30.00 | H51: 09.010.10.302.0002.2.014.3.3.90.30.00 | I51: 09 - SECRETARIA DA SAÚDE | J51: 010-DIRETORIA GERAL DE URGÊNCIA E EMERGÊNCIA | K51: 10-SAÚDE | L51: 302-ASSISTÊNCIA HOSPITALAR E AMBULATORIAL | M51: 0002-Governo Inteligente, Aberto e Inovador​ | N51: 2.014-Manutenção de Equipamentos Públicos - Atenção Hospitalar e Urgência e Emergência | O51: 3.3.90.30.00-MATERIAL DE CONSUMO | P51: GÊNEROS DE ALIMENTAÇÃO | Q51: 2.971/2025 | R51: 274000 | S51: Não tem o Cód. na LDO
A52: 09 | B52: 008 | C52: 10 | D52: 301 | E52: 0015 | F52: 2.012 | H52: 09.008.10.301.0015.2.012. | I52: 09 - SECRETARIA DA SAÚDE | J52: 008-DIRETORIA GERAL DE ATENÇÃO PRIMÁRIA EM SAÚDE | K52: 10-SAÚDE | L52: 301-ATENÇÃO BÁSICA | M52: 0015-Atenção e Cuidado em Saúde​ | N52: 2.012-Manutenção de Equipamentos Públicos - Atenção Primária | Q52: PMM - 3.3.90.48 | R52: 3037000 | S52: Não tem o Cód. na LDO
A53: 09 | B53: 008 | C53: 10 | D53: 301 | E53: 0014 | F53: 2.012 | G53: 3.3.90.39.00 | H53: 09.008.10.301.0014.2.012.3.3.90.39.00 | I53: 09 - SECRETARIA DA SAÚDE | J53: 008-DIRETORIA GERAL DE ATENÇÃO PRIMÁRIA EM SAÚDE | K53: 10-SAÚDE | L53: 301-ATENÇÃO BÁSICA | M53: 0014-Gestão em Saúde​ | N53: 2.012-Manutenção de Equipamentos Públicos - Atenção Primária | O53: 3.3.90.39.00-OUTROS SERVIÇOS DE TERCEIROS - PESSOA JURÍDICA | P53: OUTROS SERVIÇOS DE TERCEIROS - PESSOA JURÍDICA | Q53: Próteses Dentárias | R53: 960000 | S53: Não tem o Cód. na LDO
A54: 09 | B54: 012 | C54: 10 | D54: 303 | E54: 0015 | F54: 2.011 | G54: 3.3.90.32.00 | H54: 09.012.10.303.0015.2.011.3.3.90.32.00 | I54: 09 - SECRETARIA DA SAÚDE | J54: 012-DEPARTAMENTO DE ASSISTÊNCIA FARMACÊUTICA | K54: 10-SAÚDE | L54: 303-SUPORTE PROFILÁTICO E TERAPÊUTICO | M54: 0015-Atenção e Cuidado em Saúde​ | N54: 2.011-Manutenção de Equipamentos Públicos | O54: 3.3.90.32.00-MATERIAL, BEM OU SERVIÇO PARA DISTRIBUIÇÃO GRATUITA | P54: MEDICAMENTOS PARA USO DOMICILIAR | Q54: Medicamentos Manipulados | R54: 50000 | S54: Não tem o Cód. na LDO
A55: 09 | B55: 006 | C55: 10 | D55: 302 | E55: 0015 | F55: 1.002 | H55: 09.006.10.302.0015.1.002. | I55: 09 - SECRETARIA DA SAÚDE | J55: 006-HOSPITAL E MATERNIDADE MUNICIPAL AMADOR AGUIAR | K55: 10-SAÚDE | L55: 302-ASSISTÊNCIA HOSPITALAR E AMBULATORIAL | M55: 0015-Atenção e Cuidado em Saúde​ | N55: 1.002-Reforma e Ampliação de Unidades | Q55: 4.4.90.51 | R55: 1 | S55: Não tem o Cód. na LDO
A56: 09 | B56: 015 | C56: 10 | D56: 302 | E56: 0015 | F56: 2.014 | G56: 3.3.90.30.00 | H56: 09.015.10.302.0015.2.014.3.3.90.30.00 | I56: 09 - SECRETARIA DA SAÚDE | J56: 015-DIRETORIA GERAL DA GESTÃO DE SAÚDE | K56: 10-SAÚDE | L56: 302-ASSISTÊNCIA HOSPITALAR E AMBULATORIAL | M56: 0015-Atenção e Cuidado em Saúde​ | N56: 2.014-Manutenção de Equipamentos Públicos - Atenção Hospitalar e Urgência e Emergência | O56: 3.3.90.30.00-MATERIAL DE CONSUMO | P56: OUTROS MATERIAIS DE CONSUMO | Q56: EPI e EPC | R56: 300000 | S56: Não tem o Cód. na LDO
A57: 09 | B57: 008 | C57: 10 | D57: 301 | E57: 0015 | F57: 1.002 | H57: 09.008.10.301.0015.1.002. | I57: 09 - SECRETARIA DA SAÚDE | J57: 008-DIRETORIA GERAL DE ATENÇÃO PRIMÁRIA EM SAÚDE | K57: 10-SAÚDE | L57: 301-ATENÇÃO BÁSICA | M57: 0015-Atenção e Cuidado em Saúde​ | N57: 1.002-Reforma e Ampliação de Unidades | Q57: 4.4.90.51 | R57: 1 | S57: Não tem o Cód. na LDO
A58: 09 | B58: 009 | C58: 10 | D58: 302 | E58: 0015 | F58: 1.002 | H58: 09.009.10.302.0015.1.002. | I58: 09 - SECRETARIA DA SAÚDE | J58: 009-DIRETORIA GERAL DA ATENÇÃO SECUNDÁRIA EM SAÚDE | K58: 10-SAÚDE | L58: 302-ASSISTÊNCIA HOSPITALAR E AMBULATORIAL | M58: 0015-Atenção e Cuidado em Saúde​ | N58: 1.002-Reforma e Ampliação de Unidades | Q58: 4.4.90.51 | R58: 1 | S58: Não tem o Cód. na LDO
A59: 09 | B59: 010 | C59: 10 | D59: 302 | E59: 0015 | F59: 1.002 | H59: 09.010.10.302.0015.1.002. | I59: 09 - SECRETARIA DA SAÚDE | J59: 010-DIRETORIA GERAL DE URGÊNCIA E EMERGÊNCIA | K59: 10-SAÚDE | L59: 302-ASSISTÊNCIA HOSPITALAR E AMBULATORIAL | M59: 0015-Atenção e Cuidado em Saúde​ | N59: 1.002-Reforma e Ampliação de Unidades | Q59: 4.4.90.51 | R59: 1 | S59: Não tem o Cód. na LDO
A60: 09 | B60: 015 | C60: 10 | D60: 122 | E60: 0014 | F60: 1.002 | H60: 09.015.10.122.0014.1.002. | I60: 09 - SECRETARIA DA SAÚDE | J60: 015-DIRETORIA GERAL DA GESTÃO DE SAÚDE | K60: 10-SAÚDE | L60: 122-ADMINISTRAÇÃO GERAL | M60: 0014-Gestão em Saúde​ | N60: 1.002-Reforma e Ampliação de Unidades | Q60: 4.4.90.51 | R60: 1 | S60: Não tem o Cód. na LDO
A61: 09 | B61: 015 | C61: 10 | D61: 122 | E61: 0014 | F61: 2.011 | G61: 3.3.90.92.00 | H61: 09.015.10.122.0014.2.011.3.3.90.92.00 | I61: 09 - SECRETARIA DA SAÚDE | J61: 015-DIRETORIA GERAL DA GESTÃO DE SAÚDE | K61: 10-SAÚDE | L61: 122-ADMINISTRAÇÃO GERAL | M61: 0014-Gestão em Saúde​ | N61: 2.011-Manutenção de Equipamentos Públicos | O61: 3.3.90.92.00-DESPESAS DE EXERCÍCIOS ANTERIORES | P61: OUTRAS DESPESAS DE EXERCÍCIOS ANTERIORES | R61: 1 | S61: Não tem o Cód. na LDO
A62: 11 | B62: 001 | C62: 04 | D62: 122 | E62: 0001 | F62: 1.001 | G62: 3.3.90.30.00 | H62: 11.001.04.122.0001.1.001.3.3.90.30.00 | I62: 11 - SECRETARIA DE SERVIÇOS E OBRAS | J62: 001-GABINETE DA SECRETARIA DE SERVIÇOS E OBRAS | K62: 4-ADMINISTRAÇÃO | L62: 122-ADMINISTRAÇÃO GERAL | M62: 0001-Administração e Coordenação Geral​ | N62: 1.001-Estudos, Pesquisas, Planos e Projetos | O62: 3.3.90.30.00-MATERIAL DE CONSUMO | P62: MATERIAL DE COPA E COZINHA | Q62: 581/2025-3541/2024 | R62: 30000 | S62: Não tem o Cód. na LDO
A63: 11 | B63: 001 | C63: 04 | D63: 122 | E63: 0001 | F63: 1.001 | G63: 3.3.90.30.00 | H63: 11.001.04.122.0001.1.001.3.3.90.30.00 | I63: 11 - SECRETARIA DE SERVIÇOS E OBRAS | J63: 001-GABINETE DA SECRETARIA DE SERVIÇOS E OBRAS | K63: 4-ADMINISTRAÇÃO | L63: 122-ADMINISTRAÇÃO GERAL | M63: 0001-Administração e Coordenação Geral​ | N63: 1.001-Estudos, Pesquisas, Planos e Projetos | O63: 3.3.90.30.00-MATERIAL DE CONSUMO | P63: GÁS ENGARRAFADO | Q63: 25961/2022 | R63: 7000 | S63: Não tem o Cód. na LDO
A64: 11 | B64: 001 | C64: 04 | D64: 122 | E64: 0001 | F64: 1.001 | G64: 3.3.90.30.00 | H64: 11.001.04.122.0001.1.001.3.3.90.30.00 | I64: 11 - SECRETARIA DE SERVIÇOS E OBRAS | J64: 001-GABINETE DA SECRETARIA DE SERVIÇOS E OBRAS | K64: 4-ADMINISTRAÇÃO | L64: 122-ADMINISTRAÇÃO GERAL | M64: 0001-Administração e Coordenação Geral​ | N64: 1.001-Estudos, Pesquisas, Planos e Projetos | O64: 3.3.90.30.00-MATERIAL DE CONSUMO | P64: FERRAMENTAS | Q64: 2234/2024 | R64: 200000 | S64: Não tem o Cód. na LDO
A65: 11 | B65: 001 | C65: 04 | D65: 122 | E65: 0001 | F65: 1.001 | G65: 3.3.90.30.00 | H65: 11.001.04.122.0001.1.001.3.3.90.30.00 | I65: 11 - SECRETARIA DE SERVIÇOS E OBRAS | J65: 001-GABINETE DA SECRETARIA DE SERVIÇOS E OBRAS | K65: 4-ADMINISTRAÇÃO | L65: 122-ADMINISTRAÇÃO GERAL | M65: 0001-Administração e Coordenação Geral​ | N65: 1.001-Estudos, Pesquisas, Planos e Projetos | O65: 3.3.90.30.00-MATERIAL DE CONSUMO | P65: GÊNEROS DE ALIMENTAÇÃO | Q65: 3541/2024 | R65: 60000 | S65: Não tem o Cód. na LDO
A66: 11 | B66: 001 | C66: 04 | D66: 122 | E66: 0001 | F66: 1.001 | G66: 3.3.90.30.00 | H66: 11.001.04.122.0001.1.001.3.3.90.30.00 | I66: 11 - SECRETARIA DE SERVIÇOS E OBRAS | J66: 001-GABINETE DA SECRETARIA DE SERVIÇOS E OBRAS | K66: 4-ADMINISTRAÇÃO | L66: 122-ADMINISTRAÇÃO GERAL | M66: 0001-Administração e Coordenação Geral​ | N66: 1.001-Estudos, Pesquisas, Planos e Projetos | O66: 3.3.90.30.00-MATERIAL DE CONSUMO | P66: MATERIAL DE EXPEDIENTE | Q66: 581/2025 | R66: 100000 | S66: Não tem o Cód. na LDO
A67: 11 | B67: 001 | C67: 04 | D67: 122 | E67: 0001 | F67: 1.001 | G67: 3.3.90.30.00 | H67: 11.001.04.122.0001.1.001.3.3.90.30.00 | I67: 11 - SECRETARIA DE SERVIÇOS E OBRAS | J67: 001-GABINETE DA SECRETARIA DE SERVIÇOS E OBRAS | K67: 4-ADMINISTRAÇÃO | L67: 122-ADMINISTRAÇÃO GERAL | M67: 0001-Administração e Coordenação Geral​ | N67: 1.001-Estudos, Pesquisas, Planos e Projetos | O67: 3.3.90.30.00-MATERIAL DE CONSUMO | P67: MATERIAL DE LIMPEZA E PRODUTOS DE HIGIENIZAÇÃO | Q67: 850/2024 | R67: 200000 | S67: Não tem o Cód. na LDO
A68: 11 | B68: 001 | C68: 04 | D68: 122 | E68: 0001 | F68: 1.002 | G68: 3.3.90.30.00 | H68: 11.001.04.122.0001.1.002.3.3.90.30.00 | I68: 11 - SECRETARIA DE SERVIÇOS E OBRAS | J68: 001-GABINETE DA SECRETARIA DE SERVIÇOS E OBRAS | K68: 4-ADMINISTRAÇÃO | L68: 122-ADMINISTRAÇÃO GERAL | M68: 0001-Administração e Coordenação Geral​ | N68: 1.002-Reforma e Ampliação de Unidades | O68: 3.3.90.30.00-MATERIAL DE CONSUMO | P68: MATERIAL PARA MANUTENÇÃO DE BENS IMÓVEIS | R68: 1 | S68: Não tem o Cód. na LDO
A69: 11 | B69: 001 | C69: 04 | D69: 121 | E69: 0011 | F69: 2.011 | G69: 4.4.90.52.00 | H69: 11.001.04.121.0011.2.011.4.4.90.52.00 | I69: 11 - SECRETARIA DE SERVIÇOS E OBRAS | J69: 001-GABINETE DA SECRETARIA DE SERVIÇOS E OBRAS | K69: 4-ADMINISTRAÇÃO | L69: 121-PLANEJAMENTO E ORÇAMENTO | M69: 0011-Zeladoria Urbana e Cuidados com a Cidade​ | N69: 2.011-Manutenção de Equipamentos Públicos | O69: 4.4.90.52.00-EQUIPAMENTOS E MATERIAL PERMANENTE | P69: MÁQUINAS, UTENSÍLIOS E EQUIPAMENTOS DIVERSOS | Q69: 3654/2024 | R69: 10000 | S69: Não tem o Cód. na LDO
A70: 11 | B70: 001 | C70: 04 | D70: 122 | E70: 0011 | F70: 1.003 | G70: 3.3.90.39.00 | H70: 11.001.04.122.0011.1.003.3.3.90.39.00 | I70: 11 - SECRETARIA DE SERVIÇOS E OBRAS | J70: 001-GABINETE DA SECRETARIA DE SERVIÇOS E OBRAS | K70: 4-ADMINISTRAÇÃO | L70: 122-ADMINISTRAÇÃO GERAL | M70: 0011-Zeladoria Urbana e Cuidados com a Cidade​ | N70: 1.003-Implantação de Novas Unidades | O70: 3.3.90.39.00-OUTROS SERVIÇOS DE TERCEIROS - PESSOA JURÍDICA | P70: OUTROS SERVIÇOS DE TERCEIROS - PESSOA JURÍDICA | Q70: 3001/2026- Operação da Verticalização | R70: 6387943.8 | S70: Não tem o Cód. na LDO
A71: 11 | B71: 001 | C71: 04 | D71: 452 | E71: 0011 | F71: 2.034 | G71: 3.3.90.39.00 | H71: 11.001.04.452.0011.2.034.3.3.90.39.00 | I71: 11 - SECRETARIA DE SERVIÇOS E OBRAS | J71: 001-GABINETE DA SECRETARIA DE SERVIÇOS E OBRAS | K71: 4-ADMINISTRAÇÃO | L71: 452-SERVIÇOS URBNOS | M71: 0011-Zeladoria Urbana e Cuidados com a Cidade​ | N71: 2.034-Manutenção da Infraestrutura Viária | O71: 3.3.90.39.00-OUTROS SERVIÇOS DE TERCEIROS - PESSOA JURÍDICA | P71: LIMPEZA E CONSERVAÇÃO | Q71: 1085/2026-LOCAÇÃO DE MAQUINAS | R71: 6000000 | S71: Não tem o Cód. na LDO
A72: 11 | B72: 001 | C72: 04 | D72: 121 | E72: 0011 | F72: 2.011 | G72: 3.3.90.93.00 | H72: 11.001.04.121.0011.2.011.3.3.90.93.00 | I72: 11 - SECRETARIA DE SERVIÇOS E OBRAS | J72: 001-GABINETE DA SECRETARIA DE SERVIÇOS E OBRAS | K72: 4-ADMINISTRAÇÃO | L72: 121-PLANEJAMENTO E ORÇAMENTO | M72: 0011-Zeladoria Urbana e Cuidados com a Cidade​ | N72: 2.011-Manutenção de Equipamentos Públicos | O72: 3.3.90.93.00-INDENIZAÇÕES E RESTITUIÇÕES | P72: DIVERSAS INDENIZAÇÕES E RESTITUIÇÕES | R72: 5000 | S72: Não tem o Cód. na LDO
A73: 11 | B73: 001 | C73: 15 | D73: 451 | E73: 0011 | F73: 2.011 | G73: 4.4.90.51.00 | H73: 11.001.15.451.0011.2.011.4.4.90.51.00 | I73: 11 - SECRETARIA DE SERVIÇOS E OBRAS | J73: 001-GABINETE DA SECRETARIA DE SERVIÇOS E OBRAS | K73: 15-URBANISMO | L73: 451-INFRA-ESTRUTURA URBANA | M73: 0011-Zeladoria Urbana e Cuidados com a Cidade​ | N73: 2.011-Manutenção de Equipamentos Públicos | O73: 4.4.90.51.00-OBRAS E INSTALAÇÕES | P73: OBRAS EM ANDAMENTO | Q73: 7603/2022- MAURO LINDENBERG | R73: 3000000 | S73: Não tem o Cód. na LDO
A74: 11 | B74: 001 | C74: 15 | D74: 451 | E74: 0011 | F74: 2.011 | G74: 4.4.90.51.00 | H74: 11.001.15.451.0011.2.011.4.4.90.51.00 | I74: 11 - SECRETARIA DE SERVIÇOS E OBRAS | J74: 001-GABINETE DA SECRETARIA DE SERVIÇOS E OBRAS | K74: 15-URBANISMO | L74: 451-INFRA-ESTRUTURA URBANA | M74: 0011-Zeladoria Urbana e Cuidados com a Cidade​ | N74: 2.011-Manutenção de Equipamentos Públicos | O74: 4.4.90.51.00-OBRAS E INSTALAÇÕES | P74: OBRAS EM ANDAMENTO | Q74: 2269/2022-RECAPE TRECHO 3 | R74: 187659.84 | S74: Não tem o Cód. na LDO
A75: 11 | B75: 001 | C75: 15 | D75: 451 | E75: 0011 | F75: 2.011 | G75: 4.4.90.51.00 | H75: 11.001.15.451.0011.2.011.4.4.90.51.00 | I75: 11 - SECRETARIA DE SERVIÇOS E OBRAS | J75: 001-GABINETE DA SECRETARIA DE SERVIÇOS E OBRAS | K75: 15-URBANISMO | L75: 451-INFRA-ESTRUTURA URBANA | M75: 0011-Zeladoria Urbana e Cuidados com a Cidade​ | N75: 2.011-Manutenção de Equipamentos Públicos | O75: 4.4.90.51.00-OBRAS E INSTALAÇÕES | P75: OBRAS EM ANDAMENTO | Q75: 13011/20213-SANTA RITA | R75: 183662.89 | S75: Não tem o Cód. na LDO
A76: 12 | B76: 001 | C76: 04 | D76: 122 | E76: 0002 | F76: 2.032 | G76: 3.3.50.39.00 | H76: 12.001.04.122.0002.2.032.3.3.50.39.00 | I76: 12 - SECRETARIA DE ESPORTE, RECREAÇÃO E LAZER | J76: 001-GABINETE DA SECRETARIA DE ESPORTE, RECREAÇÃO E LAZER | K76: 4-ADMINISTRAÇÃO | L76: 122-ADMINISTRAÇÃO GERAL | M76: 0002-Governo Inteligente, Aberto e Inovador​ | N76: 2.032-Iniciação Esportiva | O76: 3.3.50.39.00-OUTROS SERVIÇOS DE TERCEIROS - PESSOA JURÍDICA | P76: TERMO DE FOMENTO | R76: 1 | S76: Não tem o Cód. na LDO
A77: 12 | B77: 001 | C77: 04 | D77: 122 | E77: 0001 | F77: 2.011 | G77: 3.3.90.30.00 | H77: 12.001.04.122.0001.2.011.3.3.90.30.00 | I77: 12 - SECRETARIA DE ESPORTE, RECREAÇÃO E LAZER | J77: 001-GABINETE DA SECRETARIA DE ESPORTE, RECREAÇÃO E LAZER | K77: 4-ADMINISTRAÇÃO | L77: 122-ADMINISTRAÇÃO GERAL | M77: 0001-Administração e Coordenação Geral​ | N77: 2.011-Manutenção de Equipamentos Públicos | O77: 3.3.90.30.00-MATERIAL DE CONSUMO | P77: FERRAMENTAS | R77: 10000 | S77: Não tem o Cód. na LDO
A78: 12 | B78: 001 | C78: 04 | D78: 122 | E78: 0001 | F78: 2.011 | G78: 3.3.90.30.00 | H78: 12.001.04.122.0001.2.011.3.3.90.30.00 | I78: 12 - SECRETARIA DE ESPORTE, RECREAÇÃO E LAZER | J78: 001-GABINETE DA SECRETARIA DE ESPORTE, RECREAÇÃO E LAZER | K78: 4-ADMINISTRAÇÃO | L78: 122-ADMINISTRAÇÃO GERAL | M78: 0001-Administração e Coordenação Geral​ | N78: 2.011-Manutenção de Equipamentos Públicos | O78: 3.3.90.30.00-MATERIAL DE CONSUMO | P78: GÊNEROS DE ALIMENTAÇÃO | R78: 350000 | S78: Não tem o Cód. na LDO
A79: 12 | B79: 001 | C79: 04 | D79: 122 | E79: 0001 | F79: 2.011 | G79: 3.3.90.30.00 | H79: 12.001.04.122.0001.2.011.3.3.90.30.00 | I79: 12 - SECRETARIA DE ESPORTE, RECREAÇÃO E LAZER | J79: 001-GABINETE DA SECRETARIA DE ESPORTE, RECREAÇÃO E LAZER | K79: 4-ADMINISTRAÇÃO | L79: 122-ADMINISTRAÇÃO GERAL | M79: 0001-Administração e Coordenação Geral​ | N79: 2.011-Manutenção de Equipamentos Públicos | O79: 3.3.90.30.00-MATERIAL DE CONSUMO | P79: MATERIAL DE COPA E COZINHA | R79: 50000 | S79: Não tem o Cód. na LDO
A80: 12 | B80: 001 | C80: 04 | D80: 122 | E80: 0001 | F80: 2.011 | G80: 3.3.90.30.00 | H80: 12.001.04.122.0001.2.011.3.3.90.30.00 | I80: 12 - SECRETARIA DE ESPORTE, RECREAÇÃO E LAZER | J80: 001-GABINETE DA SECRETARIA DE ESPORTE, RECREAÇÃO E LAZER | K80: 4-ADMINISTRAÇÃO | L80: 122-ADMINISTRAÇÃO GERAL | M80: 0001-Administração e Coordenação Geral​ | N80: 2.011-Manutenção de Equipamentos Públicos | O80: 3.3.90.30.00-MATERIAL DE CONSUMO | P80: MATERIAL DE EXPEDIENTE | R80: 30000 | S80: Não tem o Cód. na LDO
A81: 12 | B81: 001 | C81: 04 | D81: 122 | E81: 0001 | F81: 2.011 | G81: 3.3.90.30.00 | H81: 12.001.04.122.0001.2.011.3.3.90.30.00 | I81: 12 - SECRETARIA DE ESPORTE, RECREAÇÃO E LAZER | J81: 001-GABINETE DA SECRETARIA DE ESPORTE, RECREAÇÃO E LAZER | K81: 4-ADMINISTRAÇÃO | L81: 122-ADMINISTRAÇÃO GERAL | M81: 0001-Administração e Coordenação Geral​ | N81: 2.011-Manutenção de Equipamentos Públicos | O81: 3.3.90.30.00-MATERIAL DE CONSUMO | P81: MATERIAL DE LIMPEZA E PRODUTOS DE HIGIENIZAÇÃO | R81: 250000 | S81: Não tem o Cód. na LDO
A82: 12 | B82: 001 | C82: 04 | D82: 122 | E82: 0001 | F82: 2.011 | G82: 3.3.90.30.00 | H82: 12.001.04.122.0001.2.011.3.3.90.30.00 | I82: 12 - SECRETARIA DE ESPORTE, RECREAÇÃO E LAZER | J82: 001-GABINETE DA SECRETARIA DE ESPORTE, RECREAÇÃO E LAZER | K82: 4-ADMINISTRAÇÃO | L82: 122-ADMINISTRAÇÃO GERAL | M82: 0001-Administração e Coordenação Geral​ | N82: 2.011-Manutenção de Equipamentos Públicos | O82: 3.3.90.30.00-MATERIAL DE CONSUMO | P82: MATERIAL DE PROCESSAMENTO DE DADOS | R82: 10000 | S82: Não tem o Cód. na LDO
A83: 12 | B83: 001 | C83: 04 | D83: 122 | E83: 0001 | F83: 2.011 | G83: 3.3.90.30.00 | H83: 12.001.04.122.0001.2.011.3.3.90.30.00 | I83: 12 - SECRETARIA DE ESPORTE, RECREAÇÃO E LAZER | J83: 001-GABINETE DA SECRETARIA DE ESPORTE, RECREAÇÃO E LAZER | K83: 4-ADMINISTRAÇÃO | L83: 122-ADMINISTRAÇÃO GERAL | M83: 0001-Administração e Coordenação Geral​ | N83: 2.011-Manutenção de Equipamentos Públicos | O83: 3.3.90.30.00-MATERIAL DE CONSUMO | P83: MATERIAL ELÉTRICO E ELETRÔNICO | R83: 100000 | S83: Não tem o Cód. na LDO
A84: 12 | B84: 001 | C84: 04 | D84: 122 | E84: 0001 | F84: 2.011 | G84: 3.3.90.30.00 | H84: 12.001.04.122.0001.2.011.3.3.90.30.00 | I84: 12 - SECRETARIA DE ESPORTE, RECREAÇÃO E LAZER | J84: 001-GABINETE DA SECRETARIA DE ESPORTE, RECREAÇÃO E LAZER | K84: 4-ADMINISTRAÇÃO | L84: 122-ADMINISTRAÇÃO GERAL | M84: 0001-Administração e Coordenação Geral​ | N84: 2.011-Manutenção de Equipamentos Públicos | O84: 3.3.90.30.00-MATERIAL DE CONSUMO | P84: MATERIAL PARA MANUTENÇÃO DE BENS IMÓVEIS | R84: 150000 | S84: Não tem o Cód. na LDO
A85: 12 | B85: 001 | C85: 04 | D85: 122 | E85: 0001 | F85: 2.011 | G85: 3.3.90.30.00 | H85: 12.001.04.122.0001.2.011.3.3.90.30.00 | I85: 12 - SECRETARIA DE ESPORTE, RECREAÇÃO E LAZER | J85: 001-GABINETE DA SECRETARIA DE ESPORTE, RECREAÇÃO E LAZER | K85: 4-ADMINISTRAÇÃO | L85: 122-ADMINISTRAÇÃO GERAL | M85: 0001-Administração e Coordenação Geral​ | N85: 2.011-Manutenção de Equipamentos Públicos | O85: 3.3.90.30.00-MATERIAL DE CONSUMO | P85: MATERIAL PARA MANUTENÇÃO DE VEÍCULOS | R85: 50000 | S85: Não tem o Cód. na LDO
A86: 12 | B86: 001 | C86: 04 | D86: 122 | E86: 0001 | F86: 2.011 | G86: 3.3.90.30.00 | H86: 12.001.04.122.0001.2.011.3.3.90.30.00 | I86: 12 - SECRETARIA DE ESPORTE, RECREAÇÃO E LAZER | J86: 001-GABINETE DA SECRETARIA DE ESPORTE, RECREAÇÃO E LAZER | K86: 4-ADMINISTRAÇÃO | L86: 122-ADMINISTRAÇÃO GERAL | M86: 0001-Administração e Coordenação Geral​ | N86: 2.011-Manutenção de Equipamentos Públicos | O86: 3.3.90.30.00-MATERIAL DE CONSUMO | P86: MATERIAL QUÍMICO | R86: 1 | S86: Não tem o Cód. na LDO
A87: 12 | B87: 001 | C87: 04 | D87: 122 | E87: 0001 | F87: 2.011 | G87: 3.3.90.30.00 | H87: 12.001.04.122.0001.2.011.3.3.90.30.00 | I87: 12 - SECRETARIA DE ESPORTE, RECREAÇÃO E LAZER | J87: 001-GABINETE DA SECRETARIA DE ESPORTE, RECREAÇÃO E LAZER | K87: 4-ADMINISTRAÇÃO | L87: 122-ADMINISTRAÇÃO GERAL | M87: 0001-Administração e Coordenação Geral​ | N87: 2.011-Manutenção de Equipamentos Públicos | O87: 3.3.90.30.00-MATERIAL DE CONSUMO | P87: OUTROS MATERIAIS DE CONSUMO | R87: 100000 | S87: Não tem o Cód. na LDO
... A103: 12 | B103: 001 | C103: 04 | D103: 122 | E103: 0001 | F103: 2.006 | G103: 3.3.90.93.00 | H103: 12.001.04.122.0001.2.006.3.3.90.93.00 | I103: 12 - SECRETARIA DE ESPORTE, RECREAÇÃO E LAZER | J103: 001-GABINETE DA SECRETARIA DE ESPORTE, RECREAÇÃO E LAZER | K103: 4-ADMINISTRAÇÃO | L103: 122-ADMINISTRAÇÃO GERAL | M103: 0001-Administração e Coordenação Geral​ | N103: 2.006-Representações Oficiais | O103: 3.3.90.93.00-INDENIZAÇÕES E RESTITUIÇÕES | P103: RESSARCIMENTO DE PASSAGENS E DESPESAS COM LOCOMOÇÃO | R103: 1 | S103: Não tem o Cód. na LDO
A104: 12 | B104: 001 | C104: 04 | D104: 122 | E104: 0002 | F104: 1.002 | G104: 4.4.90.51.00 | H104: 12.001.04.122.0002.1.002.4.4.90.51.00 | I104: 12 - SECRETARIA DE ESPORTE, RECREAÇÃO E LAZER | J104: 001-GABINETE DA SECRETARIA DE ESPORTE, RECREAÇÃO E LAZER | K104: 4-ADMINISTRAÇÃO | L104: 122-ADMINISTRAÇÃO GERAL | M104: 0002-Governo Inteligente, Aberto e Inovador​ | N104: 1.002-Reforma e Ampliação de Unidades | O104: 4.4.90.51.00-OBRAS E INSTALAÇÕES | R104: 1 | S104: Não tem o Cód. na LDO
A105: 12 | B105: 001 | C105: 04 | D105: 121 | E105: 0010 | F105: 2.030 | G105: 4.4.90.52.00 | H105: 12.001.04.121.0010.2.030.4.4.90.52.00 | I105: 12 - SECRETARIA DE ESPORTE, RECREAÇÃO E LAZER | J105: 001-GABINETE DA SECRETARIA DE ESPORTE, RECREAÇÃO E LAZER | K105: 4-ADMINISTRAÇÃO | L105: 121-PLANEJAMENTO E ORÇAMENTO | M105: 0010-Esporte, Lazer e Bem-Estar​ | N105: 2.030-Apoio ao Esporte de Alto Rendimento | O105: 4.4.90.52.00-EQUIPAMENTOS E MATERIAL PERMANENTE | R105: 600000 | S105: Não tem o Cód. na LDO
A106: 12 | B106: 001 | C106: 04 | D106: 122 | E106: 0002 | F106: 2.028 | G106: 3.3.90.39.00 | H106: 12.001.04.122.0002.2.028.3.3.90.39.00 | I106: 12 - SECRETARIA DE ESPORTE, RECREAÇÃO E LAZER | J106: 001-GABINETE DA SECRETARIA DE ESPORTE, RECREAÇÃO E LAZER | K106: 4-ADMINISTRAÇÃO | L106: 122-ADMINISTRAÇÃO GERAL | M106: 0002-Governo Inteligente, Aberto e Inovador​ | N106: 2.028-Disseminação de Atividades Culturais e Esportivas Decentralizadas | O106: 3.3.90.39.00-OUTROS SERVIÇOS DE TERCEIROS - PESSOA JURÍDICA | R106: 1 | S106: Não tem o Cód. na LDO
A107: 12 | B107: 001 | C107: 27 | D107: 811 | E107: 0010 | F107: 2.031 | G107: 3.3.90.31.00 | H107: 12.001.27.811.0010.2.031.3.3.90.31.00 | I107: 12 - SECRETARIA DE ESPORTE, RECREAÇÃO E LAZER | J107: 001-GABINETE DA SECRETARIA DE ESPORTE, RECREAÇÃO E LAZER | K107: 27-DESPORTO E LAZER | L107: 811-DESPORTO DE RENDIMENTO | M107: 0010-Esporte, Lazer e Bem-Estar​ | N107: 2.031-Esporte Amador | O107: 3.3.90.31.00-PREMIAÇÕES CULTURAIS, ARTÍSTICAS, CIENTÍFICAS, DESPORTIVAS E OUTRAS | P107: PREMIAÇÕES CULTURAIS, ARTÍSTICAS, CIENTÍFICAS, DESPORTIVAS E OUTRAS | R107: 150000 | S107: Não tem o Cód. na LDO
A108: 12 | B108: 001 | C108: 27 | D108: 812 | E108: 0010 | F108: 2.032 | G108: 3.3.90.36.00 | H108: 12.001.27.812.0010.2.032.3.3.90.36.00 | I108: 12 - SECRETARIA DE ESPORTE, RECREAÇÃO E LAZER | J108: 001-GABINETE DA SECRETARIA DE ESPORTE, RECREAÇÃO E LAZER | K108: 27-DESPORTO E LAZER | L108: 812-DESPORTO COMUNITÁRIO | M108: 0010-Esporte, Lazer e Bem-Estar​ | N108: 2.032-Iniciação Esportiva | O108: 3.3.90.36.00-OUTROS SERVIÇOS DE TERCEIROS - PESSOA FÍSICA | P108: SERVIÇOS TÉCNICOS PROFISSIONAIS | R108: 1972800 | S108: Não tem o Cód. na LDO
A109: 12 | B109: 001 | C109: 27 | D109: 812 | E109: 0010 | F109: 2.030 | G109: 3.3.90.39.00 | H109: 12.001.27.812.0010.2.030.3.3.90.39.00 | I109: 12 - SECRETARIA DE ESPORTE, RECREAÇÃO E LAZER | J109: 001-GABINETE DA SECRETARIA DE ESPORTE, RECREAÇÃO E LAZER | K109: 27-DESPORTO E LAZER | L109: 812-DESPORTO COMUNITÁRIO | M109: 0010-Esporte, Lazer e Bem-Estar​ | N109: 2.030-Apoio ao Esporte de Alto Rendimento | O109: 3.3.90.39.00-OUTROS SERVIÇOS DE TERCEIROS - PESSOA JURÍDICA | P109: FORNECIMENTO DE ALIMENTAÇÃO | R109: 120000 | S109: Não tem o Cód. na LDO
A110: 12 | B110: 001 | C110: 27 | D110: 812 | E110: 0010 | F110: 2.006 | G110: 3.3.90.39.00 | H110: 12.001.27.812.0010.2.006.3.3.90.39.00 | I110: 12 - SECRETARIA DE ESPORTE, RECREAÇÃO E LAZER | J110: 001-GABINETE DA SECRETARIA DE ESPORTE, RECREAÇÃO E LAZER | K110: 27-DESPORTO E LAZER | L110: 812-DESPORTO COMUNITÁRIO | M110: 0010-Esporte, Lazer e Bem-Estar​ | N110: 2.006-Representações Oficiais | O110: 3.3.90.39.00-OUTROS SERVIÇOS DE TERCEIROS - PESSOA JURÍDICA | P110: HOSPEDAGENS | R110: 60000 | S110: Não tem o Cód. na LDO
A111: 12 | B111: 001 | C111: 27 | D111: 812 | E111: 0001 | F111: 2.032 | G111: 3.3.90.39.00 | H111: 12.001.27.812.0001.2.032.3.3.90.39.00 | I111: 12 - SECRETARIA DE ESPORTE, RECREAÇÃO E LAZER | J111: 001-GABINETE DA SECRETARIA DE ESPORTE, RECREAÇÃO E LAZER | K111: 27-DESPORTO E LAZER | L111: 812-DESPORTO COMUNITÁRIO | M111: 0001-Administração e Coordenação Geral​ | N111: 2.032-Iniciação Esportiva | O111: 3.3.90.39.00-OUTROS SERVIÇOS DE TERCEIROS - PESSOA JURÍDICA | P111: SERVIÇOS TÉCNICOS PROFISSIONAIS | R111: 100000 | S111: Não tem o Cód. na LDO
A112: 13 | B112: 001 | C112: 04 | D112: 122 | E112: 0001 | F112: 2.003 | G112: 3.3.90.36.00 | H112: 13.001.04.122.0001.2.003.3.3.90.36.00 | I112: 13 - SECRETARIA DE HABITAÇÃO | J112: 001-GABINETE DA SECRETARIA DE HABITAÇÃO | K112: 4-ADMINISTRAÇÃO | L112: 122-ADMINISTRAÇÃO GERAL | M112: 0001-Administração e Coordenação Geral​ | N112: 2.003-Qualificação de Servidores e Processos Institucionais | O112: 3.3.90.36.00-OUTROS SERVIÇOS DE TERCEIROS - PESSOA FÍSICA | Q112: - | R112: 2000 | S112: Não tem o Cód. na LDO
A113: 13 | B113: 001 | C113: 04 | D113: 122 | E113: 0001 | F113: 2.003 | G113: 3.3.90.39.00 | H113: 13.001.04.122.0001.2.003.3.3.90.39.00 | I113: 13 - SECRETARIA DE HABITAÇÃO | J113: 001-GABINETE DA SECRETARIA DE HABITAÇÃO | K113: 4-ADMINISTRAÇÃO | L113: 122-ADMINISTRAÇÃO GERAL | M113: 0001-Administração e Coordenação Geral​ | N113: 2.003-Qualificação de Servidores e Processos Institucionais | O113: 3.3.90.39.00-OUTROS SERVIÇOS DE TERCEIROS - PESSOA JURÍDICA | P113: OUTROS SERVIÇOS DE TERCEIROS - PESSOA JURÍDICA | Q113: - | R113: 30000 | S113: Não tem o Cód. na LDO
A114: 13 | B114: 001 | C114: 04 | D114: 122 | E114: 0001 | F114: 2.005 | G114: 3.3.90.93.00 | H114: 13.001.04.122.0001.2.005.3.3.90.93.00 | I114: 13 - SECRETARIA DE HABITAÇÃO | J114: 001-GABINETE DA SECRETARIA DE HABITAÇÃO | K114: 4-ADMINISTRAÇÃO | L114: 122-ADMINISTRAÇÃO GERAL | M114: 0001-Administração e Coordenação Geral​ | N114: 2.005-Promoção de Eventos, Comunicação e Participação Social | O114: 3.3.90.93.00-INDENIZAÇÕES E RESTITUIÇÕES | P114: DIVERSAS INDENIZAÇÕES E RESTITUIÇÕES | Q114: - | R114: 1000 | S114: Não tem o Cód. na LDO
A115: 13 | B115: 001 | C115: 04 | D115: 122 | E115: 0001 | F115: 2.005 | G115: 3.3.90.93.00 | H115: 13.001.04.122.0001.2.005.3.3.90.93.00 | I115: 13 - SECRETARIA DE HABITAÇÃO | J115: 001-GABINETE DA SECRETARIA DE HABITAÇÃO | K115: 4-ADMINISTRAÇÃO | L115: 122-ADMINISTRAÇÃO GERAL | M115: 0001-Administração e Coordenação Geral​ | N115: 2.005-Promoção de Eventos, Comunicação e Participação Social | O115: 3.3.90.93.00-INDENIZAÇÕES E RESTITUIÇÕES | P115: INDENIZAÇÕES | Q115: - | R115: 5000 | S115: Não tem o Cód. na LDO
...
